Workbook

Sheet Start
A1: Owner Builder in a Box: Owner Workbook
A2: Your whole owner-build in one spreadsheet. Works offline in Excel, Numbers, LibreOffice or Google Sheets (offline mode).
A3: Includes Guides and common Q&A for tracking your project efficiently
A4: How it works
A5: Colours | B5: White cells are for you. Grey cells are calculated and locked so they can't be typed over by accident (Review > Unprotect sheet if you need to; there's no password). Pale yellow rows are examples: delete them when you're ready (the Dashboard counts what's left).
A6: Start here | B6: 1. Fill in the Project tab. 2. Set your budgets on Packages. 3. Work through Compliance and Gateways from G0. 4. Log everything else as it happens.
A7: Files | B7: Documents live in Google Drive, not in the workbook. Register each one on the Documents tab: it builds a Doc ID (e.g. 02-DWG-012), the file name to use, and the Drive folder to save it in. Paste the Drive link once it's uploaded. Share documents, photos and tender documents with trades and others as needed. (recommend to use suggested naming conventions for files)
A8: Offline | B8: Excel / Numbers / LibreOffice: open this file and work. With Google Drive / Dropbox / Onedrive for desktop the project folder is on your computer too, so you can save files offline and they sync later. Google Sheets: turn on Drive > Settings > Offline, or in the Sheets app tap ⋮ > Make available offline. The Apps Script menu needs a connection.
A9: Folder links | B9: The Open links work with Google Drive, Dropbox, OneDrive or SharePoint: paste each folder's link (Share > Copy link) into the Google Drive Map tab. Working offline on a computer, paste the local folder path instead and it opens without internet.
A10: Google Sheets fast set-up | B10: Upload this file to Drive, open it, then File > Save as Google Sheets. Then Extensions > Apps Script, paste in Code.gs, save and reload. A new Owner Builder menu appears: Set up Drive folders creates the folder tree for this build and links every folder path in the workbook.
A11: Need more rows? | B11: Each tab has room for hundreds of entries. If you run out, unprotect the sheet and copy the last row down so the formulas come too. The Dashboard warns if anything is typed below the last formula row.
A12: Tabs
A13: Dashboard | B13: Current gateway, money, compliance progress and everything that needs attention.
A14: Project | B14: Address, title, owners, budget, permits, site classification.
A15: Guides / Q&A / Reference | B15: Buying guides, plain-English answers and key numbers from Owner Builder in a Box. Read-only.
A16: Gate Review | B16: G0 to G7: progress against entry, deliverables and exit checks, with your Go / Hold / Stop decision.
A17: Gateways | B17: Every entry criterion, deliverable and exit check for each gate.
A18: Compliance | B18: The 11-stage Victorian owner-builder checklist, with the folder to file the evidence in.
A19: Risks | B19: Starter risk register with likelihood × impact ratings.
A20: Google Drive Map | B20: The folder tree, what goes in each folder, the file naming rules, and the folder links.
A21: Rooms | B21: Room sizes give floor area, paint area, skirting length and tile quantities. Area type keeps garages and outdoor areas out of the paint and skirting figures.
A22: Selections | B22: Every product decision: spec, supplier, price, status.
A23: Diary | B23: Site diary, plan notes, instructions to trades, defects, questions for the building surveyor.
A24: Photos | B24: Log of site photos, especially before anything is covered.
... A31: Settings | B31: The legal thresholds and rules behind the checks (deposit caps, contract, warranty and consent thresholds, warning days). Update them here when the law changes.
A32: Important
A33: Not advice | B33: General information only. It is not legal, financial or building advice. Always confirm current requirements with the Building and Plumbing Commission (BPC), your relevant building surveyor, your council and WorkSafe Victoria. Victorian rules checked September 2026.

Sheet Dashboard
A1: Dashboard
A2: Where the build is up to. Everything here is calculated; change the other tabs, not this one.
A4: Project
A5: Project | B5: =IF(Project!$B$5="","(name it on the Project tab)",Project!$B$5)
A6: Current gateway | B6: =Project!$B$12&" "&IFERROR(INDEX('Gate Review'!$B$4:$B$11,MATCH(Project!$B$12,'Gate Review'!$A$4:$A$11,0)),"")
A7: Exit checks done at this gate | B7: =IFERROR(INDEX('Gate Review'!$H$4:$H$11,MATCH(Project!$B$12,'Gate Review'!$A$4:$A$11,0)),"")
A8: Ready to pass? | B8: =IFERROR(INDEX('Gate Review'!$I$4:$I$11,MATCH(Project!$B$12,'Gate Review'!$A$4:$A$11,0)),"")
A10: Money
A11: Total budget | B11: =N(Project!$B$16)
A12: Contingency in the budget | B12: =B11*N(Project!$B$17)
A13: Allocated to packages | B13: =SUM('Packages'!$H$4:$H$33) | F13: Sum of Packages budgets. Should be about the total budget less contingency.
A14: Committed (contracts + approved variations) | B14: =SUM('Packages'!$K$4:$K$33)
A15: Committed as % of package budgets | B15: =IF(B13=0,"",B14/B13) | F15: G3 exit check: compare with the target on Settings before going to site.
A16: G3 target | B16: =Settings!$B$14
A17: Spent to date (paid) | B17: =SUMIFS('Payments'!$F$4:$F$303,'Payments'!$K$4:$K$303,"Yes")
A18: Budget used | B18: =IF(B11=0,"",B17/B11)
A19: Forecast final cost | B19: =SUM('Packages'!$N$4:$N$33)
A20: Forecast under / (over) total budget | B20: =B11-B19
A21: Selections total | B21: =SUM('Selections'!$I$4:$I$153)
A23: Takeoffs (Rooms tab)
A24: Internal floor area (m²) | B24: =SUMIFS('Rooms'!$G$4:$G$63,'Rooms'!$C$4:$C$63,"<>Garage",'Rooms'!$C$4:$C$63,"<>External") | F24: Blank area type counts as internal.
A25: Garage floor area (m²) | B25: =SUMIFS('Rooms'!$G$4:$G$63,'Rooms'!$C$4:$C$63,"Garage")
A26: External areas (m²) | B26: =SUMIFS('Rooms'!$G$4:$G$63,'Rooms'!$C$4:$C$63,"External") | F26: Driveways, paving, decks.
A27: Wall paint, one coat (m²) | B27: =SUM('Rooms'!$I$4:$I$63)
A28: Skirting (m) | B28: =SUM('Rooms'!$H$4:$H$63)
A29: Floor covering incl. waste (m²) | B29: =SUM('Rooms'!$J$4:$J$63)
A31: Compliance by stage | B31: Items | C31: N/A | D31: Done | E31: % done
A32: 1. Eligibility | B32: =COUNTIFS('Compliance'!$B$4:$B$79,$A32) | C32: =COUNTIFS('Compliance'!$B$4:$B$79,$A32,'Compliance'!$G$4:$G$79,"N/A") | D32: =COUNTIFS('Compliance'!$B$4:$B$79,$A32,'Compliance'!$G$4:$G$79,"Done") | E32: =IF(B32-C32=0,"",D32/(B32-C32))
A33: 2. Certificate of consent | B33: =COUNTIFS('Compliance'!$B$4:$B$79,$A33) | C33: =COUNTIFS('Compliance'!$B$4:$B$79,$A33,'Compliance'!$G$4:$G$79,"N/A") | D33: =COUNTIFS('Compliance'!$B$4:$B$79,$A33,'Compliance'!$G$4:$G$79,"Done") | E33: =IF(B33-C33=0,"",D33/(B33-C33))
A34: 3. Site, planning & design | B34: =COUNTIFS('Compliance'!$B$4:$B$79,$A34) | C34: =COUNTIFS('Compliance'!$B$4:$B$79,$A34,'Compliance'!$G$4:$G$79,"N/A") | D34: =COUNTIFS('Compliance'!$B$4:$B$79,$A34,'Compliance'!$G$4:$G$79,"Done") | E34: =IF(B34-C34=0,"",D34/(B34-C34))
A35: 4. Building permit & pre-start | B35: =COUNTIFS('Compliance'!$B$4:$B$79,$A35) | C35: =COUNTIFS('Compliance'!$B$4:$B$79,$A35,'Compliance'!$G$4:$G$79,"N/A") | D35: =COUNTIFS('Compliance'!$B$4:$B$79,$A35,'Compliance'!$G$4:$G$79,"Done") | E35: =IF(B35-C35=0,"",D35/(B35-C35))
A36: 5. Health & safety (WorkSafe Victoria) | B36: =COUNTIFS('Compliance'!$B$4:$B$79,$A36) | C36: =COUNTIFS('Compliance'!$B$4:$B$79,$A36,'Compliance'!$G$4:$G$79,"N/A") | D36: =COUNTIFS('Compliance'!$B$4:$B$79,$A36,'Compliance'!$G$4:$G$79,"Done") | E36: =IF(B36-C36=0,"",D36/(B36-C36))
A37: 6. Insurance | B37: =COUNTIFS('Compliance'!$B$4:$B$79,$A37) | C37: =COUNTIFS('Compliance'!$B$4:$B$79,$A37,'Compliance'!$G$4:$G$79,"N/A") | D37: =COUNTIFS('Compliance'!$B$4:$B$79,$A37,'Compliance'!$G$4:$G$79,"Done") | E37: =IF(B37-C37=0,"",D37/(B37-C37))
A38: 7. Engaging trades | B38: =COUNTIFS('Compliance'!$B$4:$B$79,$A38) | C38: =COUNTIFS('Compliance'!$B$4:$B$79,$A38,'Compliance'!$G$4:$G$79,"N/A") | D38: =COUNTIFS('Compliance'!$B$4:$B$79,$A38,'Compliance'!$G$4:$G$79,"Done") | E38: =IF(B38-C38=0,"",D38/(B38-C38))
A39: 8. During construction | B39: =COUNTIFS('Compliance'!$B$4:$B$79,$A39) | C39: =COUNTIFS('Compliance'!$B$4:$B$79,$A39,'Compliance'!$G$4:$G$79,"N/A") | D39: =COUNTIFS('Compliance'!$B$4:$B$79,$A39,'Compliance'!$G$4:$G$79,"Done") | E39: =IF(B39-C39=0,"",D39/(B39-C39))
A40: 9. Completion & occupancy | B40: =COUNTIFS('Compliance'!$B$4:$B$79,$A40) | C40: =COUNTIFS('Compliance'!$B$4:$B$79,$A40,'Compliance'!$G$4:$G$79,"N/A") | D40: =COUNTIFS('Compliance'!$B$4:$B$79,$A40,'Compliance'!$G$4:$G$79,"Done") | E40: =IF(B40-C40=0,"",D40/(B40-C40))
A41: 10. Records & selling | B41: =COUNTIFS('Compliance'!$B$4:$B$79,$A41) | C41: =COUNTIFS('Compliance'!$B$4:$B$79,$A41,'Compliance'!$G$4:$G$79,"N/A") | D41: =COUNTIFS('Compliance'!$B$4:$B$79,$A41,'Compliance'!$G$4:$G$79,"Done") | E41: =IF(B41-C41=0,"",D41/(B41-C41))
A42: 11. Finance & tax | B42: =COUNTIFS('Compliance'!$B$4:$B$79,$A42) | C42: =COUNTIFS('Compliance'!$B$4:$B$79,$A42,'Compliance'!$G$4:$G$79,"N/A") | D42: =COUNTIFS('Compliance'!$B$4:$B$79,$A42,'Compliance'!$G$4:$G$79,"Done") | E42: =IF(B42-C42=0,"",D42/(B42-C42))
A43: All stages | B43: =SUM(B32:B42) | C43: =SUM(C32:C42) | D43: =SUM(D32:D42) | E43: =IF(B43-C43=0,"",D43/(B43-C43))
A45: Needs attention | B45: Count
A46: Entries past the pre-filled rows (not counted!) | B46: =COUNTA('Gateways'!$A$115:$J$1114)+COUNTA('Compliance'!$A$80:$M$1079)+COUNTA('Rooms'!$A$64:$N$1063)+COUNTA('Selections'!$A$154:$O$1153)+COUNTA('Diary'!$A$304:$L$1303)+COUNTA('Photos'!$A$304:$I$1303)+COUNTA('Documents'!$A$304:$T$1303)+COUNTA('Packages'!$A$34:$T$1033)+COUNTA('Trades'!$A$104:$AA$1103)+COUNTA('Tenders'!$A$104:$AF$1103)+COUNTA('Variations'!$A$154:$L$1153)+COUNTA('Payments'!$A$304:$O$1303)+COUNTA('Certificates'!$A$52:$M$1051)+COUNTA('Risks'!$A$64:$K$1063) | F46: Something was typed below the last formula row. Unprotect the sheet and copy the last row down to extend it.
A47: Go decisions with exit checks open | B47: =COUNTIF('Gate Review'!$K$4:$K$11,"?*") | F47: Gate Review tab
A48: Earlier gates without a Go decision | B48: =SUMPRODUCT(('Gate Review'!$A$4:$A$11<Project!$B$12)*('Gate Review'!$J$4:$J$11<>"Go")) | F48: Gates before the current gateway on the Project tab.
A49: Certificate of consent needed, no number recorded | B49: =IF(AND(N(Project!$B$16)>Settings!$B$9,Project!$B$20=""),1,0) | F49: Budget is over the consent threshold on Settings.
A50: Principal contractor needed, not done | B50: =IF(AND(N(Project!$B$16)>=Settings!$B$10,COUNTIFS('Compliance'!$A$4:$A$79,"oh-pc",'Compliance'!$G$4:$G$79,"Done")=0),1,0) | F50: Budget is at or over the principal contractor threshold (Compliance oh-pc).
A51: Trade paperwork expired | B51: =COUNTIF('Trades'!$W$4:$W$103,"Expired") | F51: Trades tab: licence or insurance past its expiry date.
A52: Trade paperwork expiring soon | B52: =COUNTIF('Trades'!$W$4:$W$103,"Expires*") | F52: Ask for new certificates of currency now.
A53: Trade dates typed as text or missing | B53: =COUNTIF('Trades'!$W$4:$W$103,"Check date*")+COUNTIF('Trades'!$W$4:$W$103,"Missing*") | F53: A date typed as text can't be checked for expiry.
A54: Trade contract checks to look at | B54: =COUNTIF('Trades'!$X$4:$X$103,"?*") | F54: Trades tab: duplicates, registration and home warranty.
A55: Deposits over the statutory cap | B55: =COUNTIF('Trades'!$V$4:$V$103,"Over statutory cap") | F55: Caps and threshold are on Settings.
A56: Quotes needing a look | B56: =COUNTIF('Tenders'!$AC$4:$AC$103,"?*") | F56: Tenders tab: Check column.
A57: Tender packages tied for 1st | B57: =COUNTIF('Tender Setup'!$K$4:$K$33,"Tie*") | F57: Tender Setup tab
A58: Documents with problems | B58: =COUNTIF('Documents'!$R$4:$R$303,"?*") | F58: Documents tab: Check column.
A59: Packages with naming problems | B59: =COUNTIF('Packages'!$Q$4:$Q$33,"?*") | F59: Packages tab: names must start with their No.
A60: Rooms with sizes typed as text | B60: =COUNTIF('Rooms'!$L$4:$L$63,"?*")
A61: Invoices charging GST from unregistered trades | B61: =COUNTIF('Payments'!$I$4:$I$303,"GST charged, not registered")
A62: Unpaid invoices | B62: =COUNTIFS('Payments'!$F$4:$F$303,">0",'Payments'!$K$4:$K$303,"<>Yes")
A63: Open defects | B63: =COUNTIFS('Diary'!$B$4:$B$303,"Defect",'Diary'!$J$4:$J$303,"<>Yes") | F63: Diary tab
A64: Open questions for the building surveyor | B64: =COUNTIFS('Diary'!$B$4:$B$303,"Question for RBS",'Diary'!$J$4:$J$303,"<>Yes") | F64: Diary tab
A65: Pending variations | B65: =COUNTIF('Variations'!$I$4:$I$153,"Pending") | F65: Don't let work start before the price is agreed.
A66: Selections still to choose | B66: =COUNTIF('Selections'!$J$4:$J$153,"To choose") | F66: All selections must be locked before G6.
A67: Packages forecast over budget | B67: =COUNTIF('Packages'!$P$4:$P$33,"Over budget") | F67: By more than the margin on Settings.
A68: Tender weights that don't add to 100 | B68: =SUMPRODUCT(('Tender Setup'!$A$4:$A$33<>"")*('Tender Setup'!$I$4:$I$33<>100)) | F68: Tender Setup tab
A69: Must-have certificates not yet passed | B69: =COUNTIFS('Certificates'!$G$4:$G$51,"Must",'Certificates'!$J$4:$J$51,"<>Pass") | F69: Certificates tab. Needed before the final inspection.
A70: High risks still open | B70: =COUNTIFS('Risks'!$F$4:$F$63,"High",'Risks'!$I$4:$I$63,"<>Closed")
A71: Duplicate Doc IDs | B71: =SUMPRODUCT(('Documents'!$F$4:$F$303<>"")*(COUNTIF('Documents'!$F$4:$F$303,'Documents'!$F$4:$F$303)>1)) | F71: Documents tab: rows sharing a Doc ID. Should be 0.
A72: Example rows still in the workbook | B72: =COUNTIF('Rooms'!$N$4:$N$63,"EXAMPLE: delete this row")+COUNTIF('Selections'!$O$4:$O$153,"EXAMPLE: delete this row")+COUNTIF('Diary'!$L$4:$L$303,"EXAMPLE: delete this row")+COUNTIF('Photos'!$I$4:$I$303,"EXAMPLE: delete this row")+COUNTIF('Documents'!$T$4:$T$303,"EXAMPLE: delete this row")+COUNTIF('Trades'!$AA$4:$AA$103,"EXAMPLE: delete this row")+COUNTIF('Tenders'!$AF$4:$AF$103,"EXAMPLE: delete this row")+COUNTIF('Payments'!$O$4:$O$303,"EXAMPLE: delete this row") | F72: Delete them once you've seen how each tab works.

Sheet Project
A1: Project
A2: The basics, always at hand. Yellow cells are yours to fill in.
A4: Project | C4: Notes
A5: Project name
A6: Site address
A7: Lot / plan of subdivision
A8: Title volume / folio
A9: Owner-builder(s)
A10: Phone
A11: Email
A12: Current gateway | B12: G0
A13: Target start
A14: Target finish
A15: Money
A16: Total budget inc GST ($)
A17: Contingency (%) | B17: 0.12 | C17: 10–15% is typical. Owner-builders often underestimate site works, services and finishes.
A18: Lender
A19: Approvals
A20: Certificate of consent no.
A21: Relevant building surveyor
A22: Building permit no.
A23: Planning permit no. (if any)
A24: Site & design
A25: Soil classification (AS 2870)
A26: Wind classification
A27: BAL rating (if bushfire prone)
A28: Energy rating (stars)
A29: Google Drive
A30: Project folder link | C30: Paste your project folder link (any provider), or let Owner Builder > Set up Drive folders fill it in Google Sheets.

Sheet Q&A
A1: Owner-builder Q&A (Victoria)
A2: Plain-English answers, grouped by topic. Read-only. General information, checked September 2026, not legal advice.
A3: Topic | B3: Question | C3: Answer
A4: Getting started | B4: What is an owner-builder? | C4: An owner-builder is a landowner who takes legal responsibility for domestic building work on their own land, instead of engaging a registered builder to manage the whole job. You take on the builder's responsibilities: quality, compliance, safety, and coordinating and paying trades. You can do some work yourself and hire trades for the rest.
A5: Getting started | B5: Do I have to do the building work myself? | C5: No. Most owner-builders act as project manager and engage trades for most of the work. You can do the non-licensed work yourself if you're capable, such as some carpentry, painting or landscaping. Plumbing, gasfitting and electrical work must always be done by licensed practitioners.
A6: Getting started | B6: How much can I really save? | C6: A builder's margin and overheads are commonly 15–25% of the build cost. Realistic owner-builder savings are often 10–20% after allowing for your time, mistakes, higher finance costs and missed trade discounts. Savings come from managing well, not just from cutting out the builder.
A7: Getting started | B7: How long does an owner-build take? | C7: Plan on 18–24 months from idea to occupancy for a typical new home. That's roughly 6–11 months of design, approvals and procurement, then 9–13 months on site. Owner-builders working part-time usually take longer. See the gateways program.
A8: Getting started | B8: What skills do I need? | C8: Organisation matters more than trade skills. You'll be reading plans, scheduling, negotiating, checking quality, managing money and paperwork, and keeping people safe. If you run projects or a household budget well, you're most of the way there. Owner Builder in a Box fills in the rest.
A9: Eligibility & certificate of consent | B9: When do I need a certificate of consent? | C9: When the value of the domestic building work is over $20,000 (it was $16,000 before 1 July 2026). Value means labour plus materials plus GST, including a market value for your own labour. Below that you can owner-build without consent, but you still need any building permit the work requires.
A10: Eligibility & certificate of consent | B10: Who is eligible? | C10: • You own the land, or you're a director of the owning company or a beneficiary of the owning trust • The work is for a single dwelling (or ancillary to it) • You live in it, or intend to (not required for a small second dwelling) • You're not in the business of building • No owner-builder permit in the past 5 years (with exceptions) • You've passed the BPC eLearning assessment and done construction induction training See the eligibility checklist.
A11: Eligibility & certificate of consent | B11: What is the eLearning assessment? | C11: A free online course and assessment run by the Building and Plumbing Commission. It covers your legal responsibilities, safety, contracts and the building process, and takes about 2–3 hours. You need a pass before applying for consent.
A12: Eligibility & certificate of consent | B12: Can I owner-build again within five years? | C12: Generally not on a different property. The exceptions are further work on the same home, building a small second dwelling, or an exemption granted by the BPC for special circumstances such as a substantial change in circumstances or hardship.
A13: Eligibility & certificate of consent | B13: Can I owner-build if my partner and I own the land together? | C13: Yes. Each owner-builder named needs to meet the requirements. The five-year rule also looks at people you co-own, or have co-owned, property with, so check both your histories.
A14: Eligibility & certificate of consent | B14: Can I owner-build a house to sell or rent out? | C14: Owner-builder consent is for a home you live in or intend to live in, apart from a small second dwelling. Building to sell or rent can put you "in the business of building", which requires registration.
... A42: Selling & after completion | B42: Am I liable for defects after I finish? | C42: If you sell, the buyer can rely on statutory warranties for owner-builder work for a period, and the insurance scheme backs claims. In practice that's why the defects report and insurance exist. Build it right, document it, and fix issues before sale.

Sheet Guides
A1: Buying guides & specs
A2: Stage-by-stage: the standards that apply, the spec to confirm and what to ask suppliers. Read-only. Content checked September 2026.
A3: Stage | B3: Topic | C3: Standards | D3: Spec to confirm | E3: Ask the supplier / trade
A4: Base stage | B4: Concrete footings & slab | C4: AS 2870 (residential slabs & footings), AS 3600 (concrete structures). | D4: • Spec to confirm with your engineer: slab type (waffle or raft), concrete strength (typically N20–N32 MPa), slump, mesh (e.g. SL82), bar sizes, edge beam depths, cover to steel. • Vapour barrier: 0.2 mm polyethylene, lapped and taped. Check the energy report for slab-edge insulation. • Termite management to AS 3660.1: physical barrier or chemical. Get the certificate and durable notice. | E4: Is pump hire included? What's the allowance for over-dig and extra concrete? Who books the pre-pour inspection? Will you give me delivery dockets showing MPa?
A5: Base stage | B5: Site drainage & stormwater | D5: • Pipe class and diameter per the engineer's drainage plan (commonly 90 mm and 100 mm PVC). • Rainwater tank size if your energy or water compliance relies on it (often 2,000 L or more connected to toilets or laundry). • Connection to the legal point of discharge. Your plumber lodges a compliance certificate.
A6: Frame & roof | B6: Wall frames & roof trusses | C6: AS 1684 (timber framing), AS 4440 (nail-plated trusses), NASH standard for light steel. | D6: • Timber grade: MGP10 / MGP12 pine is standard. Use H2 treated in termite zones, or light-gauge steel. • Wind classification (e.g. N2, N3) from your engineer. It drives tie-downs and bracing. • Get the frame & truss layout, design certificate and bracing plan with the delivery. | E6: Is it pre-cut or prefabricated? Are lintels, beams and bracing included? What's the lead time? Do you set out the trusses on site?
A7: Frame & roof | B7: Roofing: metal or tiles | C7: AS 1562.1 (metal roofing), AS 2050 (tiles), AS 3959 (bushfire). | D7: • Metal: 0.42 mm BMT is standard. Choose the colour's solar absorptance to match the energy report. • Anticon or sarking blanket for thermal and condensation control (NCC 2022 condensation rules). • Gutter overflow provisions and downpipe spacing per AS/NZS 3500.3. • BAL-rated ember guards and screens if you're in a bushfire prone area.
A8: Lock-up | B8: Windows & external doors | C8: AS 2047 (windows), AS 1288 (glass selection), AS 3959 (BAL). | D8: • Use the U-value and SHGC in your energy report. They are part of your 7-star compliance and must be matched. • Double glazing in thermally broken or uPVC frames is typical for 7-star compliance in Victoria. • Wind rating to match the site's wind class. BAL rating if required. • Keep the WERS label and AS 2047 certificate for your building surveyor. | E8: Do these U-value and SHGC figures match my energy report? What's the lead time? Are flashings and reveals included? Is there a warranty on hardware and seals?
A9: Lock-up | B9: Wall wrap, cladding & bricks | D9: • Vapour-permeable wall wrap (NCC 2022 condensation provisions). Check its class against the specification. • Bricks: order about 5% extra from the same batch to avoid colour variation. Check wall ties and weep holes. • Fibre cement, timber or metal cladding: fix it to the manufacturer's installation guide. Warranties depend on it.
A10: Services | B10: Insulation | D10: Standard: AS/NZS 4859.1. Values come from your energy report. • Typical Victorian 7-star: ceiling around R6.0, external walls around R2.5, plus underfloor if the floor is suspended. • Photograph every wall before plaster. The building surveyor may ask for an installation certificate.
A11: Services | B11: Hot water, heating & all-electric homes | D11: • New Victorian homes that need a planning permit (applied for from 1 January 2024) can't connect to reticulated gas. All-electric is the default choice anyway. • A heat-pump hot water system scores well in the NCC 2022 whole-of-home energy budget. • Reverse-cycle split or ducted systems: check the energy rating, zoning and the refrigerant licence (ARCtick) of the installer. • Solar PV: use a Solar Accreditation Australia (formerly CEC) accredited installer if you want rebates. Check Solar Victoria.
A12: Services | B12: Electrical: switchboard, lighting, smoke alarms | C12: AS/NZS 3000 (wiring rules), AS 3786 (smoke alarms). | D12: • RCD (safety switch) protection on all final sub-circuits. • Hardwired, interconnected smoke alarms in the locations the NCC requires. • Plan the points before rough-in: walk every room in My Build and note GPOs, switches, data and TV. • Think ahead: an EV charger circuit, induction cooktop capacity, battery-ready switchboard.
A13: Services | B13: Plumbing fixtures & tapware | D13: • Only buy WaterMark-certified products. Plumbers can refuse to install anything else, and it may not pass inspection. • Check WELS water ratings (star rating and litres per minute). • Hot water to bathrooms must be delivered at a maximum of 50°C (tempering or thermostatic valve per AS/NZS 3500.4).
A14: Fit-out | B14: Wet areas: waterproofing & tiles | D14: Standard: AS 3740 (waterproofing of domestic wet areas). • Get a waterproofing certificate for every wet area. The building surveyor needs it. • Slip resistance: use P3 or better for wet-area floors and P4–P5 for outdoor areas (AS 4586). • Order about 10% extra tiles from one batch (15% for diagonal or herringbone). My Build's room calculator does this for you.
A15: Fit-out | B15: Kitchen, benchtops & joinery | D15: • Engineered stone is banned in Australia from 1 July 2024. Consider porcelain, sintered stone, natural stone, laminate or timber. • Board: E0 / E1 low-formaldehyde, moisture-resistant under sinks. • Sign off shop drawings. Check the appliance cut-out sizes and ventilation clearances first. • Appliances: use the Energy Rating label, and check the cooktop's electrical load with your electrician.
A16: Fit-out | B16: Paint, flooring & finishes | D16: • Low-VOC, washable paints for living areas. Mould-resistant paint for wet areas. Record the colour codes in My Build. • Flooring: acclimatise timber before laying. Check the moisture content of the slab. • Keep every product's warranty registration and care guide for the handover file.
A17: How to buy | B17: Getting trade pricing as an owner-builder | D17: • Open trade accounts with your building permit and certificate of consent. Many suppliers give owner-builders a builder's discount. • Bundle orders by stage (e.g. all frame hardware together) and ask for a project price. • Compare supply-only prices against supply & install quotes using the tender tool.
A18: How to buy | B18: Deliveries, storage & checking goods | D18: • Time deliveries to the program. Early deliveries get stolen or damaged; late ones stop trades. • Check quantities and condition on arrival and note damage on the docket before you sign it. • Store off the ground, covered and secure. Photograph deliveries for insurance. • Keep every docket and invoice against its trade package in your budget.

Sheet Reference
A1: Reference
A2: Key numbers, contract types, tendering and who does what. Read-only.
A3: Key numbers
A4: Rule | B4: Figure | C4: Where it comes from
A5: Certificate of consent required | B5: Work over $20,000 (was $16,000 before 1 July 2026) | C5: Building Act 1993, BPC
A6: Owner-builder permit frequency | B6: 1 every 5 years (exemptions apply) | C6: Building Act s25E, BPC
A7: Major domestic building contract / registered builder | B7: Work over $10,000 (proposed increase to $20,000) | C7: Domestic Building Contracts Act 1995
A8: Principal contractor (OHS) | B8: Projects of $350,000 or more | C8: OHS Regulations 2017
A9: Selling: defects report & insurance | B9: Within 6 yrs 6 mths of completion. Report ≤ 6 months old | C9: Building Act s137B
A10: Energy efficiency (new homes) | B10: 7-star NatHERS + whole-of-home | C10: NCC 2022, Victoria from 1 May 2024
A11: Building permit levy | B11: Work over $10,000 | C11: Building Act, collected by the RBS
A13: Contract types
A14: Type | B14: How it's priced | C14: Best for | D14: Watch out for
A15: Lump sum (fixed price) | B15: One price for a defined scope | C15: Well-documented packages: slab, roof, electrical | D15: Vague scope means variations. Exclusions hide cost.
A16: Schedule of rates | B16: $ per m², per point, per 1,000 bricks | C16: Measurable work: bricks, plaster, tiles | D16: You carry the quantity risk. Measure it yourself.
A17: Labour only | B17: Labour price; you supply the materials | C17: Carpentry, fixing, painting | D17: You carry material risk and waste. Deliveries must be on time.
A18: Supply only | B18: Materials delivered | C18: Frames, trusses, windows, appliances | D18: Check against the plans. Delivery dates. Damage on delivery.
A19: Supply & install | B19: Materials + labour | C19: Roofing, insulation, cabinetry | D19: Confirm the spec and brand. Warranty covers both parts.
A20: Cost plus / do & charge | B20: Actual cost + margin or hourly rate | C20: Small unknowns, repairs, excavation in rock | D20: No price certainty. Cap it and require daily dockets.
A22: What goes in an RFQ pack
A23: What goes in an RFQ pack
A24: Cover letter: package, address, closing date, contact
A25: Scope of works + inclusions list
A26: Drawings & specification (with revision numbers)
A27: Engineering & energy report extracts
A28: Program: target start and duration
A29: Site info: access, power, water, slope, photos
A30: Your draft trade agreement (see Contracts)
A31: Pricing schedule so every quote breaks down the same way
A32: What to return: licence, insurance, ABN, SWMS, references
A34: Levelling: making quotes comparable
... A62: Who does what (RACI)
A63: Activity | B63: You (owner-builder) | C63: Designer / engineer | D63: Building surveyor | E63: Trades | F63: Lender
A64: Design brief & scope | B64: A/R | C64: C | D64: I | E64: – | F64: I
A65: Working drawings & engineering | B65: A | C65: R | D65: C | E65: – | F65: I
A66: Certificate of consent | B66: A/R | C66: – | D66: I | E66: – | F66: I
A67: Building permit | B67: A | C67: C | D67: R | E67: – | F67: I
A68: Tendering & contracts | B68: A/R | C68: C | D68: – | E68: C | F68: I
A69: Site safety & coordination | B69: A/R | C69: – | D69: – | E69: R (own work) | F69: –
A70: Mandatory inspections | B70: A (notify) | C70: C | D70: R | E70: C | F70: I
A71: Trade workmanship & certificates | B71: A | C71: – | D71: C | E71: R | F71: –
A72: Progress claims & payments | B72: A/R | C72: – | D72: – | E72: C | F72: R (drawdown)
A73: Occupancy permit | B73: A | C73: – | D73: R | E73: C | F73: I

Sheet Gate Review
A1: Gate review
A2: At each gate decide Go, Hold or Stop. A gate is ready when every exit check on the Gateways tab is Yes.
A3: Gate | B3: Name | C3: Purpose | D3: Entry criteria met | E3: Deliverables done | F3: Exit checks | G3: Exit checks done | H3: Exit % | I3: Ready to pass? | J3: Decision | K3: Decision check | L3: Decision date | M3: Decision guide | N3: Typical budget spent | O3: Typical duration | P3: Notes
A4: G0 | B4: Feasibility & eligibility | C4: Can I, should I, and can I afford to owner-build? | D4: =COUNTIFS('Gateways'!$A$4:$A$114,A4,'Gateways'!$C$4:$C$114,"Entry criteria",'Gateways'!$E$4:$E$114,"Yes")&" of "&COUNTIFS('Gateways'!$A$4:$A$114,A4,'Gateways'!$C$4:$C$114,"Entry criteria") | E4: =COUNTIFS('Gateways'!$A$4:$A$114,A4,'Gateways'!$C$4:$C$114,"Deliverable",'Gateways'!$E$4:$E$114,"Yes")&" of "&COUNTIFS('Gateways'!$A$4:$A$114,A4,'Gateways'!$C$4:$C$114,"Deliverable") | F4: =COUNTIFS('Gateways'!$A$4:$A$114,A4,'Gateways'!$C$4:$C$114,"Exit check") | G4: =COUNTIFS('Gateways'!$A$4:$A$114,A4,'Gateways'!$C$4:$C$114,"Exit check",'Gateways'!$E$4:$E$114,"Yes") | H4: =IF(F4=0,"",G4/F4) | I4: =IF(F4=0,"",IF(G4=F4,"Ready","Not yet")) | K4: =IF(AND(J4="Go",I4<>"Ready"),"Go recorded, exit checks open","") | M4: Go to concept, or Stop and consider a builder or part-build instead. | N4: ~0–1% | O4: 1–3 months (with G1)
A5: G1 | B5: Concept & budget | C5: Lock the brief, the concept and the money. | D5: =COUNTIFS('Gateways'!$A$4:$A$114,A5,'Gateways'!$C$4:$C$114,"Entry criteria",'Gateways'!$E$4:$E$114,"Yes")&" of "&COUNTIFS('Gateways'!$A$4:$A$114,A5,'Gateways'!$C$4:$C$114,"Entry criteria") | E5: =COUNTIFS('Gateways'!$A$4:$A$114,A5,'Gateways'!$C$4:$C$114,"Deliverable",'Gateways'!$E$4:$E$114,"Yes")&" of "&COUNTIFS('Gateways'!$A$4:$A$114,A5,'Gateways'!$C$4:$C$114,"Deliverable") | F5: =COUNTIFS('Gateways'!$A$4:$A$114,A5,'Gateways'!$C$4:$C$114,"Exit check") | G5: =COUNTIFS('Gateways'!$A$4:$A$114,A5,'Gateways'!$C$4:$C$114,"Exit check",'Gateways'!$E$4:$E$114,"Yes") | H5: =IF(F5=0,"",G5/F5) | I5: =IF(F5=0,"",IF(G5=F5,"Ready","Not yet")) | K5: =IF(AND(J5="Go",I5<>"Ready"),"Go recorded, exit checks open","") | M5: Go to detailed design, or Hold and value-manage the concept. | N5: ~2–3% | O5: 1–3 months (with G0)
A6: G2 | B6: Design & approvals | C6: Everything you need for a building permit. | D6: =COUNTIFS('Gateways'!$A$4:$A$114,A6,'Gateways'!$C$4:$C$114,"Entry criteria",'Gateways'!$E$4:$E$114,"Yes")&" of "&COUNTIFS('Gateways'!$A$4:$A$114,A6,'Gateways'!$C$4:$C$114,"Entry criteria") | E6: =COUNTIFS('Gateways'!$A$4:$A$114,A6,'Gateways'!$C$4:$C$114,"Deliverable",'Gateways'!$E$4:$E$114,"Yes")&" of "&COUNTIFS('Gateways'!$A$4:$A$114,A6,'Gateways'!$C$4:$C$114,"Deliverable") | F6: =COUNTIFS('Gateways'!$A$4:$A$114,A6,'Gateways'!$C$4:$C$114,"Exit check") | G6: =COUNTIFS('Gateways'!$A$4:$A$114,A6,'Gateways'!$C$4:$C$114,"Exit check",'Gateways'!$E$4:$E$114,"Yes") | H6: =IF(F6=0,"",G6/F6) | I6: =IF(F6=0,"",IF(G6=F6,"Ready","Not yet")) | K6: =IF(AND(J6="Go",I6<>"Ready"),"Go recorded, exit checks open","") | M6: Go to procurement, or Hold for design changes. | N6: ~5% | O6: 2–6 months
A7: G3 | B7: Procurement & permit | C7: Right trades, right price, right paperwork. Ready to start. | D7: =COUNTIFS('Gateways'!$A$4:$A$114,A7,'Gateways'!$C$4:$C$114,"Entry criteria",'Gateways'!$E$4:$E$114,"Yes")&" of "&COUNTIFS('Gateways'!$A$4:$A$114,A7,'Gateways'!$C$4:$C$114,"Entry criteria") | E7: =COUNTIFS('Gateways'!$A$4:$A$114,A7,'Gateways'!$C$4:$C$114,"Deliverable",'Gateways'!$E$4:$E$114,"Yes")&" of "&COUNTIFS('Gateways'!$A$4:$A$114,A7,'Gateways'!$C$4:$C$114,"Deliverable") | F7: =COUNTIFS('Gateways'!$A$4:$A$114,A7,'Gateways'!$C$4:$C$114,"Exit check") | G7: =COUNTIFS('Gateways'!$A$4:$A$114,A7,'Gateways'!$C$4:$C$114,"Exit check",'Gateways'!$E$4:$E$114,"Yes") | H7: =IF(F7=0,"",G7/F7) | I7: =IF(F7=0,"",IF(G7=F7,"Ready","Not yet")) | K7: =IF(AND(J7="Go",I7<>"Ready"),"Go recorded, exit checks open","") | M7: Go to site, or Hold until the price and paperwork are right. | N7: ~8% | O7: 1–2 months
A8: G4 | B8: Site works & base | C8: Out of the ground: set-out, services, footings and slab. | D8: =COUNTIFS('Gateways'!$A$4:$A$114,A8,'Gateways'!$C$4:$C$114,"Entry criteria",'Gateways'!$E$4:$E$114,"Yes")&" of "&COUNTIFS('Gateways'!$A$4:$A$114,A8,'Gateways'!$C$4:$C$114,"Entry criteria") | E8: =COUNTIFS('Gateways'!$A$4:$A$114,A8,'Gateways'!$C$4:$C$114,"Deliverable",'Gateways'!$E$4:$E$114,"Yes")&" of "&COUNTIFS('Gateways'!$A$4:$A$114,A8,'Gateways'!$C$4:$C$114,"Deliverable") | F8: =COUNTIFS('Gateways'!$A$4:$A$114,A8,'Gateways'!$C$4:$C$114,"Exit check") | G8: =COUNTIFS('Gateways'!$A$4:$A$114,A8,'Gateways'!$C$4:$C$114,"Exit check",'Gateways'!$E$4:$E$114,"Yes") | H8: =IF(F8=0,"",G8/F8) | I8: =IF(F8=0,"",IF(G8=F8,"Ready","Not yet")) | K8: =IF(AND(J8="Go",I8<>"Ready"),"Go recorded, exit checks open","") | M8: Go to frame. | N8: ~15–20% | O8: 4–8 weeks
A9: G5 | B9: Frame & lock-up | C9: Structure, roof, windows and doors. Weather-tight and secure. | D9: =COUNTIFS('Gateways'!$A$4:$A$114,A9,'Gateways'!$C$4:$C$114,"Entry criteria",'Gateways'!$E$4:$E$114,"Yes")&" of "&COUNTIFS('Gateways'!$A$4:$A$114,A9,'Gateways'!$C$4:$C$114,"Entry criteria") | E9: =COUNTIFS('Gateways'!$A$4:$A$114,A9,'Gateways'!$C$4:$C$114,"Deliverable",'Gateways'!$E$4:$E$114,"Yes")&" of "&COUNTIFS('Gateways'!$A$4:$A$114,A9,'Gateways'!$C$4:$C$114,"Deliverable") | F9: =COUNTIFS('Gateways'!$A$4:$A$114,A9,'Gateways'!$C$4:$C$114,"Exit check") | G9: =COUNTIFS('Gateways'!$A$4:$A$114,A9,'Gateways'!$C$4:$C$114,"Exit check",'Gateways'!$E$4:$E$114,"Yes") | H9: =IF(F9=0,"",G9/F9) | I9: =IF(F9=0,"",IF(G9=F9,"Ready","Not yet")) | K9: =IF(AND(J9="Go",I9<>"Ready"),"Go recorded, exit checks open","") | M9: Go to fit-out. | N9: ~45–55% | O9: 8–12 weeks
A10: G6 | B10: Fit-out & fixing | C10: Plaster to paint, wet areas, kitchen, fit-off. | D10: =COUNTIFS('Gateways'!$A$4:$A$114,A10,'Gateways'!$C$4:$C$114,"Entry criteria",'Gateways'!$E$4:$E$114,"Yes")&" of "&COUNTIFS('Gateways'!$A$4:$A$114,A10,'Gateways'!$C$4:$C$114,"Entry criteria") | E10: =COUNTIFS('Gateways'!$A$4:$A$114,A10,'Gateways'!$C$4:$C$114,"Deliverable",'Gateways'!$E$4:$E$114,"Yes")&" of "&COUNTIFS('Gateways'!$A$4:$A$114,A10,'Gateways'!$C$4:$C$114,"Deliverable") | F10: =COUNTIFS('Gateways'!$A$4:$A$114,A10,'Gateways'!$C$4:$C$114,"Exit check") | G10: =COUNTIFS('Gateways'!$A$4:$A$114,A10,'Gateways'!$C$4:$C$114,"Exit check",'Gateways'!$E$4:$E$114,"Yes") | H10: =IF(F10=0,"",G10/F10) | I10: =IF(F10=0,"",IF(G10=F10,"Ready","Not yet")) | K10: =IF(AND(J10="Go",I10<>"Ready"),"Go recorded, exit checks open","") | M10: Go to final. | N10: ~85–90% | O10: 12–20 weeks
A11: G7 | B11: Completion & handover | C11: Occupancy, close-out and your handover file. | D11: =COUNTIFS('Gateways'!$A$4:$A$114,A11,'Gateways'!$C$4:$C$114,"Entry criteria",'Gateways'!$E$4:$E$114,"Yes")&" of "&COUNTIFS('Gateways'!$A$4:$A$114,A11,'Gateways'!$C$4:$C$114,"Entry criteria") | E11: =COUNTIFS('Gateways'!$A$4:$A$114,A11,'Gateways'!$C$4:$C$114,"Deliverable",'Gateways'!$E$4:$E$114,"Yes")&" of "&COUNTIFS('Gateways'!$A$4:$A$114,A11,'Gateways'!$C$4:$C$114,"Deliverable") | F11: =COUNTIFS('Gateways'!$A$4:$A$114,A11,'Gateways'!$C$4:$C$114,"Exit check") | G11: =COUNTIFS('Gateways'!$A$4:$A$114,A11,'Gateways'!$C$4:$C$114,"Exit check",'Gateways'!$E$4:$E$114,"Yes") | H11: =IF(F11=0,"",G11/F11) | I11: =IF(F11=0,"",IF(G11=F11,"Ready","Not yet")) | K11: =IF(AND(J11="Go",I11<>"Ready"),"Go recorded, exit checks open","") | M11: Close the project. Welcome home. | N11: 100% | O11: 2–6 weeks

Sheet Gateways
A1: Gateways G0 to G7
A2: Tick each entry criterion, deliverable and exit check as it's met. A gate is ready to pass when every exit check is Yes (see Gate Review).
A3: Gate | B3: Gate name | C3: Type | D3: Item | E3: Done? | F3: Date | G3: Evidence Doc ID | H3: Drive folder (suggested) | I3: Folder | J3: Notes
A4: G0 | B4: Feasibility & eligibility | C4: Entry criteria | D4: You own, or are buying, the land | I4: =IF(H4="","",IF(IFERROR(INDEX('Google Drive Map'!$G$4:$G$33,MATCH(H4,'Google Drive Map'!$B$4:$B$33,0))&"","")="","",HYPERLINK(INDEX('Google Drive Map'!$G$4:$G$33,MATCH(H4,'Google Drive Map'!$B$4:$B$33,0)),"Open")))
A5: G0 | B5: Feasibility & eligibility | C5: Entry criteria | D5: You have a rough idea of the home you want | I5: =IF(H5="","",IF(IFERROR(INDEX('Google Drive Map'!$G$4:$G$33,MATCH(H5,'Google Drive Map'!$B$4:$B$33,0))&"","")="","",HYPERLINK(INDEX('Google Drive Map'!$G$4:$G$33,MATCH(H5,'Google Drive Map'!$B$4:$B$33,0)),"Open")))
A6: G0 | B6: Feasibility & eligibility | C6: Entry criteria | D6: You know how much time you can commit each week | I6: =IF(H6="","",IF(IFERROR(INDEX('Google Drive Map'!$G$4:$G$33,MATCH(H6,'Google Drive Map'!$B$4:$B$33,0))&"","")="","",HYPERLINK(INDEX('Google Drive Map'!$G$4:$G$33,MATCH(H6,'Google Drive Map'!$B$4:$B$33,0)),"Open")))
A7: G0 | B7: Feasibility & eligibility | C7: Deliverable | D7: Eligibility self-check (s25E) | H7: 01 Eligibility, Land & Planning | I7: =IF(H7="","",IF(IFERROR(INDEX('Google Drive Map'!$G$4:$G$33,MATCH(H7,'Google Drive Map'!$B$4:$B$33,0))&"","")="","",HYPERLINK(INDEX('Google Drive Map'!$G$4:$G$33,MATCH(H7,'Google Drive Map'!$B$4:$B$33,0)),"Open")))
A8: G0 | B8: Feasibility & eligibility | C8: Deliverable | D8: Title, zoning & overlay review | H8: 01 Eligibility, Land & Planning | I8: =IF(H8="","",IF(IFERROR(INDEX('Google Drive Map'!$G$4:$G$33,MATCH(H8,'Google Drive Map'!$B$4:$B$33,0))&"","")="","",HYPERLINK(INDEX('Google Drive Map'!$G$4:$G$33,MATCH(H8,'Google Drive Map'!$B$4:$B$33,0)),"Open")))
A9: G0 | B9: Feasibility & eligibility | C9: Deliverable | D9: Order-of-magnitude budget ($/m² × area) | H9: 03 Permits, Insurance & Finance | I9: =IF(H9="","",IF(IFERROR(INDEX('Google Drive Map'!$G$4:$G$33,MATCH(H9,'Google Drive Map'!$B$4:$B$33,0))&"","")="","",HYPERLINK(INDEX('Google Drive Map'!$G$4:$G$33,MATCH(H9,'Google Drive Map'!$B$4:$B$33,0)),"Open")))
A10: G0 | B10: Feasibility & eligibility | C10: Deliverable | D10: Finance conversation with an owner-builder-friendly lender | H10: 03 Permits, Insurance & Finance | I10: =IF(H10="","",IF(IFERROR(INDEX('Google Drive Map'!$G$4:$G$33,MATCH(H10,'Google Drive Map'!$B$4:$B$33,0))&"","")="","",HYPERLINK(INDEX('Google Drive Map'!$G$4:$G$33,MATCH(H10,'Google Drive Map'!$B$4:$B$33,0)),"Open")))
A11: G0 | B11: Feasibility & eligibility | C11: Deliverable | D11: Honest skills & time assessment | H11: 00 Project Register | I11: =IF(H11="","",IF(IFERROR(INDEX('Google Drive Map'!$G$4:$G$33,MATCH(H11,'Google Drive Map'!$B$4:$B$33,0))&"","")="","",HYPERLINK(INDEX('Google Drive Map'!$G$4:$G$33,MATCH(H11,'Google Drive Map'!$B$4:$B$33,0)),"Open")))
A12: G0 | B12: Feasibility & eligibility | C12: Exit check | D12: Eligible, or exemption pathway known | I12: =IF(H12="","",IF(IFERROR(INDEX('Google Drive Map'!$G$4:$G$33,MATCH(H12,'Google Drive Map'!$B$4:$B$33,0))&"","")="","",HYPERLINK(INDEX('Google Drive Map'!$G$4:$G$33,MATCH(H12,'Google Drive Map'!$B$4:$B$33,0)),"Open")))
A13: G0 | B13: Feasibility & eligibility | C13: Exit check | D13: No title or planning showstoppers | I13: =IF(H13="","",IF(IFERROR(INDEX('Google Drive Map'!$G$4:$G$33,MATCH(H13,'Google Drive Map'!$B$4:$B$33,0))&"","")="","",HYPERLINK(INDEX('Google Drive Map'!$G$4:$G$33,MATCH(H13,'Google Drive Map'!$B$4:$B$33,0)),"Open")))
A14: G0 | B14: Feasibility & eligibility | C14: Exit check | D14: Budget and finance roughly align | I14: =IF(H14="","",IF(IFERROR(INDEX('Google Drive Map'!$G$4:$G$33,MATCH(H14,'Google Drive Map'!$B$4:$B$33,0))&"","")="","",HYPERLINK(INDEX('Google Drive Map'!$G$4:$G$33,MATCH(H14,'Google Drive Map'!$B$4:$B$33,0)),"Open")))
A15: G0 | B15: Feasibility & eligibility | C15: Exit check | D15: Household agrees on time, stress and risk | I15: =IF(H15="","",IF(IFERROR(INDEX('Google Drive Map'!$G$4:$G$33,MATCH(H15,'Google Drive Map'!$B$4:$B$33,0))&"","")="","",HYPERLINK(INDEX('Google Drive Map'!$G$4:$G$33,MATCH(H15,'Google Drive Map'!$B$4:$B$33,0)),"Open")))
A16: G1 | B16: Concept & budget | C16: Entry criteria | D16: G0 passed | I16: =IF(H16="","",IF(IFERROR(INDEX('Google Drive Map'!$G$4:$G$33,MATCH(H16,'Google Drive Map'!$B$4:$B$33,0))&"","")="","",HYPERLINK(INDEX('Google Drive Map'!$G$4:$G$33,MATCH(H16,'Google Drive Map'!$B$4:$B$33,0)),"Open")))
A17: G1 | B17: Concept & budget | C17: Entry criteria | D17: Designer or architect engaged | I17: =IF(H17="","",IF(IFERROR(INDEX('Google Drive Map'!$G$4:$G$33,MATCH(H17,'Google Drive Map'!$B$4:$B$33,0))&"","")="","",HYPERLINK(INDEX('Google Drive Map'!$G$4:$G$33,MATCH(H17,'Google Drive Map'!$B$4:$B$33,0)),"Open")))
A18: G1 | B18: Concept & budget | C18: Entry criteria | D18: Feature & level survey and soil test ordered | I18: =IF(H18="","",IF(IFERROR(INDEX('Google Drive Map'!$G$4:$G$33,MATCH(H18,'Google Drive Map'!$B$4:$B$33,0))&"","")="","",HYPERLINK(INDEX('Google Drive Map'!$G$4:$G$33,MATCH(H18,'Google Drive Map'!$B$4:$B$33,0)),"Open")))
A19: G1 | B19: Concept & budget | C19: Deliverable | D19: Written design brief (rooms, sizes, must-haves, nice-to-haves) | H19: 02 Design & Engineering | I19: =IF(H19="","",IF(IFERROR(INDEX('Google Drive Map'!$G$4:$G$33,MATCH(H19,'Google Drive Map'!$B$4:$B$33,0))&"","")="","",HYPERLINK(INDEX('Google Drive Map'!$G$4:$G$33,MATCH(H19,'Google Drive Map'!$B$4:$B$33,0)),"Open")))
A20: G1 | B20: Concept & budget | C20: Deliverable | D20: Concept plans & room schedule in My Build | H20: 02 Design & Engineering | I20: =IF(H20="","",IF(IFERROR(INDEX('Google Drive Map'!$G$4:$G$33,MATCH(H20,'Google Drive Map'!$B$4:$B$33,0))&"","")="","",HYPERLINK(INDEX('Google Drive Map'!$G$4:$G$33,MATCH(H20,'Google Drive Map'!$B$4:$B$33,0)),"Open")))
A21: G1 | B21: Concept & budget | C21: Deliverable | D21: Elemental cost plan with 10–15% contingency | H21: 03 Permits, Insurance & Finance | I21: =IF(H21="","",IF(IFERROR(INDEX('Google Drive Map'!$G$4:$G$33,MATCH(H21,'Google Drive Map'!$B$4:$B$33,0))&"","")="","",HYPERLINK(INDEX('Google Drive Map'!$G$4:$G$33,MATCH(H21,'Google Drive Map'!$B$4:$B$33,0)),"Open")))
A22: G1 | B22: Concept & budget | C22: Deliverable | D22: Finance pre-approval | H22: 03 Permits, Insurance & Finance | I22: =IF(H22="","",IF(IFERROR(INDEX('Google Drive Map'!$G$4:$G$33,MATCH(H22,'Google Drive Map'!$B$4:$B$33,0))&"","")="","",HYPERLINK(INDEX('Google Drive Map'!$G$4:$G$33,MATCH(H22,'Google Drive Map'!$B$4:$B$33,0)),"Open")))
A23: G1 | B23: Concept & budget | C23: Deliverable | D23: Draft program (target start & finish) | H23: 00 Project Register | I23: =IF(H23="","",IF(IFERROR(INDEX('Google Drive Map'!$G$4:$G$33,MATCH(H23,'Google Drive Map'!$B$4:$B$33,0))&"","")="","",HYPERLINK(INDEX('Google Drive Map'!$G$4:$G$33,MATCH(H23,'Google Drive Map'!$B$4:$B$33,0)),"Open")))
A24: G1 | B24: Concept & budget | C24: Deliverable | D24: First risk register | H24: 00 Project Register | I24: =IF(H24="","",IF(IFERROR(INDEX('Google Drive Map'!$G$4:$G$33,MATCH(H24,'Google Drive Map'!$B$4:$B$33,0))&"","")="","",HYPERLINK(INDEX('Google Drive Map'!$G$4:$G$33,MATCH(H24,'Google Drive Map'!$B$4:$B$33,0)),"Open")))
A25: G1 | B25: Concept & budget | C25: Exit check | D25: Concept fits the budget, including contingency | I25: =IF(H25="","",IF(IFERROR(INDEX('Google Drive Map'!$G$4:$G$33,MATCH(H25,'Google Drive Map'!$B$4:$B$33,0))&"","")="","",HYPERLINK(INDEX('Google Drive Map'!$G$4:$G$33,MATCH(H25,'Google Drive Map'!$B$4:$B$33,0)),"Open")))
A26: G1 | B26: Concept & budget | C26: Exit check | D26: Concept fits the site (setbacks, overlays, fall, BAL) | I26: =IF(H26="","",IF(IFERROR(INDEX('Google Drive Map'!$G$4:$G$33,MATCH(H26,'Google Drive Map'!$B$4:$B$33,0))&"","")="","",HYPERLINK(INDEX('Google Drive Map'!$G$4:$G$33,MATCH(H26,'Google Drive Map'!$B$4:$B$33,0)),"Open")))
A27: G1 | B27: Concept & budget | C27: Exit check | D27: Scope frozen: changes after this cost money | I27: =IF(H27="","",IF(IFERROR(INDEX('Google Drive Map'!$G$4:$G$33,MATCH(H27,'Google Drive Map'!$B$4:$B$33,0))&"","")="","",HYPERLINK(INDEX('Google Drive Map'!$G$4:$G$33,MATCH(H27,'Google Drive Map'!$B$4:$B$33,0)),"Open")))
A28: G2 | B28: Design & approvals | C28: Entry criteria | D28: G1 passed, scope frozen | I28: =IF(H28="","",IF(IFERROR(INDEX('Google Drive Map'!$G$4:$G$33,MATCH(H28,'Google Drive Map'!$B$4:$B$33,0))&"","")="","",HYPERLINK(INDEX('Google Drive Map'!$G$4:$G$33,MATCH(H28,'Google Drive Map'!$B$4:$B$33,0)),"Open")))
A29: G2 | B29: Design & approvals | C29: Entry criteria | D29: Owner-builder eLearning & white card done | I29: =IF(H29="","",IF(IFERROR(INDEX('Google Drive Map'!$G$4:$G$33,MATCH(H29,'Google Drive Map'!$B$4:$B$33,0))&"","")="","",HYPERLINK(INDEX('Google Drive Map'!$G$4:$G$33,MATCH(H29,'Google Drive Map'!$B$4:$B$33,0)),"Open")))
A30: G2 | B30: Design & approvals | C30: Deliverable | D30: Working drawings & specification | H30: 02 Design & Engineering | I30: =IF(H30="","",IF(IFERROR(INDEX('Google Drive Map'!$G$4:$G$33,MATCH(H30,'Google Drive Map'!$B$4:$B$33,0))&"","")="","",HYPERLINK(INDEX('Google Drive Map'!$G$4:$G$33,MATCH(H30,'Google Drive Map'!$B$4:$B$33,0)),"Open")))
A31: G2 | B31: Design & approvals | C31: Deliverable | D31: Engineering: footings, slab, frame, drainage | H31: 02 Design & Engineering | I31: =IF(H31="","",IF(IFERROR(INDEX('Google Drive Map'!$G$4:$G$33,MATCH(H31,'Google Drive Map'!$B$4:$B$33,0))&"","")="","",HYPERLINK(INDEX('Google Drive Map'!$G$4:$G$33,MATCH(H31,'Google Drive Map'!$B$4:$B$33,0)),"Open")))
A32: G2 | B32: Design & approvals | C32: Deliverable | D32: 7-star energy report | H32: 02 Design & Engineering | I32: =IF(H32="","",IF(IFERROR(INDEX('Google Drive Map'!$G$4:$G$33,MATCH(H32,'Google Drive Map'!$B$4:$B$33,0))&"","")="","",HYPERLINK(INDEX('Google Drive Map'!$G$4:$G$33,MATCH(H32,'Google Drive Map'!$B$4:$B$33,0)),"Open")))
A33: G2 | B33: Design & approvals | C33: Deliverable | D33: BAL assessment (if bushfire prone) | H33: 02 Design & Engineering | I33: =IF(H33="","",IF(IFERROR(INDEX('Google Drive Map'!$G$4:$G$33,MATCH(H33,'Google Drive Map'!$B$4:$B$33,0))&"","")="","",HYPERLINK(INDEX('Google Drive Map'!$G$4:$G$33,MATCH(H33,'Google Drive Map'!$B$4:$B$33,0)),"Open")))
A34: G2 | B34: Design & approvals | C34: Deliverable | D34: Planning permit (if required) | H34: 01 Eligibility, Land & Planning | I34: =IF(H34="","",IF(IFERROR(INDEX('Google Drive Map'!$G$4:$G$33,MATCH(H34,'Google Drive Map'!$B$4:$B$33,0))&"","")="","",HYPERLINK(INDEX('Google Drive Map'!$G$4:$G$33,MATCH(H34,'Google Drive Map'!$B$4:$B$33,0)),"Open")))
A35: G2 | B35: Design & approvals | C35: Deliverable | D35: Certificate of consent from the BPC | H35: 01 Eligibility, Land & Planning | I35: =IF(H35="","",IF(IFERROR(INDEX('Google Drive Map'!$G$4:$G$33,MATCH(H35,'Google Drive Map'!$B$4:$B$33,0))&"","")="","",HYPERLINK(INDEX('Google Drive Map'!$G$4:$G$33,MATCH(H35,'Google Drive Map'!$B$4:$B$33,0)),"Open")))
A36: G2 | B36: Design & approvals | C36: Deliverable | D36: Legal point of discharge, easement consents | H36: 01 Eligibility, Land & Planning | I36: =IF(H36="","",IF(IFERROR(INDEX('Google Drive Map'!$G$4:$G$33,MATCH(H36,'Google Drive Map'!$B$4:$B$33,0))&"","")="","",HYPERLINK(INDEX('Google Drive Map'!$G$4:$G$33,MATCH(H36,'Google Drive Map'!$B$4:$B$33,0)),"Open")))
A37: G2 | B37: Design & approvals | C37: Exit check | D37: All documents consistent (drawings = engineering = energy) | I37: =IF(H37="","",IF(IFERROR(INDEX('Google Drive Map'!$G$4:$G$33,MATCH(H37,'Google Drive Map'!$B$4:$B$33,0))&"","")="","",HYPERLINK(INDEX('Google Drive Map'!$G$4:$G$33,MATCH(H37,'Google Drive Map'!$B$4:$B$33,0)),"Open")))
A38: G2 | B38: Design & approvals | C38: Exit check | D38: Certificate of consent issued | I38: =IF(H38="","",IF(IFERROR(INDEX('Google Drive Map'!$G$4:$G$33,MATCH(H38,'Google Drive Map'!$B$4:$B$33,0))&"","")="","",HYPERLINK(INDEX('Google Drive Map'!$G$4:$G$33,MATCH(H38,'Google Drive Map'!$B$4:$B$33,0)),"Open")))
A39: G2 | B39: Design & approvals | C39: Exit check | D39: RBS appointed and fee agreed | I39: =IF(H39="","",IF(IFERROR(INDEX('Google Drive Map'!$G$4:$G$33,MATCH(H39,'Google Drive Map'!$B$4:$B$33,0))&"","")="","",HYPERLINK(INDEX('Google Drive Map'!$G$4:$G$33,MATCH(H39,'Google Drive Map'!$B$4:$B$33,0)),"Open")))
A40: G2 | B40: Design & approvals | C40: Exit check | D40: Cost plan updated to the detailed design | I40: =IF(H40="","",IF(IFERROR(INDEX('Google Drive Map'!$G$4:$G$33,MATCH(H40,'Google Drive Map'!$B$4:$B$33,0))&"","")="","",HYPERLINK(INDEX('Google Drive Map'!$G$4:$G$33,MATCH(H40,'Google Drive Map'!$B$4:$B$33,0)),"Open")))
A41: G3 | B41: Procurement & permit | C41: Entry criteria | D41: G2 passed | I41: =IF(H41="","",IF(IFERROR(INDEX('Google Drive Map'!$G$4:$G$33,MATCH(H41,'Google Drive Map'!$B$4:$B$33,0))&"","")="","",HYPERLINK(INDEX('Google Drive Map'!$G$4:$G$33,MATCH(H41,'Google Drive Map'!$B$4:$B$33,0)),"Open")))
A42: G3 | B42: Procurement & permit | C42: Entry criteria | D42: Trade packages defined with a scope for each | I42: =IF(H42="","",IF(IFERROR(INDEX('Google Drive Map'!$G$4:$G$33,MATCH(H42,'Google Drive Map'!$B$4:$B$33,0))&"","")="","",HYPERLINK(INDEX('Google Drive Map'!$G$4:$G$33,MATCH(H42,'Google Drive Map'!$B$4:$B$33,0)),"Open")))
A43: G3 | B43: Procurement & permit | C43: Deliverable | D43: RFQ packs issued (3 quotes per package) | H43: 04 Trades & Tenders | I43: =IF(H43="","",IF(IFERROR(INDEX('Google Drive Map'!$G$4:$G$33,MATCH(H43,'Google Drive Map'!$B$4:$B$33,0))&"","")="","",HYPERLINK(INDEX('Google Drive Map'!$G$4:$G$33,MATCH(H43,'Google Drive Map'!$B$4:$B$33,0)),"Open")))
A44: G3 | B44: Procurement & permit | C44: Deliverable | D44: Tender comparison & recommendation per package (tool) | H44: 04 Trades & Tenders | I44: =IF(H44="","",IF(IFERROR(INDEX('Google Drive Map'!$G$4:$G$33,MATCH(H44,'Google Drive Map'!$B$4:$B$33,0))&"","")="","",HYPERLINK(INDEX('Google Drive Map'!$G$4:$G$33,MATCH(H44,'Google Drive Map'!$B$4:$B$33,0)),"Open")))
A45: G3 | B45: Procurement & permit | C45: Deliverable | D45: Signed trade contracts (guide) | H45: 04 Trades & Tenders | I45: =IF(H45="","",IF(IFERROR(INDEX('Google Drive Map'!$G$4:$G$33,MATCH(H45,'Google Drive Map'!$B$4:$B$33,0))&"","")="","",HYPERLINK(INDEX('Google Drive Map'!$G$4:$G$33,MATCH(H45,'Google Drive Map'!$B$4:$B$33,0)),"Open")))
A46: G3 | B46: Procurement & permit | C46: Deliverable | D46: Trade register: licences, insurance, SWMS | H46: 04 Trades & Tenders | I46: =IF(H46="","",IF(IFERROR(INDEX('Google Drive Map'!$G$4:$G$33,MATCH(H46,'Google Drive Map'!$B$4:$B$33,0))&"","")="","",HYPERLINK(INDEX('Google Drive Map'!$G$4:$G$33,MATCH(H46,'Google Drive Map'!$B$4:$B$33,0)),"Open")))
A47: G3 | B47: Procurement & permit | C47: Deliverable | D47: Building permit issued | H47: 03 Permits, Insurance & Finance | I47: =IF(H47="","",IF(IFERROR(INDEX('Google Drive Map'!$G$4:$G$33,MATCH(H47,'Google Drive Map'!$B$4:$B$33,0))&"","")="","",HYPERLINK(INDEX('Google Drive Map'!$G$4:$G$33,MATCH(H47,'Google Drive Map'!$B$4:$B$33,0)),"Open")))
A48: G3 | B48: Procurement & permit | C48: Deliverable | D48: Asset protection permit, insurances, site set-up plan | H48: 03 Permits, Insurance & Finance | I48: =IF(H48="","",IF(IFERROR(INDEX('Google Drive Map'!$G$4:$G$33,MATCH(H48,'Google Drive Map'!$B$4:$B$33,0))&"","")="","",HYPERLINK(INDEX('Google Drive Map'!$G$4:$G$33,MATCH(H48,'Google Drive Map'!$B$4:$B$33,0)),"Open")))
A49: G3 | B49: Procurement & permit | C49: Deliverable | D49: Baseline program & budget | H49: 03 Permits, Insurance & Finance | I49: =IF(H49="","",IF(IFERROR(INDEX('Google Drive Map'!$G$4:$G$33,MATCH(H49,'Google Drive Map'!$B$4:$B$33,0))&"","")="","",HYPERLINK(INDEX('Google Drive Map'!$G$4:$G$33,MATCH(H49,'Google Drive Map'!$B$4:$B$33,0)),"Open")))
A50: G3 | B50: Procurement & permit | C50: Exit check | D50: At least 80% of the budget is committed under contract or firm quote | I50: =IF(H50="","",IF(IFERROR(INDEX('Google Drive Map'!$G$4:$G$33,MATCH(H50,'Google Drive Map'!$B$4:$B$33,0))&"","")="","",HYPERLINK(INDEX('Google Drive Map'!$G$4:$G$33,MATCH(H50,'Google Drive Map'!$B$4:$B$33,0)),"Open")))
A51: G3 | B51: Procurement & permit | C51: Exit check | D51: Every early trade has compliant paperwork | I51: =IF(H51="","",IF(IFERROR(INDEX('Google Drive Map'!$G$4:$G$33,MATCH(H51,'Google Drive Map'!$B$4:$B$33,0))&"","")="","",HYPERLINK(INDEX('Google Drive Map'!$G$4:$G$33,MATCH(H51,'Google Drive Map'!$B$4:$B$33,0)),"Open")))
A52: G3 | B52: Procurement & permit | C52: Exit check | D52: Permit, consent & insurances in place | I52: =IF(H52="","",IF(IFERROR(INDEX('Google Drive Map'!$G$4:$G$33,MATCH(H52,'Google Drive Map'!$B$4:$B$33,0))&"","")="","",HYPERLINK(INDEX('Google Drive Map'!$G$4:$G$33,MATCH(H52,'Google Drive Map'!$B$4:$B$33,0)),"Open")))
A53: G3 | B53: Procurement & permit | C53: Exit check | D53: Finance drawdown schedule agreed with the lender | I53: =IF(H53="","",IF(IFERROR(INDEX('Google Drive Map'!$G$4:$G$33,MATCH(H53,'Google Drive Map'!$B$4:$B$33,0))&"","")="","",HYPERLINK(INDEX('Google Drive Map'!$G$4:$G$33,MATCH(H53,'Google Drive Map'!$B$4:$B$33,0)),"Open")))
A54: G4 | B54: Site works & base | C54: Entry criteria | D54: G3 passed | I54: =IF(H54="","",IF(IFERROR(INDEX('Google Drive Map'!$G$4:$G$33,MATCH(H54,'Google Drive Map'!$B$4:$B$33,0))&"","")="","",HYPERLINK(INDEX('Google Drive Map'!$G$4:$G$33,MATCH(H54,'Google Drive Map'!$B$4:$B$33,0)),"Open")))
A55: G4 | B55: Site works & base | C55: Entry criteria | D55: Before You Dig done, site fenced, sign up, toilet on site | I55: =IF(H55="","",IF(IFERROR(INDEX('Google Drive Map'!$G$4:$G$33,MATCH(H55,'Google Drive Map'!$B$4:$B$33,0))&"","")="","",HYPERLINK(INDEX('Google Drive Map'!$G$4:$G$33,MATCH(H55,'Google Drive Map'!$B$4:$B$33,0)),"Open")))
A56: G4 | B56: Site works & base | C56: Deliverable | D56: Surveyor set-out | H56: 02 Design & Engineering | I56: =IF(H56="","",IF(IFERROR(INDEX('Google Drive Map'!$G$4:$G$33,MATCH(H56,'Google Drive Map'!$B$4:$B$33,0))&"","")="","",HYPERLINK(INDEX('Google Drive Map'!$G$4:$G$33,MATCH(H56,'Google Drive Map'!$B$4:$B$33,0)),"Open")))
A57: G4 | B57: Site works & base | C57: Deliverable | D57: Site cut, drainage & underslab plumbing (PCC) | H57: 07 Inspections & Certificates | I57: =IF(H57="","",IF(IFERROR(INDEX('Google Drive Map'!$G$4:$G$33,MATCH(H57,'Google Drive Map'!$B$4:$B$33,0))&"","")="","",HYPERLINK(INDEX('Google Drive Map'!$G$4:$G$33,MATCH(H57,'Google Drive Map'!$B$4:$B$33,0)),"Open")))
A58: G4 | B58: Site works & base | C58: Deliverable | D58: Hold point: footing / pre-slab inspection | H58: 07 Inspections & Certificates | I58: =IF(H58="","",IF(IFERROR(INDEX('Google Drive Map'!$G$4:$G$33,MATCH(H58,'Google Drive Map'!$B$4:$B$33,0))&"","")="","",HYPERLINK(INDEX('Google Drive Map'!$G$4:$G$33,MATCH(H58,'Google Drive Map'!$B$4:$B$33,0)),"Open")))
A59: G4 | B59: Site works & base | C59: Deliverable | D59: Slab poured, termite management installed | H59: 00 Project Register | I59: =IF(H59="","",IF(IFERROR(INDEX('Google Drive Map'!$G$4:$G$33,MATCH(H59,'Google Drive Map'!$B$4:$B$33,0))&"","")="","",HYPERLINK(INDEX('Google Drive Map'!$G$4:$G$33,MATCH(H59,'Google Drive Map'!$B$4:$B$33,0)),"Open")))
A60: G4 | B60: Site works & base | C60: Deliverable | D60: Site diary & photos of everything before it's covered | H60: 06 Site Diary & Photos | I60: =IF(H60="","",IF(IFERROR(INDEX('Google Drive Map'!$G$4:$G$33,MATCH(H60,'Google Drive Map'!$B$4:$B$33,0))&"","")="","",HYPERLINK(INDEX('Google Drive Map'!$G$4:$G$33,MATCH(H60,'Google Drive Map'!$B$4:$B$33,0)),"Open")))
A61: G4 | B61: Site works & base | C61: Exit check | D61: RBS inspections passed and certificates filed | I61: =IF(H61="","",IF(IFERROR(INDEX('Google Drive Map'!$G$4:$G$33,MATCH(H61,'Google Drive Map'!$B$4:$B$33,0))&"","")="","",HYPERLINK(INDEX('Google Drive Map'!$G$4:$G$33,MATCH(H61,'Google Drive Map'!$B$4:$B$33,0)),"Open")))
A62: G4 | B62: Site works & base | C62: Exit check | D62: Engineer's sign-off (if required) | I62: =IF(H62="","",IF(IFERROR(INDEX('Google Drive Map'!$G$4:$G$33,MATCH(H62,'Google Drive Map'!$B$4:$B$33,0))&"","")="","",HYPERLINK(INDEX('Google Drive Map'!$G$4:$G$33,MATCH(H62,'Google Drive Map'!$B$4:$B$33,0)),"Open")))
A63: G4 | B63: Site works & base | C63: Exit check | D63: Cost to date within ±5% of the baseline | I63: =IF(H63="","",IF(IFERROR(INDEX('Google Drive Map'!$G$4:$G$33,MATCH(H63,'Google Drive Map'!$B$4:$B$33,0))&"","")="","",HYPERLINK(INDEX('Google Drive Map'!$G$4:$G$33,MATCH(H63,'Google Drive Map'!$B$4:$B$33,0)),"Open")))
A64: G5 | B64: Frame & lock-up | C64: Entry criteria | D64: G4 passed | I64: =IF(H64="","",IF(IFERROR(INDEX('Google Drive Map'!$G$4:$G$33,MATCH(H64,'Google Drive Map'!$B$4:$B$33,0))&"","")="","",HYPERLINK(INDEX('Google Drive Map'!$G$4:$G$33,MATCH(H64,'Google Drive Map'!$B$4:$B$33,0)),"Open")))
A65: G5 | B65: Frame & lock-up | C65: Entry criteria | D65: Frame, truss & window orders confirmed against the plans | I65: =IF(H65="","",IF(IFERROR(INDEX('Google Drive Map'!$G$4:$G$33,MATCH(H65,'Google Drive Map'!$B$4:$B$33,0))&"","")="","",HYPERLINK(INDEX('Google Drive Map'!$G$4:$G$33,MATCH(H65,'Google Drive Map'!$B$4:$B$33,0)),"Open")))
A66: G5 | B66: Frame & lock-up | C66: Deliverable | D66: Wall frames, trusses, bracing, tie-downs | H66: 02 Design & Engineering | I66: =IF(H66="","",IF(IFERROR(INDEX('Google Drive Map'!$G$4:$G$33,MATCH(H66,'Google Drive Map'!$B$4:$B$33,0))&"","")="","",HYPERLINK(INDEX('Google Drive Map'!$G$4:$G$33,MATCH(H66,'Google Drive Map'!$B$4:$B$33,0)),"Open")))
A67: G5 | B67: Frame & lock-up | C67: Deliverable | D67: Hold point: frame inspection (plus engineer if required) | H67: 07 Inspections & Certificates | I67: =IF(H67="","",IF(IFERROR(INDEX('Google Drive Map'!$G$4:$G$33,MATCH(H67,'Google Drive Map'!$B$4:$B$33,0))&"","")="","",HYPERLINK(INDEX('Google Drive Map'!$G$4:$G$33,MATCH(H67,'Google Drive Map'!$B$4:$B$33,0)),"Open")))
A68: G5 | B68: Frame & lock-up | C68: Deliverable | D68: Roof, gutters, fascia, sarking | H68: 00 Project Register | I68: =IF(H68="","",IF(IFERROR(INDEX('Google Drive Map'!$G$4:$G$33,MATCH(H68,'Google Drive Map'!$B$4:$B$33,0))&"","")="","",HYPERLINK(INDEX('Google Drive Map'!$G$4:$G$33,MATCH(H68,'Google Drive Map'!$B$4:$B$33,0)),"Open")))
A69: G5 | B69: Frame & lock-up | C69: Deliverable | D69: Windows & external doors, wrap, cladding | H69: 02 Design & Engineering | I69: =IF(H69="","",IF(IFERROR(INDEX('Google Drive Map'!$G$4:$G$33,MATCH(H69,'Google Drive Map'!$B$4:$B$33,0))&"","")="","",HYPERLINK(INDEX('Google Drive Map'!$G$4:$G$33,MATCH(H69,'Google Drive Map'!$B$4:$B$33,0)),"Open")))
A70: G5 | B70: Frame & lock-up | C70: Deliverable | D70: Services rough-in: plumbing, electrical, data, HVAC | H70: 00 Project Register | I70: =IF(H70="","",IF(IFERROR(INDEX('Google Drive Map'!$G$4:$G$33,MATCH(H70,'Google Drive Map'!$B$4:$B$33,0))&"","")="","",HYPERLINK(INDEX('Google Drive Map'!$G$4:$G$33,MATCH(H70,'Google Drive Map'!$B$4:$B$33,0)),"Open")))
A71: G5 | B71: Frame & lock-up | C71: Exit check | D71: Frame inspection passed | I71: =IF(H71="","",IF(IFERROR(INDEX('Google Drive Map'!$G$4:$G$33,MATCH(H71,'Google Drive Map'!$B$4:$B$33,0))&"","")="","",HYPERLINK(INDEX('Google Drive Map'!$G$4:$G$33,MATCH(H71,'Google Drive Map'!$B$4:$B$33,0)),"Open")))
A72: G5 | B72: Frame & lock-up | C72: Exit check | D72: Lock-up reached (lender progress draw) | I72: =IF(H72="","",IF(IFERROR(INDEX('Google Drive Map'!$G$4:$G$33,MATCH(H72,'Google Drive Map'!$B$4:$B$33,0))&"","")="","",HYPERLINK(INDEX('Google Drive Map'!$G$4:$G$33,MATCH(H72,'Google Drive Map'!$B$4:$B$33,0)),"Open")))
A73: G5 | B73: Frame & lock-up | C73: Exit check | D73: Rough-in certificates, insulation installed & photographed | I73: =IF(H73="","",IF(IFERROR(INDEX('Google Drive Map'!$G$4:$G$33,MATCH(H73,'Google Drive Map'!$B$4:$B$33,0))&"","")="","",HYPERLINK(INDEX('Google Drive Map'!$G$4:$G$33,MATCH(H73,'Google Drive Map'!$B$4:$B$33,0)),"Open")))
A74: G6 | B74: Fit-out & fixing | C74: Entry criteria | D74: G5 passed | I74: =IF(H74="","",IF(IFERROR(INDEX('Google Drive Map'!$G$4:$G$33,MATCH(H74,'Google Drive Map'!$B$4:$B$33,0))&"","")="","",HYPERLINK(INDEX('Google Drive Map'!$G$4:$G$33,MATCH(H74,'Google Drive Map'!$B$4:$B$33,0)),"Open")))
A75: G6 | B75: Fit-out & fixing | C75: Entry criteria | D75: All selections locked in My Build (tiles, taps, appliances, paint) | I75: =IF(H75="","",IF(IFERROR(INDEX('Google Drive Map'!$G$4:$G$33,MATCH(H75,'Google Drive Map'!$B$4:$B$33,0))&"","")="","",HYPERLINK(INDEX('Google Drive Map'!$G$4:$G$33,MATCH(H75,'Google Drive Map'!$B$4:$B$33,0)),"Open")))
A76: G6 | B76: Fit-out & fixing | C76: Deliverable | D76: Plaster, cornice, internal doors, architraves | H76: 00 Project Register | I76: =IF(H76="","",IF(IFERROR(INDEX('Google Drive Map'!$G$4:$G$33,MATCH(H76,'Google Drive Map'!$B$4:$B$33,0))&"","")="","",HYPERLINK(INDEX('Google Drive Map'!$G$4:$G$33,MATCH(H76,'Google Drive Map'!$B$4:$B$33,0)),"Open")))
A77: G6 | B77: Fit-out & fixing | C77: Deliverable | D77: Waterproofing (certificate) & tiling | H77: 07 Inspections & Certificates | I77: =IF(H77="","",IF(IFERROR(INDEX('Google Drive Map'!$G$4:$G$33,MATCH(H77,'Google Drive Map'!$B$4:$B$33,0))&"","")="","",HYPERLINK(INDEX('Google Drive Map'!$G$4:$G$33,MATCH(H77,'Google Drive Map'!$B$4:$B$33,0)),"Open")))
A78: G6 | B78: Fit-out & fixing | C78: Deliverable | D78: Cabinetry, benchtops, joinery | H78: 00 Project Register | I78: =IF(H78="","",IF(IFERROR(INDEX('Google Drive Map'!$G$4:$G$33,MATCH(H78,'Google Drive Map'!$B$4:$B$33,0))&"","")="","",HYPERLINK(INDEX('Google Drive Map'!$G$4:$G$33,MATCH(H78,'Google Drive Map'!$B$4:$B$33,0)),"Open")))
A79: G6 | B79: Fit-out & fixing | C79: Deliverable | D79: Painting | H79: 00 Project Register | I79: =IF(H79="","",IF(IFERROR(INDEX('Google Drive Map'!$G$4:$G$33,MATCH(H79,'Google Drive Map'!$B$4:$B$33,0))&"","")="","",HYPERLINK(INDEX('Google Drive Map'!$G$4:$G$33,MATCH(H79,'Google Drive Map'!$B$4:$B$33,0)),"Open")))
A80: G6 | B80: Fit-out & fixing | C80: Deliverable | D80: Plumbing & electrical fit-off (PCC & Certificate of Electrical Safety) | H80: 07 Inspections & Certificates | I80: =IF(H80="","",IF(IFERROR(INDEX('Google Drive Map'!$G$4:$G$33,MATCH(H80,'Google Drive Map'!$B$4:$B$33,0))&"","")="","",HYPERLINK(INDEX('Google Drive Map'!$G$4:$G$33,MATCH(H80,'Google Drive Map'!$B$4:$B$33,0)),"Open")))
A81: G6 | B81: Fit-out & fixing | C81: Deliverable | D81: Floor coverings | H81: 00 Project Register | I81: =IF(H81="","",IF(IFERROR(INDEX('Google Drive Map'!$G$4:$G$33,MATCH(H81,'Google Drive Map'!$B$4:$B$33,0))&"","")="","",HYPERLINK(INDEX('Google Drive Map'!$G$4:$G$33,MATCH(H81,'Google Drive Map'!$B$4:$B$33,0)),"Open")))
A82: G6 | B82: Fit-out & fixing | C82: Exit check | D82: All compliance certificates collected | I82: =IF(H82="","",IF(IFERROR(INDEX('Google Drive Map'!$G$4:$G$33,MATCH(H82,'Google Drive Map'!$B$4:$B$33,0))&"","")="","",HYPERLINK(INDEX('Google Drive Map'!$G$4:$G$33,MATCH(H82,'Google Drive Map'!$B$4:$B$33,0)),"Open")))
A83: G6 | B83: Fit-out & fixing | C83: Exit check | D83: Own defects walk-through done, list issued to trades | I83: =IF(H83="","",IF(IFERROR(INDEX('Google Drive Map'!$G$4:$G$33,MATCH(H83,'Google Drive Map'!$B$4:$B$33,0))&"","")="","",HYPERLINK(INDEX('Google Drive Map'!$G$4:$G$33,MATCH(H83,'Google Drive Map'!$B$4:$B$33,0)),"Open")))
A84: G6 | B84: Fit-out & fixing | C84: Exit check | D84: Budget forecast to complete is confirmed | I84: =IF(H84="","",IF(IFERROR(INDEX('Google Drive Map'!$G$4:$G$33,MATCH(H84,'Google Drive Map'!$B$4:$B$33,0))&"","")="","",HYPERLINK(INDEX('Google Drive Map'!$G$4:$G$33,MATCH(H84,'Google Drive Map'!$B$4:$B$33,0)),"Open")))
A85: G7 | B85: Completion & handover | C85: Entry criteria | D85: G6 passed | I85: =IF(H85="","",IF(IFERROR(INDEX('Google Drive Map'!$G$4:$G$33,MATCH(H85,'Google Drive Map'!$B$4:$B$33,0))&"","")="","",HYPERLINK(INDEX('Google Drive Map'!$G$4:$G$33,MATCH(H85,'Google Drive Map'!$B$4:$B$33,0)),"Open")))
A86: G7 | B86: Completion & handover | C86: Entry criteria | D86: Defects closed out, site cleaned | I86: =IF(H86="","",IF(IFERROR(INDEX('Google Drive Map'!$G$4:$G$33,MATCH(H86,'Google Drive Map'!$B$4:$B$33,0))&"","")="","",HYPERLINK(INDEX('Google Drive Map'!$G$4:$G$33,MATCH(H86,'Google Drive Map'!$B$4:$B$33,0)),"Open")))
A87: G7 | B87: Completion & handover | C87: Deliverable | D87: Hold point: final inspection | H87: 07 Inspections & Certificates | I87: =IF(H87="","",IF(IFERROR(INDEX('Google Drive Map'!$G$4:$G$33,MATCH(H87,'Google Drive Map'!$B$4:$B$33,0))&"","")="","",HYPERLINK(INDEX('Google Drive Map'!$G$4:$G$33,MATCH(H87,'Google Drive Map'!$B$4:$B$33,0)),"Open")))
A88: G7 | B88: Completion & handover | C88: Deliverable | D88: Occupancy permit / certificate of final inspection | H88: 08 Handover, Records & Sale | I88: =IF(H88="","",IF(IFERROR(INDEX('Google Drive Map'!$G$4:$G$33,MATCH(H88,'Google Drive Map'!$B$4:$B$33,0))&"","")="","",HYPERLINK(INDEX('Google Drive Map'!$G$4:$G$33,MATCH(H88,'Google Drive Map'!$B$4:$B$33,0)),"Open")))
A89: G7 | B89: Completion & handover | C89: Deliverable | D89: Utilities, driveway, landscaping, asset bond refund | H89: 03 Permits, Insurance & Finance | I89: =IF(H89="","",IF(IFERROR(INDEX('Google Drive Map'!$G$4:$G$33,MATCH(H89,'Google Drive Map'!$B$4:$B$33,0))&"","")="","",HYPERLINK(INDEX('Google Drive Map'!$G$4:$G$33,MATCH(H89,'Google Drive Map'!$B$4:$B$33,0)),"Open")))
A90: G7 | B90: Completion & handover | C90: Deliverable | D90: Handover file: permits, certificates, warranties, as-builts | H90: 08 Handover, Records & Sale | I90: =IF(H90="","",IF(IFERROR(INDEX('Google Drive Map'!$G$4:$G$33,MATCH(H90,'Google Drive Map'!$B$4:$B$33,0))&"","")="","",HYPERLINK(INDEX('Google Drive Map'!$G$4:$G$33,MATCH(H90,'Google Drive Map'!$B$4:$B$33,0)),"Open")))
A91: G7 | B91: Completion & handover | C91: Deliverable | D91: Final cost report & lessons learned | H91: 08 Handover, Records & Sale | I91: =IF(H91="","",IF(IFERROR(INDEX('Google Drive Map'!$G$4:$G$33,MATCH(H91,'Google Drive Map'!$B$4:$B$33,0))&"","")="","",HYPERLINK(INDEX('Google Drive Map'!$G$4:$G$33,MATCH(H91,'Google Drive Map'!$B$4:$B$33,0)),"Open")))
A92: G7 | B92: Completion & handover | C92: Exit check | D92: Occupancy permit issued before move-in | I92: =IF(H92="","",IF(IFERROR(INDEX('Google Drive Map'!$G$4:$G$33,MATCH(H92,'Google Drive Map'!$B$4:$B$33,0))&"","")="","",HYPERLINK(INDEX('Google Drive Map'!$G$4:$G$33,MATCH(H92,'Google Drive Map'!$B$4:$B$33,0)),"Open")))
A93: G7 | B93: Completion & handover | C93: Exit check | D93: All trades paid, retentions released per contract | I93: =IF(H93="","",IF(IFERROR(INDEX('Google Drive Map'!$G$4:$G$33,MATCH(H93,'Google Drive Map'!$B$4:$B$33,0))&"","")="","",HYPERLINK(INDEX('Google Drive Map'!$G$4:$G$33,MATCH(H93,'Google Drive Map'!$B$4:$B$33,0)),"Open")))
A94: G7 | B94: Completion & handover | C94: Exit check | D94: Warranty & defects-period reminders set | I94: =IF(H94="","",IF(IFERROR(INDEX('Google Drive Map'!$G$4:$G$33,MATCH(H94,'Google Drive Map'!$B$4:$B$33,0))&"","")="","",HYPERLINK(INDEX('Google Drive Map'!$G$4:$G$33,MATCH(H94,'Google Drive Map'!$B$4:$B$33,0)),"Open")))
I95: =IF(H95="","",IF(IFERROR(INDEX('Google Drive Map'!$G$4:$G$33,MATCH(H95,'Google Drive Map'!$B$4:$B$33,0))&"","")="","",HYPERLINK(INDEX('Google Drive Map'!$G$4:$G$33,MATCH(H95,'Google Drive Map'!$B$4:$B$33,0)),"Open")))
I96: =IF(H96="","",IF(IFERROR(INDEX('Google Drive Map'!$G$4:$G$33,MATCH(H96,'Google Drive Map'!$B$4:$B$33,0))&"","")="","",HYPERLINK(INDEX('Google Drive Map'!$G$4:$G$33,MATCH(H96,'Google Drive Map'!$B$4:$B$33,0)),"Open")))
I97: =IF(H97="","",IF(IFERROR(INDEX('Google Drive Map'!$G$4:$G$33,MATCH(H97,'Google Drive Map'!$B$4:$B$33,0))&"","")="","",HYPERLINK(INDEX('Google Drive Map'!$G$4:$G$33,MATCH(H97,'Google Drive Map'!$B$4:$B$33,0)),"Open")))
I98: =IF(H98="","",IF(IFERROR(INDEX('Google Drive Map'!$G$4:$G$33,MATCH(H98,'Google Drive Map'!$B$4:$B$33,0))&"","")="","",HYPERLINK(INDEX('Google Drive Map'!$G$4:$G$33,MATCH(H98,'Google Drive Map'!$B$4:$B$33,0)),"Open")))
I99: =IF(H99="","",IF(IFERROR(INDEX('Google Drive Map'!$G$4:$G$33,MATCH(H99,'Google Drive Map'!$B$4:$B$33,0))&"","")="","",HYPERLINK(INDEX('Google Drive Map'!$G$4:$G$33,MATCH(H99,'Google Drive Map'!$B$4:$B$33,0)),"Open")))
I100: =IF(H100="","",IF(IFERROR(INDEX('Google Drive Map'!$G$4:$G$33,MATCH(H100,'Google Drive Map'!$B$4:$B$33,0))&"","")="","",HYPERLINK(INDEX('Google Drive Map'!$G$4:$G$33,MATCH(H100,'Google Drive Map'!$B$4:$B$33,0)),"Open")))
...

Sheet Compliance
A1: Victorian owner-builder compliance
A2: Every item from the 11-stage checklist. Set Status as you go; use N/A only where the item genuinely doesn't apply to your build.
A3: ID | B3: Stage | C3: Item | D3: Requirement | E3: What it means | F3: Gateway | G3: Status | H3: Date done | I3: Reference / permit no. | J3: Evidence Doc ID | K3: Drive folder | L3: Folder | M3: Notes
A4: el-own | B4: 1. Eligibility | C4: You own the land | D4: Must | E4: Or you're a director of the company, or a beneficiary of the trust, that owns it. Your name must match the title. | F4: G0 | G4: Not started | K4: 01 Eligibility, Land & Planning | L4: =IF(K4="","",IF(IFERROR(INDEX('Google Drive Map'!$G$4:$G$33,MATCH(K4,'Google Drive Map'!$B$4:$B$33,0))&"","")="","",HYPERLINK(INDEX('Google Drive Map'!$G$4:$G$33,MATCH(K4,'Google Drive Map'!$B$4:$B$33,0)),"Open")))
A5: el-single | B5: 1. Eligibility | C5: The work relates to a single domestic dwelling | D5: Must | E5: This includes work ancillary to it, such as a garage, shed, pool or deck. Multi-unit developments are out. | F5: G0 | G5: Not started | K5: 01 Eligibility, Land & Planning | L5: =IF(K5="","",IF(IFERROR(INDEX('Google Drive Map'!$G$4:$G$33,MATCH(K5,'Google Drive Map'!$B$4:$B$33,0))&"","")="","",HYPERLINK(INDEX('Google Drive Map'!$G$4:$G$33,MATCH(K5,'Google Drive Map'!$B$4:$B$33,0)),"Open")))
A6: el-reside | B6: 1. Eligibility | C6: You live in it, or intend to live in it | D6: Must | E6: A small second dwelling on the same lot is exempt from this rule. | F6: G0 | G6: Not started | K6: 01 Eligibility, Land & Planning | L6: =IF(K6="","",IF(IFERROR(INDEX('Google Drive Map'!$G$4:$G$33,MATCH(K6,'Google Drive Map'!$B$4:$B$33,0))&"","")="","",HYPERLINK(INDEX('Google Drive Map'!$G$4:$G$33,MATCH(K6,'Google Drive Map'!$B$4:$B$33,0)),"Open")))
A7: el-business | B7: 1. Eligibility | C7: You're not in the "business of building" | D7: Must | E7: Owner-building repeatedly for profit is treated as running a building business and needs registration. | F7: G0 | G7: Not started | K7: 01 Eligibility, Land & Planning | L7: =IF(K7="","",IF(IFERROR(INDEX('Google Drive Map'!$G$4:$G$33,MATCH(K7,'Google Drive Map'!$B$4:$B$33,0))&"","")="","",HYPERLINK(INDEX('Google Drive Map'!$G$4:$G$33,MATCH(K7,'Google Drive Map'!$B$4:$B$33,0)),"Open")))
A8: el-5yr | B8: 1. Eligibility | C8: No owner-builder permit in the last 5 years | D8: Must | E8: This applies to you and to anyone you co-own, or have co-owned, property with. Small second dwellings and further work on the same home are exceptions. The BPC can grant exemptions for special circumstances such as hardship. | F8: G0 | G8: Not started | K8: 01 Eligibility, Land & Planning | L8: =IF(K8="","",IF(IFERROR(INDEX('Google Drive Map'!$G$4:$G$33,MATCH(K8,'Google Drive Map'!$B$4:$B$33,0))&"","")="","",HYPERLINK(INDEX('Google Drive Map'!$G$4:$G$33,MATCH(K8,'Google Drive Map'!$B$4:$B$33,0)),"Open")))
A9: el-elearn | B9: 1. Eligibility | C9: Pass the BPC owner-builder eLearning assessment | D9: Must | E9: Free and online, about 2–3 hours. Download and keep your pass certificate. | F9: G2 | G9: Not started | K9: 01 Eligibility, Land & Planning | L9: =IF(K9="","",IF(IFERROR(INDEX('Google Drive Map'!$G$4:$G$33,MATCH(K9,'Google Drive Map'!$B$4:$B$33,0))&"","")="","",HYPERLINK(INDEX('Google Drive Map'!$G$4:$G$33,MATCH(K9,'Google Drive Map'!$B$4:$B$33,0)),"Open")))
A10: el-white | B10: 1. Eligibility | C10: Complete construction induction training (white card) | D10: Must | E10: It's part of the eligibility criteria. Anyone else working on your site needs one too. | F10: G2 | G10: Not started | K10: 01 Eligibility, Land & Planning | L10: =IF(K10="","",IF(IFERROR(INDEX('Google Drive Map'!$G$4:$G$33,MATCH(K10,'Google Drive Map'!$B$4:$B$33,0))&"","")="","",HYPERLINK(INDEX('Google Drive Map'!$G$4:$G$33,MATCH(K10,'Google Drive Map'!$B$4:$B$33,0)),"Open")))
A11: co-value | B11: 2. Certificate of consent | C11: Estimate the full value of the work | D11: Must | E11: Use market rates for your own labour. Keep the working. The building surveyor and BPC may ask for it. | F11: G2 | G11: Not started | K11: 01 Eligibility, Land & Planning | L11: =IF(K11="","",IF(IFERROR(INDEX('Google Drive Map'!$G$4:$G$33,MATCH(K11,'Google Drive Map'!$B$4:$B$33,0))&"","")="","",HYPERLINK(INDEX('Google Drive Map'!$G$4:$G$33,MATCH(K11,'Google Drive Map'!$B$4:$B$33,0)),"Open")))
A12: co-apply | B12: 2. Certificate of consent | C12: Apply to the BPC with proof of ownership and ID | D12: Must | E12: Include your eLearning pass, construction induction card, title search and project description. There's a non-refundable application fee, so check the BPC fee schedule. | F12: G2 | G12: Not started | K12: 01 Eligibility, Land & Planning | L12: =IF(K12="","",IF(IFERROR(INDEX('Google Drive Map'!$G$4:$G$33,MATCH(K12,'Google Drive Map'!$B$4:$B$33,0))&"","")="","",HYPERLINK(INDEX('Google Drive Map'!$G$4:$G$33,MATCH(K12,'Google Drive Map'!$B$4:$B$33,0)),"Open")))
A13: co-receive | B13: 2. Certificate of consent | C13: Receive your certificate of consent | D13: Must | E13: Give a copy to your relevant building surveyor. It's specific to you, this land and this work. | F13: G2 | G13: Not started | K13: 01 Eligibility, Land & Planning | L13: =IF(K13="","",IF(IFERROR(INDEX('Google Drive Map'!$G$4:$G$33,MATCH(K13,'Google Drive Map'!$B$4:$B$33,0))&"","")="","",HYPERLINK(INDEX('Google Drive Map'!$G$4:$G$33,MATCH(K13,'Google Drive Map'!$B$4:$B$33,0)),"Open")))
A14: de-title | B14: 3. Site, planning & design | C14: Title search: covenants, easements, section 173 agreements | D14: Must | E14: These can limit what, where and how you build. Get the plan of subdivision too. | F14: G0 | G14: Not started | K14: 01 Eligibility, Land & Planning | L14: =IF(K14="","",IF(IFERROR(INDEX('Google Drive Map'!$G$4:$G$33,MATCH(K14,'Google Drive Map'!$B$4:$B$33,0))&"","")="","",HYPERLINK(INDEX('Google Drive Map'!$G$4:$G$33,MATCH(K14,'Google Drive Map'!$B$4:$B$33,0)),"Open")))
A15: de-planning | B15: 3. Site, planning & design | C15: Check zoning & overlays and get a planning permit | D15: If applies | E15: Use VicPlan / Planning Property Report. Heritage, bushfire (BMO), flood, vegetation and neighbourhood character overlays often need a permit from council. | F15: G2 | G15: Not started | K15: 01 Eligibility, Land & Planning | L15: =IF(K15="","",IF(IFERROR(INDEX('Google Drive Map'!$G$4:$G$33,MATCH(K15,'Google Drive Map'!$B$4:$B$33,0))&"","")="","",HYPERLINK(INDEX('Google Drive Map'!$G$4:$G$33,MATCH(K15,'Google Drive Map'!$B$4:$B$33,0)),"Open")))
... A64: mo-tax | B64: 11. Finance & tax | C64: Get tax advice on GST & CGT | D64: Best practice | E64: Building to live in is generally private. Building to sell can be treated as a business. Get advice early. | F64: G0 | G64: Not started | K64: 03 Permits, Insurance & Finance | L64: =IF(K64="","",IF(IFERROR(INDEX('Google Drive Map'!$G$4:$G$33,MATCH(K64,'Google Drive Map'!$B$4:$B$33,0))&"","")="","",HYPERLINK(INDEX('Google Drive Map'!$G$4:$G$33,MATCH(K64,'Google Drive Map'!$B$4:$B$33,0)),"Open")))
L65: =IF(K65="","",IF(IFERROR(INDEX('Google Drive Map'!$G$4:$G$33,MATCH(K65,'Google Drive Map'!$B$4:$B$33,0))&"","")="","",HYPERLINK(INDEX('Google Drive Map'!$G$4:$G$33,MATCH(K65,'Google Drive Map'!$B$4:$B$33,0)),"Open")))
L66: =IF(K66="","",IF(IFERROR(INDEX('Google Drive Map'!$G$4:$G$33,MATCH(K66,'Google Drive Map'!$B$4:$B$33,0))&"","")="","",HYPERLINK(INDEX('Google Drive Map'!$G$4:$G$33,MATCH(K66,'Google Drive Map'!$B$4:$B$33,0)),"Open")))
L67: =IF(K67="","",IF(IFERROR(INDEX('Google Drive Map'!$G$4:$G$33,MATCH(K67,'Google Drive Map'!$B$4:$B$33,0))&"","")="","",HYPERLINK(INDEX('Google Drive Map'!$G$4:$G$33,MATCH(K67,'Google Drive Map'!$B$4:$B$33,0)),"Open")))
L68: =IF(K68="","",IF(IFERROR(INDEX('Google Drive Map'!$G$4:$G$33,MATCH(K68,'Google Drive Map'!$B$4:$B$33,0))&"","")="","",HYPERLINK(INDEX('Google Drive Map'!$G$4:$G$33,MATCH(K68,'Google Drive Map'!$B$4:$B$33,0)),"Open")))
L69: =IF(K69="","",IF(IFERROR(INDEX('Google Drive Map'!$G$4:$G$33,MATCH(K69,'Google Drive Map'!$B$4:$B$33,0))&"","")="","",HYPERLINK(INDEX('Google Drive Map'!$G$4:$G$33,MATCH(K69,'Google Drive Map'!$B$4:$B$33,0)),"Open")))
L70: =IF(K70="","",IF(IFERROR(INDEX('Google Drive Map'!$G$4:$G$33,MATCH(K70,'Google Drive Map'!$B$4:$B$33,0))&"","")="","",HYPERLINK(INDEX('Google Drive Map'!$G$4:$G$33,MATCH(K70,'Google Drive Map'!$B$4:$B$33,0)),"Open")))
L71: =IF(K71="","",IF(IFERROR(INDEX('Google Drive Map'!$G$4:$G$33,MATCH(K71,'Google Drive Map'!$B$4:$B$33,0))&"","")="","",HYPERLINK(INDEX('Google Drive Map'!$G$4:$G$33,MATCH(K71,'Google Drive Map'!$B$4:$B$33,0)),"Open")))
L72: =IF(K72="","",IF(IFERROR(INDEX('Google Drive Map'!$G$4:$G$33,MATCH(K72,'Google Drive Map'!$B$4:$B$33,0))&"","")="","",HYPERLINK(INDEX('Google Drive Map'!$G$4:$G$33,MATCH(K72,'Google Drive Map'!$B$4:$B$33,0)),"Open")))
L73: =IF(K73="","",IF(IFERROR(INDEX('Google Drive Map'!$G$4:$G$33,MATCH(K73,'Google Drive Map'!$B$4:$B$33,0))&"","")="","",HYPERLINK(INDEX('Google Drive Map'!$G$4:$G$33,MATCH(K73,'Google Drive Map'!$B$4:$B$33,0)),"Open")))
L74: =IF(K74="","",IF(IFERROR(INDEX('Google Drive Map'!$G$4:$G$33,MATCH(K74,'Google Drive Map'!$B$4:$B$33,0))&"","")="","",HYPERLINK(INDEX('Google Drive Map'!$G$4:$G$33,MATCH(K74,'Google Drive Map'!$B$4:$B$33,0)),"Open")))
L75: =IF(K75="","",IF(IFERROR(INDEX('Google Drive Map'!$G$4:$G$33,MATCH(K75,'Google Drive Map'!$B$4:$B$33,0))&"","")="","",HYPERLINK(INDEX('Google Drive Map'!$G$4:$G$33,MATCH(K75,'Google Drive Map'!$B$4:$B$33,0)),"Open")))
L76: =IF(K76="","",IF(IFERROR(INDEX('Google Drive Map'!$G$4:$G$33,MATCH(K76,'Google Drive Map'!$B$4:$B$33,0))&"","")="","",HYPERLINK(INDEX('Google Drive Map'!$G$4:$G$33,MATCH(K76,'Google Drive Map'!$B$4:$B$33,0)),"Open")))
... L79: =IF(K79="","",IF(IFERROR(INDEX('Google Drive Map'!$G$4:$G$33,MATCH(K79,'Google Drive Map'!$B$4:$B$33,0))&"","")="","",HYPERLINK(INDEX('Google Drive Map'!$G$4:$G$33,MATCH(K79,'Google Drive Map'!$B$4:$B$33,0)),"Open")))

Sheet Risks
A1: Risk register
A2: Likelihood × impact gives the rating. Review it weekly. Contingency is money set aside for these risks, not for upgrades.
A3: ID | B3: Risk | C3: Likelihood | D3: Impact | E3: Score | F3: Rating | G3: Response | H3: Owner | I3: Status | J3: Next review | K3: Notes
A4: R01 | B4: Site costs blow out (rock, fill, poor soil, services) | C4: Med | D4: High | E4: =IF(OR(C4="",D4=""),"",MATCH(C4,{"Low","Med","High"},0)*MATCH(D4,{"Low","Med","High"},0)) | F4: =IF(E4="","",IF(E4>=6,"High",IF(E4>=3,"Medium","Low"))) | G4: Soil test and feature survey before G1. Get a site-works provisional sum with a cap. | H4: Owner-builder | I4: Open
A5: R02 | B5: Key trade unavailable, program slips | C5: High | D5: Med | E5: =IF(OR(C5="",D5=""),"",MATCH(C5,{"Low","Med","High"},0)*MATCH(D5,{"Low","Med","High"},0)) | F5: =IF(E5="","",IF(E5>=6,"High",IF(E5>=3,"Medium","Low"))) | G5: Book critical-path trades at G3. Keep a backup quote for each. | H5: Owner-builder | I5: Open
A6: R03 | B6: Trade insurance or registration lapses mid-job | C6: Med | D6: High | E6: =IF(OR(C6="",D6=""),"",MATCH(C6,{"Low","Med","High"},0)*MATCH(D6,{"Low","Med","High"},0)) | F6: =IF(E6="","",IF(E6>=6,"High",IF(E6>=3,"Medium","Low"))) | G6: Track expiry dates in the trade register with automatic reminders. | H6: Owner-builder | I6: Open
A7: R04 | B7: Failed inspection | C7: Med | D7: Med | E7: =IF(OR(C7="",D7=""),"",MATCH(C7,{"Low","Med","High"},0)*MATCH(D7,{"Low","Med","High"},0)) | F7: =IF(E7="","",IF(E7>=6,"High",IF(E7>=3,"Medium","Low"))) | G7: Run your own ITP checklist before calling the RBS. | H7: Owner-builder | I7: Open
A8: R05 | B8: Scope creep (upgrades) | C8: High | D8: Med | E8: =IF(OR(C8="",D8=""),"",MATCH(C8,{"Low","Med","High"},0)*MATCH(D8,{"Low","Med","High"},0)) | F8: =IF(E8="","",IF(E8>=6,"High",IF(E8>=3,"Medium","Low"))) | G8: Freeze scope at G1. Every change goes through a written variation. | H8: Owner-builder | I8: Open
A9: R06 | B9: Owner-builder burnout or injury | C9: Med | D9: High | E9: =IF(OR(C9="",D9=""),"",MATCH(C9,{"Low","Med","High"},0)*MATCH(D9,{"Low","Med","High"},0)) | F9: =IF(E9="","",IF(E9>=6,"High",IF(E9>=3,"Medium","Low"))) | G9: Realistic program, personal accident cover, a mentor at each gateway. | H9: Owner-builder | I9: Open
A10: R07 | B10: Wet weather | C10: High | D10: Low | E10: =IF(OR(C10="",D10=""),"",MATCH(C10,{"Low","Med","High"},0)*MATCH(D10,{"Low","Med","High"},0)) | F10: =IF(E10="","",IF(E10>=6,"High",IF(E10>=3,"Medium","Low"))) | G10: Allow weather days in the program. Prioritise lock-up. | H10: Owner-builder | I10: Open
E11: =IF(OR(C11="",D11=""),"",MATCH(C11,{"Low","Med","High"},0)*MATCH(D11,{"Low","Med","High"},0)) | F11: =IF(E11="","",IF(E11>=6,"High",IF(E11>=3,"Medium","Low")))
E12: =IF(OR(C12="",D12=""),"",MATCH(C12,{"Low","Med","High"},0)*MATCH(D12,{"Low","Med","High"},0)) | F12: =IF(E12="","",IF(E12>=6,"High",IF(E12>=3,"Medium","Low")))
E13: =IF(OR(C13="",D13=""),"",MATCH(C13,{"Low","Med","High"},0)*MATCH(D13,{"Low","Med","High"},0)) | F13: =IF(E13="","",IF(E13>=6,"High",IF(E13>=3,"Medium","Low")))
E14: =IF(OR(C14="",D14=""),"",MATCH(C14,{"Low","Med","High"},0)*MATCH(D14,{"Low","Med","High"},0)) | F14: =IF(E14="","",IF(E14>=6,"High",IF(E14>=3,"Medium","Low")))
E15: =IF(OR(C15="",D15=""),"",MATCH(C15,{"Low","Med","High"},0)*MATCH(D15,{"Low","Med","High"},0)) | F15: =IF(E15="","",IF(E15>=6,"High",IF(E15>=3,"Medium","Low")))
E16: =IF(OR(C16="",D16=""),"",MATCH(C16,{"Low","Med","High"},0)*MATCH(D16,{"Low","Med","High"},0)) | F16: =IF(E16="","",IF(E16>=6,"High",IF(E16>=3,"Medium","Low")))
E17: =IF(OR(C17="",D17=""),"",MATCH(C17,{"Low","Med","High"},0)*MATCH(D17,{"Low","Med","High"},0)) | F17: =IF(E17="","",IF(E17>=6,"High",IF(E17>=3,"Medium","Low")))
E18: =IF(OR(C18="",D18=""),"",MATCH(C18,{"Low","Med","High"},0)*MATCH(D18,{"Low","Med","High"},0)) | F18: =IF(E18="","",IF(E18>=6,"High",IF(E18>=3,"Medium","Low")))
E19: =IF(OR(C19="",D19=""),"",MATCH(C19,{"Low","Med","High"},0)*MATCH(D19,{"Low","Med","High"},0)) | F19: =IF(E19="","",IF(E19>=6,"High",IF(E19>=3,"Medium","Low")))
E20: =IF(OR(C20="",D20=""),"",MATCH(C20,{"Low","Med","High"},0)*MATCH(D20,{"Low","Med","High"},0)) | F20: =IF(E20="","",IF(E20>=6,"High",IF(E20>=3,"Medium","Low")))
E21: =IF(OR(C21="",D21=""),"",MATCH(C21,{"Low","Med","High"},0)*MATCH(D21,{"Low","Med","High"},0)) | F21: =IF(E21="","",IF(E21>=6,"High",IF(E21>=3,"Medium","Low")))
E22: =IF(OR(C22="",D22=""),"",MATCH(C22,{"Low","Med","High"},0)*MATCH(D22,{"Low","Med","High"},0)) | F22: =IF(E22="","",IF(E22>=6,"High",IF(E22>=3,"Medium","Low")))
... E63: =IF(OR(C63="",D63=""),"",MATCH(C63,{"Low","Med","High"},0)*MATCH(D63,{"Low","Med","High"},0)) | F63: =IF(E63="","",IF(E63>=6,"High",IF(E63>=3,"Medium","Low")))

Sheet Google Drive Map
A1: Folder map
A2: The folder tree for one build, in Google Drive, Dropbox or OneDrive. Paste each folder's link, or a local folder path, into Folder link; the Open links on other tabs use it. In Google Sheets the Apps Script can create the folders and fill in the links.
A3: Code | B3: Folder path | C3: What goes here | D3: Compliance stages | E3: Gateways | F3: Tabs that point here | G3: Folder link (paste)
A4: 00 | B4: 00 Project Register | C4: This workbook, its backups and the Apps Script notes. | E4: All | F4: Every tab
A5: 01 | B5: 01 Eligibility, Land & Planning | C5: eLearning pass, white card, certificate of consent and application, title search, plan of subdivision, covenants, s173 agreements, Planning Property Report, planning permit, legal point of discharge, build-over-easement and siting consents. | D5: 1, 2, 3 | E5: G0, G1, G2 | F5: Compliance, Gateways, Documents
A6: 02 | B6: 02 Design & Engineering | C6: Design brief, concept and working drawings, specification, engineering, energy (NatHERS) report, BAL assessment, feature & level survey, soil report, asbestos report, approved amendments. | D6: 3, 8 | E6: G1, G2 | F6: Documents, Rooms (drawing refs), Diary (plan notes)
A7: 03 | B7: 03 Permits, Insurance & Finance | C7: RBS fee proposal and appointment, building permit, asset protection permit and bond, protection work notices, Before You Dig, your insurance policies, WorkSafe and principal contractor papers, loan, valuations, drawdowns, cost plan, tax advice. | D7: 4, 5, 6, 11 | E7: G0, G1, G3 | F7: Project, Packages, Compliance
A8: 04 | B8: 04 Trades & Tenders | C8: One subfolder per trade package. In each: RFQ pack and quotes, tender comparison, signed contract and variations, licence, insurance certificates of currency and SWMS, invoices and payment records. | D8: 5, 6, 7 | E8: G3 to G7 | F8: Packages, Trades, Tenders, Variations, Payments
A9: 04/01 | B9: 04 Trades & Tenders/01 Surveyor | C9: RFQ & quotes, contract & variations, licence / insurance / SWMS, invoices.
A10: 04/02 | B10: 04 Trades & Tenders/02 Demolition & earthworks | C10: RFQ & quotes, contract & variations, licence / insurance / SWMS, invoices.
A11: 04/03 | B11: 04 Trades & Tenders/03 Plumbing & drainage | C11: RFQ & quotes, contract & variations, licence / insurance / SWMS, invoices.
A12: 04/04 | B12: 04 Trades & Tenders/04 Concreter | C12: RFQ & quotes, contract & variations, licence / insurance / SWMS, invoices.
A13: 04/05 | B13: 04 Trades & Tenders/05 Termite management | C13: RFQ & quotes, contract & variations, licence / insurance / SWMS, invoices.
A14: 04/06 | B14: 04 Trades & Tenders/06 Frame & truss supply | C14: RFQ & quotes, contract & variations, licence / insurance / SWMS, invoices.
A15: 04/07 | B15: 04 Trades & Tenders/07 Carpenter (frame) | C15: RFQ & quotes, contract & variations, licence / insurance / SWMS, invoices.
A16: 04/08 | B16: 04 Trades & Tenders/08 Roofing | C16: RFQ & quotes, contract & variations, licence / insurance / SWMS, invoices.
A17: 04/09 | B17: 04 Trades & Tenders/09 Windows & external doors | C17: RFQ & quotes, contract & variations, licence / insurance / SWMS, invoices.
A18: 04/10 | B18: 04 Trades & Tenders/10 Bricklayer & cladding | C18: RFQ & quotes, contract & variations, licence / insurance / SWMS, invoices.
A19: 04/11 | B19: 04 Trades & Tenders/11 Electrician | C19: RFQ & quotes, contract & variations, licence / insurance / SWMS, invoices.
A20: 04/12 | B20: 04 Trades & Tenders/12 Insulation | C20: RFQ & quotes, contract & variations, licence / insurance / SWMS, invoices.
... A28: 04/20 | B28: 04 Trades & Tenders/20 Floor coverings & landscaping | C28: RFQ & quotes, contract & variations, licence / insurance / SWMS, invoices.
A29: 05 | B29: 05 Selections & Specs | C29: Product spec sheets, brochures, colour and tile codes, quotes from suppliers, orders and delivery dockets. | E29: G5, G6 | F29: Selections
A30: 06 | B30: 06 Site Diary & Photos | C30: Site photos (especially before anything is covered), diary exports, site induction and sign-in register. | D30: 5, 8 | E30: G4 to G7 | F30: Diary, Photos
A31: 07 | B31: 07 Inspections & Certificates | C31: RBS inspection reports and every compliance certificate: plumbing (PCC), electrical (CoES), termite, waterproofing, glazing, insulation, smoke alarms, engineer sign-offs, commissioning sheets. | D31: 8, 9 | E31: G4 to G7 | F31: Certificates, Compliance
A32: 08 | B32: 08 Handover, Records & Sale | C32: Occupancy permit or certificate of final inspection, warranties, manuals, as-built service locations, paint and tile codes, s137B defects report, owner-builder insurance, section 32 papers. | D32: 9, 10 | E32: G7 | F32: Compliance, Certificates
A33: 99 | B33: 99 Archive | C33: Superseded drawings and documents, unsuccessful quotes. Never delete: move here. | F33: Documents (status Superseded)
B35: File naming: DocID_Description_Rev
B36: Doc ID = folder code - document type - number, e.g. 02-DWG-012 is drawing number 12 in 02 Design & Engineering.
B37: File name = Doc ID, then a short description with hyphens, then the revision: 02-DWG-012_Floor-Plan_RevC.pdf
B38: Register every file in the Documents tab first. It builds the Doc ID and file name for you and tells you which folder to save it in.
B39: Trade paperwork goes in that package's subfolder of 04, e.g. 04 Trades & Tenders/08 Roofing/04-CON-003_Roofing-Contract.pdf
B40: When a drawing is replaced, set the old one to Superseded in Documents and move the file to 99 Archive. Never delete.
B41: Folder links: any provider
B42: Google Drive, Dropbox, OneDrive or SharePoint: open the folder in your browser, choose Share > Copy link, and paste it into Folder link.
B43: Working offline on a computer? Paste the local folder path instead, e.g. C:\Users\you\Dropbox\Owner Build\02 Design & Engineering or /Users/you/Library/CloudStorage/... It opens without internet.
B44: Google Sheets: Owner Builder > Set up Drive folders creates the folders and fills in every link for you.
B45: Document types
B46: DWG Drawing
... B69: OTH Other

Sheet Rooms
A1: Rooms & spaces | B1: Takeoffs
A2: Enter each room or area once. Internal rooms get every quantity; garages skip skirting; external areas (driveways, paving, decks) get floor area only. Blank area type counts as internal. | B2: NOTE: Include Garages and Outdoor areas where pricing and quoting is required (i.e driveways, paving etc)
A3: Room / area | B3: Level | C3: Area type | D3: Length (m) | E3: Width (m) | F3: Ceiling (m) | G3: Floor area (m²) | H3: Skirting (m) | I3: Wall paint (m²) | J3: Floor covering + waste (m²) | K3: Squares | L3: Check | M3: Drawing ref | N3: Notes
A4: Kitchen / living | B4: Ground | C4: Internal | D4: 7.2 | E4: 5.4 | G4: =IF(AND(ISNUMBER(D4),ISNUMBER(E4)),D4*E4,"") | H4: =IF(OR(G4="",C4="Garage",C4="External"),"",2*(D4+E4)) | I4: =IF(OR(G4="",C4="External"),"",2*(D4+E4)*IF(ISNUMBER(F4),F4,Settings!$B$15)) | J4: =IF(G4="","",G4*(1+Settings!$B$16)) | K4: =IF(OR(G4="",C4="External"),"",G4/9.29) | L4: =IF(OR(AND(D4<>"",NOT(ISNUMBER(D4))),AND(E4<>"",NOT(ISNUMBER(E4))),AND(F4<>"",NOT(ISNUMBER(F4)))),"Type sizes as numbers in metres, e.g. 3.2","") | N4: EXAMPLE: delete this row
A5: Driveway | B5: External | C5: External | D5: 12 | E5: 3.5 | G5: =IF(AND(ISNUMBER(D5),ISNUMBER(E5)),D5*E5,"") | H5: =IF(OR(G5="",C5="Garage",C5="External"),"",2*(D5+E5)) | I5: =IF(OR(G5="",C5="External"),"",2*(D5+E5)*IF(ISNUMBER(F5),F5,Settings!$B$15)) | J5: =IF(G5="","",G5*(1+Settings!$B$16)) | K5: =IF(OR(G5="",C5="External"),"",G5/9.29) | L5: =IF(OR(AND(D5<>"",NOT(ISNUMBER(D5))),AND(E5<>"",NOT(ISNUMBER(E5))),AND(F5<>"",NOT(ISNUMBER(F5)))),"Type sizes as numbers in metres, e.g. 3.2","") | N5: EXAMPLE: delete this row
G6: =IF(AND(ISNUMBER(D6),ISNUMBER(E6)),D6*E6,"") | H6: =IF(OR(G6="",C6="Garage",C6="External"),"",2*(D6+E6)) | I6: =IF(OR(G6="",C6="External"),"",2*(D6+E6)*IF(ISNUMBER(F6),F6,Settings!$B$15)) | J6: =IF(G6="","",G6*(1+Settings!$B$16)) | K6: =IF(OR(G6="",C6="External"),"",G6/9.29) | L6: =IF(OR(AND(D6<>"",NOT(ISNUMBER(D6))),AND(E6<>"",NOT(ISNUMBER(E6))),AND(F6<>"",NOT(ISNUMBER(F6)))),"Type sizes as numbers in metres, e.g. 3.2","")
G7: =IF(AND(ISNUMBER(D7),ISNUMBER(E7)),D7*E7,"") | H7: =IF(OR(G7="",C7="Garage",C7="External"),"",2*(D7+E7)) | I7: =IF(OR(G7="",C7="External"),"",2*(D7+E7)*IF(ISNUMBER(F7),F7,Settings!$B$15)) | J7: =IF(G7="","",G7*(1+Settings!$B$16)) | K7: =IF(OR(G7="",C7="External"),"",G7/9.29) | L7: =IF(OR(AND(D7<>"",NOT(ISNUMBER(D7))),AND(E7<>"",NOT(ISNUMBER(E7))),AND(F7<>"",NOT(ISNUMBER(F7)))),"Type sizes as numbers in metres, e.g. 3.2","")
G8: =IF(AND(ISNUMBER(D8),ISNUMBER(E8)),D8*E8,"") | H8: =IF(OR(G8="",C8="Garage",C8="External"),"",2*(D8+E8)) | I8: =IF(OR(G8="",C8="External"),"",2*(D8+E8)*IF(ISNUMBER(F8),F8,Settings!$B$15)) | J8: =IF(G8="","",G8*(1+Settings!$B$16)) | K8: =IF(OR(G8="",C8="External"),"",G8/9.29) | L8: =IF(OR(AND(D8<>"",NOT(ISNUMBER(D8))),AND(E8<>"",NOT(ISNUMBER(E8))),AND(F8<>"",NOT(ISNUMBER(F8)))),"Type sizes as numbers in metres, e.g. 3.2","")
G9: =IF(AND(ISNUMBER(D9),ISNUMBER(E9)),D9*E9,"") | H9: =IF(OR(G9="",C9="Garage",C9="External"),"",2*(D9+E9)) | I9: =IF(OR(G9="",C9="External"),"",2*(D9+E9)*IF(ISNUMBER(F9),F9,Settings!$B$15)) | J9: =IF(G9="","",G9*(1+Settings!$B$16)) | K9: =IF(OR(G9="",C9="External"),"",G9/9.29) | L9: =IF(OR(AND(D9<>"",NOT(ISNUMBER(D9))),AND(E9<>"",NOT(ISNUMBER(E9))),AND(F9<>"",NOT(ISNUMBER(F9)))),"Type sizes as numbers in metres, e.g. 3.2","")
G10: =IF(AND(ISNUMBER(D10),ISNUMBER(E10)),D10*E10,"") | H10: =IF(OR(G10="",C10="Garage",C10="External"),"",2*(D10+E10)) | I10: =IF(OR(G10="",C10="External"),"",2*(D10+E10)*IF(ISNUMBER(F10),F10,Settings!$B$15)) | J10: =IF(G10="","",G10*(1+Settings!$B$16)) | K10: =IF(OR(G10="",C10="External"),"",G10/9.29) | L10: =IF(OR(AND(D10<>"",NOT(ISNUMBER(D10))),AND(E10<>"",NOT(ISNUMBER(E10))),AND(F10<>"",NOT(ISNUMBER(F10)))),"Type sizes as numbers in metres, e.g. 3.2","")
G11: =IF(AND(ISNUMBER(D11),ISNUMBER(E11)),D11*E11,"") | H11: =IF(OR(G11="",C11="Garage",C11="External"),"",2*(D11+E11)) | I11: =IF(OR(G11="",C11="External"),"",2*(D11+E11)*IF(ISNUMBER(F11),F11,Settings!$B$15)) | J11: =IF(G11="","",G11*(1+Settings!$B$16)) | K11: =IF(OR(G11="",C11="External"),"",G11/9.29) | L11: =IF(OR(AND(D11<>"",NOT(ISNUMBER(D11))),AND(E11<>"",NOT(ISNUMBER(E11))),AND(F11<>"",NOT(ISNUMBER(F11)))),"Type sizes as numbers in metres, e.g. 3.2","")
G12: =IF(AND(ISNUMBER(D12),ISNUMBER(E12)),D12*E12,"") | H12: =IF(OR(G12="",C12="Garage",C12="External"),"",2*(D12+E12)) | I12: =IF(OR(G12="",C12="External"),"",2*(D12+E12)*IF(ISNUMBER(F12),F12,Settings!$B$15)) | J12: =IF(G12="","",G12*(1+Settings!$B$16)) | K12: =IF(OR(G12="",C12="External"),"",G12/9.29) | L12: =IF(OR(AND(D12<>"",NOT(ISNUMBER(D12))),AND(E12<>"",NOT(ISNUMBER(E12))),AND(F12<>"",NOT(ISNUMBER(F12)))),"Type sizes as numbers in metres, e.g. 3.2","")
G13: =IF(AND(ISNUMBER(D13),ISNUMBER(E13)),D13*E13,"") | H13: =IF(OR(G13="",C13="Garage",C13="External"),"",2*(D13+E13)) | I13: =IF(OR(G13="",C13="External"),"",2*(D13+E13)*IF(ISNUMBER(F13),F13,Settings!$B$15)) | J13: =IF(G13="","",G13*(1+Settings!$B$16)) | K13: =IF(OR(G13="",C13="External"),"",G13/9.29) | L13: =IF(OR(AND(D13<>"",NOT(ISNUMBER(D13))),AND(E13<>"",NOT(ISNUMBER(E13))),AND(F13<>"",NOT(ISNUMBER(F13)))),"Type sizes as numbers in metres, e.g. 3.2","")
G14: =IF(AND(ISNUMBER(D14),ISNUMBER(E14)),D14*E14,"") | H14: =IF(OR(G14="",C14="Garage",C14="External"),"",2*(D14+E14)) | I14: =IF(OR(G14="",C14="External"),"",2*(D14+E14)*IF(ISNUMBER(F14),F14,Settings!$B$15)) | J14: =IF(G14="","",G14*(1+Settings!$B$16)) | K14: =IF(OR(G14="",C14="External"),"",G14/9.29) | L14: =IF(OR(AND(D14<>"",NOT(ISNUMBER(D14))),AND(E14<>"",NOT(ISNUMBER(E14))),AND(F14<>"",NOT(ISNUMBER(F14)))),"Type sizes as numbers in metres, e.g. 3.2","")
G15: =IF(AND(ISNUMBER(D15),ISNUMBER(E15)),D15*E15,"") | H15: =IF(OR(G15="",C15="Garage",C15="External"),"",2*(D15+E15)) | I15: =IF(OR(G15="",C15="External"),"",2*(D15+E15)*IF(ISNUMBER(F15),F15,Settings!$B$15)) | J15: =IF(G15="","",G15*(1+Settings!$B$16)) | K15: =IF(OR(G15="",C15="External"),"",G15/9.29) | L15: =IF(OR(AND(D15<>"",NOT(ISNUMBER(D15))),AND(E15<>"",NOT(ISNUMBER(E15))),AND(F15<>"",NOT(ISNUMBER(F15)))),"Type sizes as numbers in metres, e.g. 3.2","")
G16: =IF(AND(ISNUMBER(D16),ISNUMBER(E16)),D16*E16,"") | H16: =IF(OR(G16="",C16="Garage",C16="External"),"",2*(D16+E16)) | I16: =IF(OR(G16="",C16="External"),"",2*(D16+E16)*IF(ISNUMBER(F16),F16,Settings!$B$15)) | J16: =IF(G16="","",G16*(1+Settings!$B$16)) | K16: =IF(OR(G16="",C16="External"),"",G16/9.29) | L16: =IF(OR(AND(D16<>"",NOT(ISNUMBER(D16))),AND(E16<>"",NOT(ISNUMBER(E16))),AND(F16<>"",NOT(ISNUMBER(F16)))),"Type sizes as numbers in metres, e.g. 3.2","")
G17: =IF(AND(ISNUMBER(D17),ISNUMBER(E17)),D17*E17,"") | H17: =IF(OR(G17="",C17="Garage",C17="External"),"",2*(D17+E17)) | I17: =IF(OR(G17="",C17="External"),"",2*(D17+E17)*IF(ISNUMBER(F17),F17,Settings!$B$15)) | J17: =IF(G17="","",G17*(1+Settings!$B$16)) | K17: =IF(OR(G17="",C17="External"),"",G17/9.29) | L17: =IF(OR(AND(D17<>"",NOT(ISNUMBER(D17))),AND(E17<>"",NOT(ISNUMBER(E17))),AND(F17<>"",NOT(ISNUMBER(F17)))),"Type sizes as numbers in metres, e.g. 3.2","")
... G63: =IF(AND(ISNUMBER(D63),ISNUMBER(E63)),D63*E63,"") | H63: =IF(OR(G63="",C63="Garage",C63="External"),"",2*(D63+E63)) | I63: =IF(OR(G63="",C63="External"),"",2*(D63+E63)*IF(ISNUMBER(F63),F63,Settings!$B$15)) | J63: =IF(G63="","",G63*(1+Settings!$B$16)) | K63: =IF(OR(G63="",C63="External"),"",G63/9.29) | L63: =IF(OR(AND(D63<>"",NOT(ISNUMBER(D63))),AND(E63<>"",NOT(ISNUMBER(E63))),AND(F63<>"",NOT(ISNUMBER(F63)))),"Type sizes as numbers in metres, e.g. 3.2","")

Sheet Selections
A1: Selections & specs
A2: Every product decision in one list. Lock them all in before G6 (fit-out). File spec sheets in 05 Selections & Specs. | B2: Note: You may have a separate spec sheet from your contract but keep this here to track
A3: Item | B3: Category | C3: Room | D3: Spec / model / colour | E3: Supplier | F3: Qty | G3: Unit | H3: Unit price ($) | I3: Total ($) | J3: Status | K3: Needed by | L3: Order date | M3: Delivery date | N3: Spec Doc ID | O3: Notes
A4: Kitchen mixer tap | B4: Fit-out | C4: Kitchen / living | D4: Gooseneck, brushed nickel, WELS 5-star | E4: Plumbing supplier | F4: 1 | G4: ea | H4: 420 | I4: =IF(H4="","",H4*IF(F4="",1,F4)) | J4: Selected | K4: G6 | O4: EXAMPLE: delete this row
I5: =IF(H5="","",H5*IF(F5="",1,F5))
I6: =IF(H6="","",H6*IF(F6="",1,F6))
I7: =IF(H7="","",H7*IF(F7="",1,F7))
I8: =IF(H8="","",H8*IF(F8="",1,F8))
I9: =IF(H9="","",H9*IF(F9="",1,F9))
I10: =IF(H10="","",H10*IF(F10="",1,F10))
I11: =IF(H11="","",H11*IF(F11="",1,F11))
I12: =IF(H12="","",H12*IF(F12="",1,F12))
I13: =IF(H13="","",H13*IF(F13="",1,F13))
I14: =IF(H14="","",H14*IF(F14="",1,F14))
I15: =IF(H15="","",H15*IF(F15="",1,F15))
I16: =IF(H16="","",H16*IF(F16="",1,F16))
... I153: =IF(H153="","",H153*IF(F153="",1,F153))

Sheet Diary
A1: Plan notes & site diary
A2: Who was on site, weather, deliveries, instructions, defects and questions for the building surveyor. Link notes to a drawing sheet.
A3: Date | B3: Type | C3: Drawing / sheet ref | D3: Note | E3: On site | F3: Weather | G3: Trade / package | H3: Action by | I3: Due | J3: Closed? | K3: Photo Doc IDs | L3: Notes
B4: Instruction to trade | C4: A102 | D4: Move kitchen power point 300 mm left of window as marked on site. | G4: 11 Electrician | H4: Electrician | J4: No | L4: EXAMPLE: delete this row

Sheet Photos
A1: Site photo log
A2: Photograph everything before it's covered: slab mesh, frame, plumbing, insulation, waterproofing. Save the files in 06 Site Diary & Photos and log them here.
A3: Date | B3: Stage | C3: Location / element | D3: Hold point | E3: Before covering? | F3: Description | G3: Doc ID / file name | H3: Google Drive link | I3: Notes
B4: G4 | C4: Slab, north side | D4: Pre-slab | E4: Yes | F4: Mesh, bar chairs and edge beam before pour | G4: 06-PHO-001_Slab-mesh-north | I4: EXAMPLE: delete this row

Sheet Documents
A1: Document register
A2: Register every plan, permit, quote, contract, certificate and photo set. Pick the folder and type, type the number shown under 'Next free no.', and save the file with the name in column N.
A3: Folder | B3: Type | C3: No. | D3: Folder code | E3: Next free no. | F3: Doc ID | G3: Description | H3: Rev | I3: Date | J3: From / issued by | K3: Trade package | L3: Status | M3: Gateway | N3: Compliance ID | O3: File name to use | P3: Save in Drive folder | Q3: Folder | R3: Check | S3: File link | T3: Notes
A4: 02 | B4: DWG | C4: 1 | D4: =IF(A4="","",IF(ISNUMBER(A4),TEXT(A4,"00"),TRIM(A4))) | E4: {=IF(OR(D4="",B4=""),"",MAX(IF((D$4:D$303=D4)*(B$4:B$303=B4)*ISNUMBER(C$4:C$303),C$4:C$303,0))+1)} | F4: =IF(OR(D4="",B4="",NOT(ISNUMBER(C4))),"",D4&"-"&B4&"-"&TEXT(C4,"000")) | G4: Floor plan | H4: C | J4: Draftsperson | L4: Current | M4: G2 | N4: de-drawings | O4: =IF(F4="","",F4&"_"&SUBSTITUTE(SUBSTITUTE(SUBSTITUTE(SUBSTITUTE(SUBSTITUTE(SUBSTITUTE(SUBSTITUTE(SUBSTITUTE(SUBSTITUTE(SUBSTITUTE(TRIM(G4)," ","-"),"/","-"),"\","-"),":","-"),"*","-"),"?","-"),"""","-"),"<","-"),">","-"),"|","-")&IF(H4="","","_Rev"&H4)) | P4: =IF(D4="","",IF(L4="Superseded","99 Archive",IF(AND(D4="04",K4<>""),IFERROR(INDEX('Google Drive Map'!$B$4:$B$33,MATCH("04/"&LEFT(K4,2),'Google Drive Map'!$A$4:$A$33,0)),"04 Trades & Tenders/"&K4),IFERROR(INDEX('Google Drive Map'!$B$4:$B$33,MATCH(D4,'Google Drive Map'!$A$4:$A$33,0)),"")))) | Q4: =IF(P4="","",IF(IFERROR(INDEX('Google Drive Map'!$G$4:$G$33,MATCH(P4,'Google Drive Map'!$B$4:$B$33,0))&"","")="","",HYPERLINK(INDEX('Google Drive Map'!$G$4:$G$33,MATCH(P4,'Google Drive Map'!$B$4:$B$33,0)),"Open"))) | R4: =IF(AND(A4="",B4="",C4=""),"",TRIM(IF(AND(D4<>"",ISNA(MATCH(D4,'Google Drive Map'!$A$4:$A$33,0))),"Folder code isn't on the folder map. ","")&IF(AND(C4<>"",NOT(ISNUMBER(C4))),"No. must be a whole number. ","")&IF(AND(D4<>"",B4<>"",C4=""),"Type the next free no. ","")&IF(AND(F4<>"",COUNTIF(F$4:F$303,F4)>1),"Duplicate Doc ID. ",""))) | T4: EXAMPLE: delete this row
D5: =IF(A5="","",IF(ISNUMBER(A5),TEXT(A5,"00"),TRIM(A5))) | E5: {=IF(OR(D5="",B5=""),"",MAX(IF((D$4:D$303=D5)*(B$4:B$303=B5)*ISNUMBER(C$4:C$303),C$4:C$303,0))+1)} | F5: =IF(OR(D5="",B5="",NOT(ISNUMBER(C5))),"",D5&"-"&B5&"-"&TEXT(C5,"000")) | O5: =IF(F5="","",F5&"_"&SUBSTITUTE(SUBSTITUTE(SUBSTITUTE(SUBSTITUTE(SUBSTITUTE(SUBSTITUTE(SUBSTITUTE(SUBSTITUTE(SUBSTITUTE(SUBSTITUTE(TRIM(G5)," ","-"),"/","-"),"\","-"),":","-"),"*","-"),"?","-"),"""","-"),"<","-"),">","-"),"|","-")&IF(H5="","","_Rev"&H5)) | P5: =IF(D5="","",IF(L5="Superseded","99 Archive",IF(AND(D5="04",K5<>""),IFERROR(INDEX('Google Drive Map'!$B$4:$B$33,MATCH("04/"&LEFT(K5,2),'Google Drive Map'!$A$4:$A$33,0)),"04 Trades & Tenders/"&K5),IFERROR(INDEX('Google Drive Map'!$B$4:$B$33,MATCH(D5,'Google Drive Map'!$A$4:$A$33,0)),"")))) | Q5: =IF(P5="","",IF(IFERROR(INDEX('Google Drive Map'!$G$4:$G$33,MATCH(P5,'Google Drive Map'!$B$4:$B$33,0))&"","")="","",HYPERLINK(INDEX('Google Drive Map'!$G$4:$G$33,MATCH(P5,'Google Drive Map'!$B$4:$B$33,0)),"Open"))) | R5: =IF(AND(A5="",B5="",C5=""),"",TRIM(IF(AND(D5<>"",ISNA(MATCH(D5,'Google Drive Map'!$A$4:$A$33,0))),"Folder code isn't on the folder map. ","")&IF(AND(C5<>"",NOT(ISNUMBER(C5))),"No. must be a whole number. ","")&IF(AND(D5<>"",B5<>"",C5=""),"Type the next free no. ","")&IF(AND(F5<>"",COUNTIF(F$4:F$303,F5)>1),"Duplicate Doc ID. ","")))
D6: =IF(A6="","",IF(ISNUMBER(A6),TEXT(A6,"00"),TRIM(A6))) | E6: {=IF(OR(D6="",B6=""),"",MAX(IF((D$4:D$303=D6)*(B$4:B$303=B6)*ISNUMBER(C$4:C$303),C$4:C$303,0))+1)} | F6: =IF(OR(D6="",B6="",NOT(ISNUMBER(C6))),"",D6&"-"&B6&"-"&TEXT(C6,"000")) | O6: =IF(F6="","",F6&"_"&SUBSTITUTE(SUBSTITUTE(SUBSTITUTE(SUBSTITUTE(SUBSTITUTE(SUBSTITUTE(SUBSTITUTE(SUBSTITUTE(SUBSTITUTE(SUBSTITUTE(TRIM(G6)," ","-"),"/","-"),"\","-"),":","-"),"*","-"),"?","-"),"""","-"),"<","-"),">","-"),"|","-")&IF(H6="","","_Rev"&H6)) | P6: =IF(D6="","",IF(L6="Superseded","99 Archive",IF(AND(D6="04",K6<>""),IFERROR(INDEX('Google Drive Map'!$B$4:$B$33,MATCH("04/"&LEFT(K6,2),'Google Drive Map'!$A$4:$A$33,0)),"04 Trades & Tenders/"&K6),IFERROR(INDEX('Google Drive Map'!$B$4:$B$33,MATCH(D6,'Google Drive Map'!$A$4:$A$33,0)),"")))) | Q6: =IF(P6="","",IF(IFERROR(INDEX('Google Drive Map'!$G$4:$G$33,MATCH(P6,'Google Drive Map'!$B$4:$B$33,0))&"","")="","",HYPERLINK(INDEX('Google Drive Map'!$G$4:$G$33,MATCH(P6,'Google Drive Map'!$B$4:$B$33,0)),"Open"))) | R6: =IF(AND(A6="",B6="",C6=""),"",TRIM(IF(AND(D6<>"",ISNA(MATCH(D6,'Google Drive Map'!$A$4:$A$33,0))),"Folder code isn't on the folder map. ","")&IF(AND(C6<>"",NOT(ISNUMBER(C6))),"No. must be a whole number. ","")&IF(AND(D6<>"",B6<>"",C6=""),"Type the next free no. ","")&IF(AND(F6<>"",COUNTIF(F$4:F$303,F6)>1),"Duplicate Doc ID. ","")))
D7: =IF(A7="","",IF(ISNUMBER(A7),TEXT(A7,"00"),TRIM(A7))) | E7: {=IF(OR(D7="",B7=""),"",MAX(IF((D$4:D$303=D7)*(B$4:B$303=B7)*ISNUMBER(C$4:C$303),C$4:C$303,0))+1)} | F7: =IF(OR(D7="",B7="",NOT(ISNUMBER(C7))),"",D7&"-"&B7&"-"&TEXT(C7,"000")) | O7: =IF(F7="","",F7&"_"&SUBSTITUTE(SUBSTITUTE(SUBSTITUTE(SUBSTITUTE(SUBSTITUTE(SUBSTITUTE(SUBSTITUTE(SUBSTITUTE(SUBSTITUTE(SUBSTITUTE(TRIM(G7)," ","-"),"/","-"),"\","-"),":","-"),"*","-"),"?","-"),"""","-"),"<","-"),">","-"),"|","-")&IF(H7="","","_Rev"&H7)) | P7: =IF(D7="","",IF(L7="Superseded","99 Archive",IF(AND(D7="04",K7<>""),IFERROR(INDEX('Google Drive Map'!$B$4:$B$33,MATCH("04/"&LEFT(K7,2),'Google Drive Map'!$A$4:$A$33,0)),"04 Trades & Tenders/"&K7),IFERROR(INDEX('Google Drive Map'!$B$4:$B$33,MATCH(D7,'Google Drive Map'!$A$4:$A$33,0)),"")))) | Q7: =IF(P7="","",IF(IFERROR(INDEX('Google Drive Map'!$G$4:$G$33,MATCH(P7,'Google Drive Map'!$B$4:$B$33,0))&"","")="","",HYPERLINK(INDEX('Google Drive Map'!$G$4:$G$33,MATCH(P7,'Google Drive Map'!$B$4:$B$33,0)),"Open"))) | R7: =IF(AND(A7="",B7="",C7=""),"",TRIM(IF(AND(D7<>"",ISNA(MATCH(D7,'Google Drive Map'!$A$4:$A$33,0))),"Folder code isn't on the folder map. ","")&IF(AND(C7<>"",NOT(ISNUMBER(C7))),"No. must be a whole number. ","")&IF(AND(D7<>"",B7<>"",C7=""),"Type the next free no. ","")&IF(AND(F7<>"",COUNTIF(F$4:F$303,F7)>1),"Duplicate Doc ID. ","")))
D8: =IF(A8="","",IF(ISNUMBER(A8),TEXT(A8,"00"),TRIM(A8))) | E8: {=IF(OR(D8="",B8=""),"",MAX(IF((D$4:D$303=D8)*(B$4:B$303=B8)*ISNUMBER(C$4:C$303),C$4:C$303,0))+1)} | F8: =IF(OR(D8="",B8="",NOT(ISNUMBER(C8))),"",D8&"-"&B8&"-"&TEXT(C8,"000")) | O8: =IF(F8="","",F8&"_"&SUBSTITUTE(SUBSTITUTE(SUBSTITUTE(SUBSTITUTE(SUBSTITUTE(SUBSTITUTE(SUBSTITUTE(SUBSTITUTE(SUBSTITUTE(SUBSTITUTE(TRIM(G8)," ","-"),"/","-"),"\","-"),":","-"),"*","-"),"?","-"),"""","-"),"<","-"),">","-"),"|","-")&IF(H8="","","_Rev"&H8)) | P8: =IF(D8="","",IF(L8="Superseded","99 Archive",IF(AND(D8="04",K8<>""),IFERROR(INDEX('Google Drive Map'!$B$4:$B$33,MATCH("04/"&LEFT(K8,2),'Google Drive Map'!$A$4:$A$33,0)),"04 Trades & Tenders/"&K8),IFERROR(INDEX('Google Drive Map'!$B$4:$B$33,MATCH(D8,'Google Drive Map'!$A$4:$A$33,0)),"")))) | Q8: =IF(P8="","",IF(IFERROR(INDEX('Google Drive Map'!$G$4:$G$33,MATCH(P8,'Google Drive Map'!$B$4:$B$33,0))&"","")="","",HYPERLINK(INDEX('Google Drive Map'!$G$4:$G$33,MATCH(P8,'Google Drive Map'!$B$4:$B$33,0)),"Open"))) | R8: =IF(AND(A8="",B8="",C8=""),"",TRIM(IF(AND(D8<>"",ISNA(MATCH(D8,'Google Drive Map'!$A$4:$A$33,0))),"Folder code isn't on the folder map. ","")&IF(AND(C8<>"",NOT(ISNUMBER(C8))),"No. must be a whole number. ","")&IF(AND(D8<>"",B8<>"",C8=""),"Type the next free no. ","")&IF(AND(F8<>"",COUNTIF(F$4:F$303,F8)>1),"Duplicate Doc ID. ","")))
D9: =IF(A9="","",IF(ISNUMBER(A9),TEXT(A9,"00"),TRIM(A9))) | E9: {=IF(OR(D9="",B9=""),"",MAX(IF((D$4:D$303=D9)*(B$4:B$303=B9)*ISNUMBER(C$4:C$303),C$4:C$303,0))+1)} | F9: =IF(OR(D9="",B9="",NOT(ISNUMBER(C9))),"",D9&"-"&B9&"-"&TEXT(C9,"000")) | O9: =IF(F9="","",F9&"_"&SUBSTITUTE(SUBSTITUTE(SUBSTITUTE(SUBSTITUTE(SUBSTITUTE(SUBSTITUTE(SUBSTITUTE(SUBSTITUTE(SUBSTITUTE(SUBSTITUTE(TRIM(G9)," ","-"),"/","-"),"\","-"),":","-"),"*","-"),"?","-"),"""","-"),"<","-"),">","-"),"|","-")&IF(H9="","","_Rev"&H9)) | P9: =IF(D9="","",IF(L9="Superseded","99 Archive",IF(AND(D9="04",K9<>""),IFERROR(INDEX('Google Drive Map'!$B$4:$B$33,MATCH("04/"&LEFT(K9,2),'Google Drive Map'!$A$4:$A$33,0)),"04 Trades & Tenders/"&K9),IFERROR(INDEX('Google Drive Map'!$B$4:$B$33,MATCH(D9,'Google Drive Map'!$A$4:$A$33,0)),"")))) | Q9: =IF(P9="","",IF(IFERROR(INDEX('Google Drive Map'!$G$4:$G$33,MATCH(P9,'Google Drive Map'!$B$4:$B$33,0))&"","")="","",HYPERLINK(INDEX('Google Drive Map'!$G$4:$G$33,MATCH(P9,'Google Drive Map'!$B$4:$B$33,0)),"Open"))) | R9: =IF(AND(A9="",B9="",C9=""),"",TRIM(IF(AND(D9<>"",ISNA(MATCH(D9,'Google Drive Map'!$A$4:$A$33,0))),"Folder code isn't on the folder map. ","")&IF(AND(C9<>"",NOT(ISNUMBER(C9))),"No. must be a whole number. ","")&IF(AND(D9<>"",B9<>"",C9=""),"Type the next free no. ","")&IF(AND(F9<>"",COUNTIF(F$4:F$303,F9)>1),"Duplicate Doc ID. ","")))
D10: =IF(A10="","",IF(ISNUMBER(A10),TEXT(A10,"00"),TRIM(A10))) | E10: {=IF(OR(D10="",B10=""),"",MAX(IF((D$4:D$303=D10)*(B$4:B$303=B10)*ISNUMBER(C$4:C$303),C$4:C$303,0))+1)} | F10: =IF(OR(D10="",B10="",NOT(ISNUMBER(C10))),"",D10&"-"&B10&"-"&TEXT(C10,"000")) | O10: =IF(F10="","",F10&"_"&SUBSTITUTE(SUBSTITUTE(SUBSTITUTE(SUBSTITUTE(SUBSTITUTE(SUBSTITUTE(SUBSTITUTE(SUBSTITUTE(SUBSTITUTE(SUBSTITUTE(TRIM(G10)," ","-"),"/","-"),"\","-"),":","-"),"*","-"),"?","-"),"""","-"),"<","-"),">","-"),"|","-")&IF(H10="","","_Rev"&H10)) | P10: =IF(D10="","",IF(L10="Superseded","99 Archive",IF(AND(D10="04",K10<>""),IFERROR(INDEX('Google Drive Map'!$B$4:$B$33,MATCH("04/"&LEFT(K10,2),'Google Drive Map'!$A$4:$A$33,0)),"04 Trades & Tenders/"&K10),IFERROR(INDEX('Google Drive Map'!$B$4:$B$33,MATCH(D10,'Google Drive Map'!$A$4:$A$33,0)),"")))) | Q10: =IF(P10="","",IF(IFERROR(INDEX('Google Drive Map'!$G$4:$G$33,MATCH(P10,'Google Drive Map'!$B$4:$B$33,0))&"","")="","",HYPERLINK(INDEX('Google Drive Map'!$G$4:$G$33,MATCH(P10,'Google Drive Map'!$B$4:$B$33,0)),"Open"))) | R10: =IF(AND(A10="",B10="",C10=""),"",TRIM(IF(AND(D10<>"",ISNA(MATCH(D10,'Google Drive Map'!$A$4:$A$33,0))),"Folder code isn't on the folder map. ","")&IF(AND(C10<>"",NOT(ISNUMBER(C10))),"No. must be a whole number. ","")&IF(AND(D10<>"",B10<>"",C10=""),"Type the next free no. ","")&IF(AND(F10<>"",COUNTIF(F$4:F$303,F10)>1),"Duplicate Doc ID. ","")))
D11: =IF(A11="","",IF(ISNUMBER(A11),TEXT(A11,"00"),TRIM(A11))) | E11: {=IF(OR(D11="",B11=""),"",MAX(IF((D$4:D$303=D11)*(B$4:B$303=B11)*ISNUMBER(C$4:C$303),C$4:C$303,0))+1)} | F11: =IF(OR(D11="",B11="",NOT(ISNUMBER(C11))),"",D11&"-"&B11&"-"&TEXT(C11,"000")) | O11: =IF(F11="","",F11&"_"&SUBSTITUTE(SUBSTITUTE(SUBSTITUTE(SUBSTITUTE(SUBSTITUTE(SUBSTITUTE(SUBSTITUTE(SUBSTITUTE(SUBSTITUTE(SUBSTITUTE(TRIM(G11)," ","-"),"/","-"),"\","-"),":","-"),"*","-"),"?","-"),"""","-"),"<","-"),">","-"),"|","-")&IF(H11="","","_Rev"&H11)) | P11: =IF(D11="","",IF(L11="Superseded","99 Archive",IF(AND(D11="04",K11<>""),IFERROR(INDEX('Google Drive Map'!$B$4:$B$33,MATCH("04/"&LEFT(K11,2),'Google Drive Map'!$A$4:$A$33,0)),"04 Trades & Tenders/"&K11),IFERROR(INDEX('Google Drive Map'!$B$4:$B$33,MATCH(D11,'Google Drive Map'!$A$4:$A$33,0)),"")))) | Q11: =IF(P11="","",IF(IFERROR(INDEX('Google Drive Map'!$G$4:$G$33,MATCH(P11,'Google Drive Map'!$B$4:$B$33,0))&"","")="","",HYPERLINK(INDEX('Google Drive Map'!$G$4:$G$33,MATCH(P11,'Google Drive Map'!$B$4:$B$33,0)),"Open"))) | R11: =IF(AND(A11="",B11="",C11=""),"",TRIM(IF(AND(D11<>"",ISNA(MATCH(D11,'Google Drive Map'!$A$4:$A$33,0))),"Folder code isn't on the folder map. ","")&IF(AND(C11<>"",NOT(ISNUMBER(C11))),"No. must be a whole number. ","")&IF(AND(D11<>"",B11<>"",C11=""),"Type the next free no. ","")&IF(AND(F11<>"",COUNTIF(F$4:F$303,F11)>1),"Duplicate Doc ID. ","")))
D12: =IF(A12="","",IF(ISNUMBER(A12),TEXT(A12,"00"),TRIM(A12))) | E12: {=IF(OR(D12="",B12=""),"",MAX(IF((D$4:D$303=D12)*(B$4:B$303=B12)*ISNUMBER(C$4:C$303),C$4:C$303,0))+1)} | F12: =IF(OR(D12="",B12="",NOT(ISNUMBER(C12))),"",D12&"-"&B12&"-"&TEXT(C12,"000")) | O12: =IF(F12="","",F12&"_"&SUBSTITUTE(SUBSTITUTE(SUBSTITUTE(SUBSTITUTE(SUBSTITUTE(SUBSTITUTE(SUBSTITUTE(SUBSTITUTE(SUBSTITUTE(SUBSTITUTE(TRIM(G12)," ","-"),"/","-"),"\","-"),":","-"),"*","-"),"?","-"),"""","-"),"<","-"),">","-"),"|","-")&IF(H12="","","_Rev"&H12)) | P12: =IF(D12="","",IF(L12="Superseded","99 Archive",IF(AND(D12="04",K12<>""),IFERROR(INDEX('Google Drive Map'!$B$4:$B$33,MATCH("04/"&LEFT(K12,2),'Google Drive Map'!$A$4:$A$33,0)),"04 Trades & Tenders/"&K12),IFERROR(INDEX('Google Drive Map'!$B$4:$B$33,MATCH(D12,'Google Drive Map'!$A$4:$A$33,0)),"")))) | Q12: =IF(P12="","",IF(IFERROR(INDEX('Google Drive Map'!$G$4:$G$33,MATCH(P12,'Google Drive Map'!$B$4:$B$33,0))&"","")="","",HYPERLINK(INDEX('Google Drive Map'!$G$4:$G$33,MATCH(P12,'Google Drive Map'!$B$4:$B$33,0)),"Open"))) | R12: =IF(AND(A12="",B12="",C12=""),"",TRIM(IF(AND(D12<>"",ISNA(MATCH(D12,'Google Drive Map'!$A$4:$A$33,0))),"Folder code isn't on the folder map. ","")&IF(AND(C12<>"",NOT(ISNUMBER(C12))),"No. must be a whole number. ","")&IF(AND(D12<>"",B12<>"",C12=""),"Type the next free no. ","")&IF(AND(F12<>"",COUNTIF(F$4:F$303,F12)>1),"Duplicate Doc ID. ","")))
D13: =IF(A13="","",IF(ISNUMBER(A13),TEXT(A13,"00"),TRIM(A13))) | E13: {=IF(OR(D13="",B13=""),"",MAX(IF((D$4:D$303=D13)*(B$4:B$303=B13)*ISNUMBER(C$4:C$303),C$4:C$303,0))+1)} | F13: =IF(OR(D13="",B13="",NOT(ISNUMBER(C13))),"",D13&"-"&B13&"-"&TEXT(C13,"000")) | O13: =IF(F13="","",F13&"_"&SUBSTITUTE(SUBSTITUTE(SUBSTITUTE(SUBSTITUTE(SUBSTITUTE(SUBSTITUTE(SUBSTITUTE(SUBSTITUTE(SUBSTITUTE(SUBSTITUTE(TRIM(G13)," ","-"),"/","-"),"\","-"),":","-"),"*","-"),"?","-"),"""","-"),"<","-"),">","-"),"|","-")&IF(H13="","","_Rev"&H13)) | P13: =IF(D13="","",IF(L13="Superseded","99 Archive",IF(AND(D13="04",K13<>""),IFERROR(INDEX('Google Drive Map'!$B$4:$B$33,MATCH("04/"&LEFT(K13,2),'Google Drive Map'!$A$4:$A$33,0)),"04 Trades & Tenders/"&K13),IFERROR(INDEX('Google Drive Map'!$B$4:$B$33,MATCH(D13,'Google Drive Map'!$A$4:$A$33,0)),"")))) | Q13: =IF(P13="","",IF(IFERROR(INDEX('Google Drive Map'!$G$4:$G$33,MATCH(P13,'Google Drive Map'!$B$4:$B$33,0))&"","")="","",HYPERLINK(INDEX('Google Drive Map'!$G$4:$G$33,MATCH(P13,'Google Drive Map'!$B$4:$B$33,0)),"Open"))) | R13: =IF(AND(A13="",B13="",C13=""),"",TRIM(IF(AND(D13<>"",ISNA(MATCH(D13,'Google Drive Map'!$A$4:$A$33,0))),"Folder code isn't on the folder map. ","")&IF(AND(C13<>"",NOT(ISNUMBER(C13))),"No. must be a whole number. ","")&IF(AND(D13<>"",B13<>"",C13=""),"Type the next free no. ","")&IF(AND(F13<>"",COUNTIF(F$4:F$303,F13)>1),"Duplicate Doc ID. ","")))
D14: =IF(A14="","",IF(ISNUMBER(A14),TEXT(A14,"00"),TRIM(A14))) | E14: {=IF(OR(D14="",B14=""),"",MAX(IF((D$4:D$303=D14)*(B$4:B$303=B14)*ISNUMBER(C$4:C$303),C$4:C$303,0))+1)} | F14: =IF(OR(D14="",B14="",NOT(ISNUMBER(C14))),"",D14&"-"&B14&"-"&TEXT(C14,"000")) | O14: =IF(F14="","",F14&"_"&SUBSTITUTE(SUBSTITUTE(SUBSTITUTE(SUBSTITUTE(SUBSTITUTE(SUBSTITUTE(SUBSTITUTE(SUBSTITUTE(SUBSTITUTE(SUBSTITUTE(TRIM(G14)," ","-"),"/","-"),"\","-"),":","-"),"*","-"),"?","-"),"""","-"),"<","-"),">","-"),"|","-")&IF(H14="","","_Rev"&H14)) | P14: =IF(D14="","",IF(L14="Superseded","99 Archive",IF(AND(D14="04",K14<>""),IFERROR(INDEX('Google Drive Map'!$B$4:$B$33,MATCH("04/"&LEFT(K14,2),'Google Drive Map'!$A$4:$A$33,0)),"04 Trades & Tenders/"&K14),IFERROR(INDEX('Google Drive Map'!$B$4:$B$33,MATCH(D14,'Google Drive Map'!$A$4:$A$33,0)),"")))) | Q14: =IF(P14="","",IF(IFERROR(INDEX('Google Drive Map'!$G$4:$G$33,MATCH(P14,'Google Drive Map'!$B$4:$B$33,0))&"","")="","",HYPERLINK(INDEX('Google Drive Map'!$G$4:$G$33,MATCH(P14,'Google Drive Map'!$B$4:$B$33,0)),"Open"))) | R14: =IF(AND(A14="",B14="",C14=""),"",TRIM(IF(AND(D14<>"",ISNA(MATCH(D14,'Google Drive Map'!$A$4:$A$33,0))),"Folder code isn't on the folder map. ","")&IF(AND(C14<>"",NOT(ISNUMBER(C14))),"No. must be a whole number. ","")&IF(AND(D14<>"",B14<>"",C14=""),"Type the next free no. ","")&IF(AND(F14<>"",COUNTIF(F$4:F$303,F14)>1),"Duplicate Doc ID. ","")))
D15: =IF(A15="","",IF(ISNUMBER(A15),TEXT(A15,"00"),TRIM(A15))) | E15: {=IF(OR(D15="",B15=""),"",MAX(IF((D$4:D$303=D15)*(B$4:B$303=B15)*ISNUMBER(C$4:C$303),C$4:C$303,0))+1)} | F15: =IF(OR(D15="",B15="",NOT(ISNUMBER(C15))),"",D15&"-"&B15&"-"&TEXT(C15,"000")) | O15: =IF(F15="","",F15&"_"&SUBSTITUTE(SUBSTITUTE(SUBSTITUTE(SUBSTITUTE(SUBSTITUTE(SUBSTITUTE(SUBSTITUTE(SUBSTITUTE(SUBSTITUTE(SUBSTITUTE(TRIM(G15)," ","-"),"/","-"),"\","-"),":","-"),"*","-"),"?","-"),"""","-"),"<","-"),">","-"),"|","-")&IF(H15="","","_Rev"&H15)) | P15: =IF(D15="","",IF(L15="Superseded","99 Archive",IF(AND(D15="04",K15<>""),IFERROR(INDEX('Google Drive Map'!$B$4:$B$33,MATCH("04/"&LEFT(K15,2),'Google Drive Map'!$A$4:$A$33,0)),"04 Trades & Tenders/"&K15),IFERROR(INDEX('Google Drive Map'!$B$4:$B$33,MATCH(D15,'Google Drive Map'!$A$4:$A$33,0)),"")))) | Q15: =IF(P15="","",IF(IFERROR(INDEX('Google Drive Map'!$G$4:$G$33,MATCH(P15,'Google Drive Map'!$B$4:$B$33,0))&"","")="","",HYPERLINK(INDEX('Google Drive Map'!$G$4:$G$33,MATCH(P15,'Google Drive Map'!$B$4:$B$33,0)),"Open"))) | R15: =IF(AND(A15="",B15="",C15=""),"",TRIM(IF(AND(D15<>"",ISNA(MATCH(D15,'Google Drive Map'!$A$4:$A$33,0))),"Folder code isn't on the folder map. ","")&IF(AND(C15<>"",NOT(ISNUMBER(C15))),"No. must be a whole number. ","")&IF(AND(D15<>"",B15<>"",C15=""),"Type the next free no. ","")&IF(AND(F15<>"",COUNTIF(F$4:F$303,F15)>1),"Duplicate Doc ID. ","")))
D16: =IF(A16="","",IF(ISNUMBER(A16),TEXT(A16,"00"),TRIM(A16))) | E16: {=IF(OR(D16="",B16=""),"",MAX(IF((D$4:D$303=D16)*(B$4:B$303=B16)*ISNUMBER(C$4:C$303),C$4:C$303,0))+1)} | F16: =IF(OR(D16="",B16="",NOT(ISNUMBER(C16))),"",D16&"-"&B16&"-"&TEXT(C16,"000")) | O16: =IF(F16="","",F16&"_"&SUBSTITUTE(SUBSTITUTE(SUBSTITUTE(SUBSTITUTE(SUBSTITUTE(SUBSTITUTE(SUBSTITUTE(SUBSTITUTE(SUBSTITUTE(SUBSTITUTE(TRIM(G16)," ","-"),"/","-"),"\","-"),":","-"),"*","-"),"?","-"),"""","-"),"<","-"),">","-"),"|","-")&IF(H16="","","_Rev"&H16)) | P16: =IF(D16="","",IF(L16="Superseded","99 Archive",IF(AND(D16="04",K16<>""),IFERROR(INDEX('Google Drive Map'!$B$4:$B$33,MATCH("04/"&LEFT(K16,2),'Google Drive Map'!$A$4:$A$33,0)),"04 Trades & Tenders/"&K16),IFERROR(INDEX('Google Drive Map'!$B$4:$B$33,MATCH(D16,'Google Drive Map'!$A$4:$A$33,0)),"")))) | Q16: =IF(P16="","",IF(IFERROR(INDEX('Google Drive Map'!$G$4:$G$33,MATCH(P16,'Google Drive Map'!$B$4:$B$33,0))&"","")="","",HYPERLINK(INDEX('Google Drive Map'!$G$4:$G$33,MATCH(P16,'Google Drive Map'!$B$4:$B$33,0)),"Open"))) | R16: =IF(AND(A16="",B16="",C16=""),"",TRIM(IF(AND(D16<>"",ISNA(MATCH(D16,'Google Drive Map'!$A$4:$A$33,0))),"Folder code isn't on the folder map. ","")&IF(AND(C16<>"",NOT(ISNUMBER(C16))),"No. must be a whole number. ","")&IF(AND(D16<>"",B16<>"",C16=""),"Type the next free no. ","")&IF(AND(F16<>"",COUNTIF(F$4:F$303,F16)>1),"Duplicate Doc ID. ","")))
... D303: =IF(A303="","",IF(ISNUMBER(A303),TEXT(A303,"00"),TRIM(A303))) | E303: {=IF(OR(D303="",B303=""),"",MAX(IF((D$4:D$303=D303)*(B$4:B$303=B303)*ISNUMBER(C$4:C$303),C$4:C$303,0))+1)} | F303: =IF(OR(D303="",B303="",NOT(ISNUMBER(C303))),"",D303&"-"&B303&"-"&TEXT(C303,"000")) | O303: =IF(F303="","",F303&"_"&SUBSTITUTE(SUBSTITUTE(SUBSTITUTE(SUBSTITUTE(SUBSTITUTE(SUBSTITUTE(SUBSTITUTE(SUBSTITUTE(SUBSTITUTE(SUBSTITUTE(TRIM(G303)," ","-"),"/","-"),"\","-"),":","-"),"*","-"),"?","-"),"""","-"),"<","-"),">","-"),"|","-")&IF(H303="","","_Rev"&H303)) | P303: =IF(D303="","",IF(L303="Superseded","99 Archive",IF(AND(D303="04",K303<>""),IFERROR(INDEX('Google Drive Map'!$B$4:$B$33,MATCH("04/"&LEFT(K303,2),'Google Drive Map'!$A$4:$A$33,0)),"04 Trades & Tenders/"&K303),IFERROR(INDEX('Google Drive Map'!$B$4:$B$33,MATCH(D303,'Google Drive Map'!$A$4:$A$33,0)),"")))) | Q303: =IF(P303="","",IF(IFERROR(INDEX('Google Drive Map'!$G$4:$G$33,MATCH(P303,'Google Drive Map'!$B$4:$B$33,0))&"","")="","",HYPERLINK(INDEX('Google Drive Map'!$G$4:$G$33,MATCH(P303,'Google Drive Map'!$B$4:$B$33,0)),"Open"))) | R303: =IF(AND(A303="",B303="",C303=""),"",TRIM(IF(AND(D303<>"",ISNA(MATCH(D303,'Google Drive Map'!$A$4:$A$33,0))),"Folder code isn't on the folder map. ","")&IF(AND(C303<>"",NOT(ISNUMBER(C303))),"No. must be a whole number. ","")&IF(AND(D303<>"",B303<>"",C303=""),"Type the next free no. ","")&IF(AND(F303<>"",COUNTIF(F$4:F$303,F303)>1),"Duplicate Doc ID. ","")))

Sheet Tender Setup
A1: Tender weights & recommendations
A2: Set the scoring weights for each package (they must add to 100). The recommendation updates as you enter quotes on the Tenders tab.
A3: Package | B3: Budget ($) | C3: Price % | D3: Experience % | E3: Program % | F3: Quality % | G3: Comms % | H3: Warranty % | I3: Total % | J3: Compliant tenders | K3: Recommended | L3: Score /100 | M3: Levelled price ($) | N3: Over / (under) budget ($) | O3: Lead over #2 (points) | P3: Notes
A4: =IF('Packages'!B4="","",'Packages'!B4) | B4: =IF('Packages'!H4="","",'Packages'!H4) | C4: 50 | D4: 15 | E4: 15 | F4: 10 | G4: 5 | H4: 5 | I4: =IF(A4="","",SUM(C4:H4)) | J4: =IF($A4="","",COUNTIFS('Tenders'!$T$4:$T$103,LEFT($A4,2),'Tenders'!$I$4:$I$103,"Yes")) | K4: =IF($A4="","",IF(COUNTIF('Tenders'!$AD$4:$AD$103,LEFT($A4,2)&"|1")>1,"Tie: "&COUNTIF('Tenders'!$AD$4:$AD$103,LEFT($A4,2)&"|1")&" quotes share 1st",IFERROR(INDEX('Tenders'!$B$4:$B$103,MATCH(LEFT($A4,2)&"|1",'Tenders'!$AD$4:$AD$103,0)),""))) | L4: =IF($A4="","",IFERROR(INDEX('Tenders'!$Z$4:$Z$103,MATCH(LEFT($A4,2)&"|1",'Tenders'!$AD$4:$AD$103,0)),"")) | M4: =IF(OR($A4="",COUNTIF('Tenders'!$AD$4:$AD$103,LEFT($A4,2)&"|1")>1),"",IFERROR(INDEX('Tenders'!$N$4:$N$103,MATCH(LEFT($A4,2)&"|1",'Tenders'!$AD$4:$AD$103,0)),"")) | N4: =IF(OR(M4="",N(B4)=0),"",M4-B4) | O4: =IF(OR($A4="",COUNTIF('Tenders'!$AD$4:$AD$103,LEFT($A4,2)&"|1")>1),"",IFERROR(L4-INDEX('Tenders'!$Z$4:$Z$103,MATCH(LEFT($A4,2)&"|2",'Tenders'!$AD$4:$AD$103,0)),""))
A5: =IF('Packages'!B5="","",'Packages'!B5) | B5: =IF('Packages'!H5="","",'Packages'!H5) | C5: 50 | D5: 15 | E5: 15 | F5: 10 | G5: 5 | H5: 5 | I5: =IF(A5="","",SUM(C5:H5)) | J5: =IF($A5="","",COUNTIFS('Tenders'!$T$4:$T$103,LEFT($A5,2),'Tenders'!$I$4:$I$103,"Yes")) | K5: =IF($A5="","",IF(COUNTIF('Tenders'!$AD$4:$AD$103,LEFT($A5,2)&"|1")>1,"Tie: "&COUNTIF('Tenders'!$AD$4:$AD$103,LEFT($A5,2)&"|1")&" quotes share 1st",IFERROR(INDEX('Tenders'!$B$4:$B$103,MATCH(LEFT($A5,2)&"|1",'Tenders'!$AD$4:$AD$103,0)),""))) | L5: =IF($A5="","",IFERROR(INDEX('Tenders'!$Z$4:$Z$103,MATCH(LEFT($A5,2)&"|1",'Tenders'!$AD$4:$AD$103,0)),"")) | M5: =IF(OR($A5="",COUNTIF('Tenders'!$AD$4:$AD$103,LEFT($A5,2)&"|1")>1),"",IFERROR(INDEX('Tenders'!$N$4:$N$103,MATCH(LEFT($A5,2)&"|1",'Tenders'!$AD$4:$AD$103,0)),"")) | N5: =IF(OR(M5="",N(B5)=0),"",M5-B5) | O5: =IF(OR($A5="",COUNTIF('Tenders'!$AD$4:$AD$103,LEFT($A5,2)&"|1")>1),"",IFERROR(L5-INDEX('Tenders'!$Z$4:$Z$103,MATCH(LEFT($A5,2)&"|2",'Tenders'!$AD$4:$AD$103,0)),""))
A6: =IF('Packages'!B6="","",'Packages'!B6) | B6: =IF('Packages'!H6="","",'Packages'!H6) | C6: 50 | D6: 15 | E6: 15 | F6: 10 | G6: 5 | H6: 5 | I6: =IF(A6="","",SUM(C6:H6)) | J6: =IF($A6="","",COUNTIFS('Tenders'!$T$4:$T$103,LEFT($A6,2),'Tenders'!$I$4:$I$103,"Yes")) | K6: =IF($A6="","",IF(COUNTIF('Tenders'!$AD$4:$AD$103,LEFT($A6,2)&"|1")>1,"Tie: "&COUNTIF('Tenders'!$AD$4:$AD$103,LEFT($A6,2)&"|1")&" quotes share 1st",IFERROR(INDEX('Tenders'!$B$4:$B$103,MATCH(LEFT($A6,2)&"|1",'Tenders'!$AD$4:$AD$103,0)),""))) | L6: =IF($A6="","",IFERROR(INDEX('Tenders'!$Z$4:$Z$103,MATCH(LEFT($A6,2)&"|1",'Tenders'!$AD$4:$AD$103,0)),"")) | M6: =IF(OR($A6="",COUNTIF('Tenders'!$AD$4:$AD$103,LEFT($A6,2)&"|1")>1),"",IFERROR(INDEX('Tenders'!$N$4:$N$103,MATCH(LEFT($A6,2)&"|1",'Tenders'!$AD$4:$AD$103,0)),"")) | N6: =IF(OR(M6="",N(B6)=0),"",M6-B6) | O6: =IF(OR($A6="",COUNTIF('Tenders'!$AD$4:$AD$103,LEFT($A6,2)&"|1")>1),"",IFERROR(L6-INDEX('Tenders'!$Z$4:$Z$103,MATCH(LEFT($A6,2)&"|2",'Tenders'!$AD$4:$AD$103,0)),""))
A7: =IF('Packages'!B7="","",'Packages'!B7) | B7: =IF('Packages'!H7="","",'Packages'!H7) | C7: 50 | D7: 15 | E7: 15 | F7: 10 | G7: 5 | H7: 5 | I7: =IF(A7="","",SUM(C7:H7)) | J7: =IF($A7="","",COUNTIFS('Tenders'!$T$4:$T$103,LEFT($A7,2),'Tenders'!$I$4:$I$103,"Yes")) | K7: =IF($A7="","",IF(COUNTIF('Tenders'!$AD$4:$AD$103,LEFT($A7,2)&"|1")>1,"Tie: "&COUNTIF('Tenders'!$AD$4:$AD$103,LEFT($A7,2)&"|1")&" quotes share 1st",IFERROR(INDEX('Tenders'!$B$4:$B$103,MATCH(LEFT($A7,2)&"|1",'Tenders'!$AD$4:$AD$103,0)),""))) | L7: =IF($A7="","",IFERROR(INDEX('Tenders'!$Z$4:$Z$103,MATCH(LEFT($A7,2)&"|1",'Tenders'!$AD$4:$AD$103,0)),"")) | M7: =IF(OR($A7="",COUNTIF('Tenders'!$AD$4:$AD$103,LEFT($A7,2)&"|1")>1),"",IFERROR(INDEX('Tenders'!$N$4:$N$103,MATCH(LEFT($A7,2)&"|1",'Tenders'!$AD$4:$AD$103,0)),"")) | N7: =IF(OR(M7="",N(B7)=0),"",M7-B7) | O7: =IF(OR($A7="",COUNTIF('Tenders'!$AD$4:$AD$103,LEFT($A7,2)&"|1")>1),"",IFERROR(L7-INDEX('Tenders'!$Z$4:$Z$103,MATCH(LEFT($A7,2)&"|2",'Tenders'!$AD$4:$AD$103,0)),""))
A8: =IF('Packages'!B8="","",'Packages'!B8) | B8: =IF('Packages'!H8="","",'Packages'!H8) | C8: 50 | D8: 15 | E8: 15 | F8: 10 | G8: 5 | H8: 5 | I8: =IF(A8="","",SUM(C8:H8)) | J8: =IF($A8="","",COUNTIFS('Tenders'!$T$4:$T$103,LEFT($A8,2),'Tenders'!$I$4:$I$103,"Yes")) | K8: =IF($A8="","",IF(COUNTIF('Tenders'!$AD$4:$AD$103,LEFT($A8,2)&"|1")>1,"Tie: "&COUNTIF('Tenders'!$AD$4:$AD$103,LEFT($A8,2)&"|1")&" quotes share 1st",IFERROR(INDEX('Tenders'!$B$4:$B$103,MATCH(LEFT($A8,2)&"|1",'Tenders'!$AD$4:$AD$103,0)),""))) | L8: =IF($A8="","",IFERROR(INDEX('Tenders'!$Z$4:$Z$103,MATCH(LEFT($A8,2)&"|1",'Tenders'!$AD$4:$AD$103,0)),"")) | M8: =IF(OR($A8="",COUNTIF('Tenders'!$AD$4:$AD$103,LEFT($A8,2)&"|1")>1),"",IFERROR(INDEX('Tenders'!$N$4:$N$103,MATCH(LEFT($A8,2)&"|1",'Tenders'!$AD$4:$AD$103,0)),"")) | N8: =IF(OR(M8="",N(B8)=0),"",M8-B8) | O8: =IF(OR($A8="",COUNTIF('Tenders'!$AD$4:$AD$103,LEFT($A8,2)&"|1")>1),"",IFERROR(L8-INDEX('Tenders'!$Z$4:$Z$103,MATCH(LEFT($A8,2)&"|2",'Tenders'!$AD$4:$AD$103,0)),""))
A9: =IF('Packages'!B9="","",'Packages'!B9) | B9: =IF('Packages'!H9="","",'Packages'!H9) | C9: 50 | D9: 15 | E9: 15 | F9: 10 | G9: 5 | H9: 5 | I9: =IF(A9="","",SUM(C9:H9)) | J9: =IF($A9="","",COUNTIFS('Tenders'!$T$4:$T$103,LEFT($A9,2),'Tenders'!$I$4:$I$103,"Yes")) | K9: =IF($A9="","",IF(COUNTIF('Tenders'!$AD$4:$AD$103,LEFT($A9,2)&"|1")>1,"Tie: "&COUNTIF('Tenders'!$AD$4:$AD$103,LEFT($A9,2)&"|1")&" quotes share 1st",IFERROR(INDEX('Tenders'!$B$4:$B$103,MATCH(LEFT($A9,2)&"|1",'Tenders'!$AD$4:$AD$103,0)),""))) | L9: =IF($A9="","",IFERROR(INDEX('Tenders'!$Z$4:$Z$103,MATCH(LEFT($A9,2)&"|1",'Tenders'!$AD$4:$AD$103,0)),"")) | M9: =IF(OR($A9="",COUNTIF('Tenders'!$AD$4:$AD$103,LEFT($A9,2)&"|1")>1),"",IFERROR(INDEX('Tenders'!$N$4:$N$103,MATCH(LEFT($A9,2)&"|1",'Tenders'!$AD$4:$AD$103,0)),"")) | N9: =IF(OR(M9="",N(B9)=0),"",M9-B9) | O9: =IF(OR($A9="",COUNTIF('Tenders'!$AD$4:$AD$103,LEFT($A9,2)&"|1")>1),"",IFERROR(L9-INDEX('Tenders'!$Z$4:$Z$103,MATCH(LEFT($A9,2)&"|2",'Tenders'!$AD$4:$AD$103,0)),""))
A10: =IF('Packages'!B10="","",'Packages'!B10) | B10: =IF('Packages'!H10="","",'Packages'!H10) | C10: 50 | D10: 15 | E10: 15 | F10: 10 | G10: 5 | H10: 5 | I10: =IF(A10="","",SUM(C10:H10)) | J10: =IF($A10="","",COUNTIFS('Tenders'!$T$4:$T$103,LEFT($A10,2),'Tenders'!$I$4:$I$103,"Yes")) | K10: =IF($A10="","",IF(COUNTIF('Tenders'!$AD$4:$AD$103,LEFT($A10,2)&"|1")>1,"Tie: "&COUNTIF('Tenders'!$AD$4:$AD$103,LEFT($A10,2)&"|1")&" quotes share 1st",IFERROR(INDEX('Tenders'!$B$4:$B$103,MATCH(LEFT($A10,2)&"|1",'Tenders'!$AD$4:$AD$103,0)),""))) | L10: =IF($A10="","",IFERROR(INDEX('Tenders'!$Z$4:$Z$103,MATCH(LEFT($A10,2)&"|1",'Tenders'!$AD$4:$AD$103,0)),"")) | M10: =IF(OR($A10="",COUNTIF('Tenders'!$AD$4:$AD$103,LEFT($A10,2)&"|1")>1),"",IFERROR(INDEX('Tenders'!$N$4:$N$103,MATCH(LEFT($A10,2)&"|1",'Tenders'!$AD$4:$AD$103,0)),"")) | N10: =IF(OR(M10="",N(B10)=0),"",M10-B10) | O10: =IF(OR($A10="",COUNTIF('Tenders'!$AD$4:$AD$103,LEFT($A10,2)&"|1")>1),"",IFERROR(L10-INDEX('Tenders'!$Z$4:$Z$103,MATCH(LEFT($A10,2)&"|2",'Tenders'!$AD$4:$AD$103,0)),""))
A11: =IF('Packages'!B11="","",'Packages'!B11) | B11: =IF('Packages'!H11="","",'Packages'!H11) | C11: 50 | D11: 15 | E11: 15 | F11: 10 | G11: 5 | H11: 5 | I11: =IF(A11="","",SUM(C11:H11)) | J11: =IF($A11="","",COUNTIFS('Tenders'!$T$4:$T$103,LEFT($A11,2),'Tenders'!$I$4:$I$103,"Yes")) | K11: =IF($A11="","",IF(COUNTIF('Tenders'!$AD$4:$AD$103,LEFT($A11,2)&"|1")>1,"Tie: "&COUNTIF('Tenders'!$AD$4:$AD$103,LEFT($A11,2)&"|1")&" quotes share 1st",IFERROR(INDEX('Tenders'!$B$4:$B$103,MATCH(LEFT($A11,2)&"|1",'Tenders'!$AD$4:$AD$103,0)),""))) | L11: =IF($A11="","",IFERROR(INDEX('Tenders'!$Z$4:$Z$103,MATCH(LEFT($A11,2)&"|1",'Tenders'!$AD$4:$AD$103,0)),"")) | M11: =IF(OR($A11="",COUNTIF('Tenders'!$AD$4:$AD$103,LEFT($A11,2)&"|1")>1),"",IFERROR(INDEX('Tenders'!$N$4:$N$103,MATCH(LEFT($A11,2)&"|1",'Tenders'!$AD$4:$AD$103,0)),"")) | N11: =IF(OR(M11="",N(B11)=0),"",M11-B11) | O11: =IF(OR($A11="",COUNTIF('Tenders'!$AD$4:$AD$103,LEFT($A11,2)&"|1")>1),"",IFERROR(L11-INDEX('Tenders'!$Z$4:$Z$103,MATCH(LEFT($A11,2)&"|2",'Tenders'!$AD$4:$AD$103,0)),""))
A12: =IF('Packages'!B12="","",'Packages'!B12) | B12: =IF('Packages'!H12="","",'Packages'!H12) | C12: 50 | D12: 15 | E12: 15 | F12: 10 | G12: 5 | H12: 5 | I12: =IF(A12="","",SUM(C12:H12)) | J12: =IF($A12="","",COUNTIFS('Tenders'!$T$4:$T$103,LEFT($A12,2),'Tenders'!$I$4:$I$103,"Yes")) | K12: =IF($A12="","",IF(COUNTIF('Tenders'!$AD$4:$AD$103,LEFT($A12,2)&"|1")>1,"Tie: "&COUNTIF('Tenders'!$AD$4:$AD$103,LEFT($A12,2)&"|1")&" quotes share 1st",IFERROR(INDEX('Tenders'!$B$4:$B$103,MATCH(LEFT($A12,2)&"|1",'Tenders'!$AD$4:$AD$103,0)),""))) | L12: =IF($A12="","",IFERROR(INDEX('Tenders'!$Z$4:$Z$103,MATCH(LEFT($A12,2)&"|1",'Tenders'!$AD$4:$AD$103,0)),"")) | M12: =IF(OR($A12="",COUNTIF('Tenders'!$AD$4:$AD$103,LEFT($A12,2)&"|1")>1),"",IFERROR(INDEX('Tenders'!$N$4:$N$103,MATCH(LEFT($A12,2)&"|1",'Tenders'!$AD$4:$AD$103,0)),"")) | N12: =IF(OR(M12="",N(B12)=0),"",M12-B12) | O12: =IF(OR($A12="",COUNTIF('Tenders'!$AD$4:$AD$103,LEFT($A12,2)&"|1")>1),"",IFERROR(L12-INDEX('Tenders'!$Z$4:$Z$103,MATCH(LEFT($A12,2)&"|2",'Tenders'!$AD$4:$AD$103,0)),""))
A13: =IF('Packages'!B13="","",'Packages'!B13) | B13: =IF('Packages'!H13="","",'Packages'!H13) | C13: 50 | D13: 15 | E13: 15 | F13: 10 | G13: 5 | H13: 5 | I13: =IF(A13="","",SUM(C13:H13)) | J13: =IF($A13="","",COUNTIFS('Tenders'!$T$4:$T$103,LEFT($A13,2),'Tenders'!$I$4:$I$103,"Yes")) | K13: =IF($A13="","",IF(COUNTIF('Tenders'!$AD$4:$AD$103,LEFT($A13,2)&"|1")>1,"Tie: "&COUNTIF('Tenders'!$AD$4:$AD$103,LEFT($A13,2)&"|1")&" quotes share 1st",IFERROR(INDEX('Tenders'!$B$4:$B$103,MATCH(LEFT($A13,2)&"|1",'Tenders'!$AD$4:$AD$103,0)),""))) | L13: =IF($A13="","",IFERROR(INDEX('Tenders'!$Z$4:$Z$103,MATCH(LEFT($A13,2)&"|1",'Tenders'!$AD$4:$AD$103,0)),"")) | M13: =IF(OR($A13="",COUNTIF('Tenders'!$AD$4:$AD$103,LEFT($A13,2)&"|1")>1),"",IFERROR(INDEX('Tenders'!$N$4:$N$103,MATCH(LEFT($A13,2)&"|1",'Tenders'!$AD$4:$AD$103,0)),"")) | N13: =IF(OR(M13="",N(B13)=0),"",M13-B13) | O13: =IF(OR($A13="",COUNTIF('Tenders'!$AD$4:$AD$103,LEFT($A13,2)&"|1")>1),"",IFERROR(L13-INDEX('Tenders'!$Z$4:$Z$103,MATCH(LEFT($A13,2)&"|2",'Tenders'!$AD$4:$AD$103,0)),""))
A14: =IF('Packages'!B14="","",'Packages'!B14) | B14: =IF('Packages'!H14="","",'Packages'!H14) | C14: 50 | D14: 15 | E14: 15 | F14: 10 | G14: 5 | H14: 5 | I14: =IF(A14="","",SUM(C14:H14)) | J14: =IF($A14="","",COUNTIFS('Tenders'!$T$4:$T$103,LEFT($A14,2),'Tenders'!$I$4:$I$103,"Yes")) | K14: =IF($A14="","",IF(COUNTIF('Tenders'!$AD$4:$AD$103,LEFT($A14,2)&"|1")>1,"Tie: "&COUNTIF('Tenders'!$AD$4:$AD$103,LEFT($A14,2)&"|1")&" quotes share 1st",IFERROR(INDEX('Tenders'!$B$4:$B$103,MATCH(LEFT($A14,2)&"|1",'Tenders'!$AD$4:$AD$103,0)),""))) | L14: =IF($A14="","",IFERROR(INDEX('Tenders'!$Z$4:$Z$103,MATCH(LEFT($A14,2)&"|1",'Tenders'!$AD$4:$AD$103,0)),"")) | M14: =IF(OR($A14="",COUNTIF('Tenders'!$AD$4:$AD$103,LEFT($A14,2)&"|1")>1),"",IFERROR(INDEX('Tenders'!$N$4:$N$103,MATCH(LEFT($A14,2)&"|1",'Tenders'!$AD$4:$AD$103,0)),"")) | N14: =IF(OR(M14="",N(B14)=0),"",M14-B14) | O14: =IF(OR($A14="",COUNTIF('Tenders'!$AD$4:$AD$103,LEFT($A14,2)&"|1")>1),"",IFERROR(L14-INDEX('Tenders'!$Z$4:$Z$103,MATCH(LEFT($A14,2)&"|2",'Tenders'!$AD$4:$AD$103,0)),""))
A15: =IF('Packages'!B15="","",'Packages'!B15) | B15: =IF('Packages'!H15="","",'Packages'!H15) | C15: 50 | D15: 15 | E15: 15 | F15: 10 | G15: 5 | H15: 5 | I15: =IF(A15="","",SUM(C15:H15)) | J15: =IF($A15="","",COUNTIFS('Tenders'!$T$4:$T$103,LEFT($A15,2),'Tenders'!$I$4:$I$103,"Yes")) | K15: =IF($A15="","",IF(COUNTIF('Tenders'!$AD$4:$AD$103,LEFT($A15,2)&"|1")>1,"Tie: "&COUNTIF('Tenders'!$AD$4:$AD$103,LEFT($A15,2)&"|1")&" quotes share 1st",IFERROR(INDEX('Tenders'!$B$4:$B$103,MATCH(LEFT($A15,2)&"|1",'Tenders'!$AD$4:$AD$103,0)),""))) | L15: =IF($A15="","",IFERROR(INDEX('Tenders'!$Z$4:$Z$103,MATCH(LEFT($A15,2)&"|1",'Tenders'!$AD$4:$AD$103,0)),"")) | M15: =IF(OR($A15="",COUNTIF('Tenders'!$AD$4:$AD$103,LEFT($A15,2)&"|1")>1),"",IFERROR(INDEX('Tenders'!$N$4:$N$103,MATCH(LEFT($A15,2)&"|1",'Tenders'!$AD$4:$AD$103,0)),"")) | N15: =IF(OR(M15="",N(B15)=0),"",M15-B15) | O15: =IF(OR($A15="",COUNTIF('Tenders'!$AD$4:$AD$103,LEFT($A15,2)&"|1")>1),"",IFERROR(L15-INDEX('Tenders'!$Z$4:$Z$103,MATCH(LEFT($A15,2)&"|2",'Tenders'!$AD$4:$AD$103,0)),""))
... A33: =IF('Packages'!B33="","",'Packages'!B33) | B33: =IF('Packages'!H33="","",'Packages'!H33) | C33: 50 | D33: 15 | E33: 15 | F33: 10 | G33: 5 | H33: 5 | I33: =IF(A33="","",SUM(C33:H33)) | J33: =IF($A33="","",COUNTIFS('Tenders'!$T$4:$T$103,LEFT($A33,2),'Tenders'!$I$4:$I$103,"Yes")) | K33: =IF($A33="","",IF(COUNTIF('Tenders'!$AD$4:$AD$103,LEFT($A33,2)&"|1")>1,"Tie: "&COUNTIF('Tenders'!$AD$4:$AD$103,LEFT($A33,2)&"|1")&" quotes share 1st",IFERROR(INDEX('Tenders'!$B$4:$B$103,MATCH(LEFT($A33,2)&"|1",'Tenders'!$AD$4:$AD$103,0)),""))) | L33: =IF($A33="","",IFERROR(INDEX('Tenders'!$Z$4:$Z$103,MATCH(LEFT($A33,2)&"|1",'Tenders'!$AD$4:$AD$103,0)),"")) | M33: =IF(OR($A33="",COUNTIF('Tenders'!$AD$4:$AD$103,LEFT($A33,2)&"|1")>1),"",IFERROR(INDEX('Tenders'!$N$4:$N$103,MATCH(LEFT($A33,2)&"|1",'Tenders'!$AD$4:$AD$103,0)),"")) | N33: =IF(OR(M33="",N(B33)=0),"",M33-B33) | O33: =IF(OR($A33="",COUNTIF('Tenders'!$AD$4:$AD$103,LEFT($A33,2)&"|1")>1),"",IFERROR(L33-INDEX('Tenders'!$Z$4:$Z$103,MATCH(LEFT($A33,2)&"|2",'Tenders'!$AD$4:$AD$103,0)),""))

Sheet Tenders
A1: Tender comparison
A2: One row per quote. Fail any gate and the quote is excluded. Levelling adds exclusions, provisional-sum adjustments and a risk allowance so prices are like-for-like. Scores are 0 to 10. The Check column says why a quote is excluded or needs a look.
A3: Package | B3: Tenderer | C3: Received | D3: Registered / licensed | E3: Insurance current | F3: ABN verified | G3: SWMS provided | H3: Scope conforms | I3: Compliant? | J3: Quoted price inc GST ($) | K3: + Cost of exclusions ($) | L3: ± Provisional sum adj. ($) | M3: + Risk allowance ($) | N3: Levelled price ($) | O3: Experience & references | P3: Program / availability | Q3: Quality of past work | R3: Communication | S3: Warranty & defects terms | T3: Package no. | U3: Weights row | V3: Lowest compliant in package ($) | W3: Median compliant in package ($) | X3: Price points | Y3: Other points | Z3: Total /100 | AA3: Rank | AB3: Price check | AC3: Check | AD3: Key | AE3: Quote Doc ID | AF3: Notes
A4: 08 Roofing | B4: Summit Roofing | D4: Yes | E4: Yes | F4: Yes | G4: Yes | H4: Yes | I4: =IF(B4="","",IF(AND(COUNTIF(D4:H4,"Yes")=5,SUMPRODUCT(--ISTEXT(J4:M4))=0,N(J4)>0,N(N4)>0,U4>0),"Yes","No")) | J4: 32500 | K4: 1800 | L4: 0 | M4: 500 | N4: =IF(B4="","",N(J4)+N(K4)+N(L4)+N(M4)) | O4: 8 | P4: 6 | Q4: 8 | R4: 7 | S4: 7 | T4: =IF(A4="","",LEFT(A4,2)) | U4: =IF(A4="",0,IFERROR(MATCH(LEFT(A4,3)&"*",'Tender Setup'!$A$4:$A$33,0),0)) | V4: {=IF(I4<>"Yes","",MIN(IF((T$4:T$103=T4)*(I$4:I$103="Yes"),N$4:N$103)))} | W4: {=IF(I4<>"Yes","",MEDIAN(IF((T$4:T$103=T4)*(I$4:I$103="Yes"),N$4:N$103)))} | X4: =IF(I4<>"Yes",0,V4/N4*INDEX('Tender Setup'!$C$4:$C$33,U4)) | Y4: =IF(I4<>"Yes",0,(MIN(10,MAX(0,N(O4)))*INDEX('Tender Setup'!$D$4:$D$33,U4)+MIN(10,MAX(0,N(P4)))*INDEX('Tender Setup'!$E$4:$E$33,U4)+MIN(10,MAX(0,N(Q4)))*INDEX('Tender Setup'!$F$4:$F$33,U4)+MIN(10,MAX(0,N(R4)))*INDEX('Tender Setup'!$G$4:$G$33,U4)+MIN(10,MAX(0,N(S4)))*INDEX('Tender Setup'!$H$4:$H$33,U4))/10) | Z4: =IF(B4="","",IF(I4<>"Yes",0,IF(N(INDEX('Tender Setup'!$I$4:$I$33,U4))=0,0,(X4+Y4)*100/INDEX('Tender Setup'!$I$4:$I$33,U4)))) | AA4: =IF(B4="","",IF(I4<>"Yes","Excluded",COUNTIFS(T$4:T$103,T4,I$4:I$103,"Yes",Z$4:Z$103,">"&Z4)+1)) | AB4: =IF(I4<>"Yes","",IF(AND(COUNTIFS(T$4:T$103,T4,I$4:I$103,"Yes")>=2,N4<W4*(1-Settings!$B$12)),"Well under median: check scope","")) | AC4: =IF(B4="","",TRIM(IF(COUNTIF(D4:H4,"Yes")<5,"Compliance gates not all Yes. ","")&IF(SUMPRODUCT(--ISTEXT(J4:M4))>0,"A price cell holds text, not a number. ","")&IF(N(J4)<=0,"No quoted price. ",IF(N(N4)<=0,"Levelled price is $0 or less. ",""))&IF(U4=0,"Package isn't on the Packages tab. ","")&IF(SUMPRODUCT(ISTEXT(O4:S4)+(O4:S4<0)+(O4:S4>10))>0,"Scores must be 0 to 10 (capped). ","")&IF(AND(AA4=1,COUNTIFS(T$4:T$103,T4,AA$4:AA$103,1)>1),"Tied for 1st: ask both for clarifications. ",""))) | AD4: =T4&"|"&AA4 | AF4: EXAMPLE: delete this row
A5: 08 Roofing | B5: Ridgeline Metal Roofs | D5: Yes | E5: Yes | F5: Yes | G5: Yes | H5: Yes | I5: =IF(B5="","",IF(AND(COUNTIF(D5:H5,"Yes")=5,SUMPRODUCT(--ISTEXT(J5:M5))=0,N(J5)>0,N(N5)>0,U5>0),"Yes","No")) | J5: 36900 | K5: 0 | L5: 0 | M5: 0 | N5: =IF(B5="","",N(J5)+N(K5)+N(L5)+N(M5)) | O5: 9 | P5: 8 | Q5: 9 | R5: 9 | S5: 8 | T5: =IF(A5="","",LEFT(A5,2)) | U5: =IF(A5="",0,IFERROR(MATCH(LEFT(A5,3)&"*",'Tender Setup'!$A$4:$A$33,0),0)) | V5: {=IF(I5<>"Yes","",MIN(IF((T$4:T$103=T5)*(I$4:I$103="Yes"),N$4:N$103)))} | W5: {=IF(I5<>"Yes","",MEDIAN(IF((T$4:T$103=T5)*(I$4:I$103="Yes"),N$4:N$103)))} | X5: =IF(I5<>"Yes",0,V5/N5*INDEX('Tender Setup'!$C$4:$C$33,U5)) | Y5: =IF(I5<>"Yes",0,(MIN(10,MAX(0,N(O5)))*INDEX('Tender Setup'!$D$4:$D$33,U5)+MIN(10,MAX(0,N(P5)))*INDEX('Tender Setup'!$E$4:$E$33,U5)+MIN(10,MAX(0,N(Q5)))*INDEX('Tender Setup'!$F$4:$F$33,U5)+MIN(10,MAX(0,N(R5)))*INDEX('Tender Setup'!$G$4:$G$33,U5)+MIN(10,MAX(0,N(S5)))*INDEX('Tender Setup'!$H$4:$H$33,U5))/10) | Z5: =IF(B5="","",IF(I5<>"Yes",0,IF(N(INDEX('Tender Setup'!$I$4:$I$33,U5))=0,0,(X5+Y5)*100/INDEX('Tender Setup'!$I$4:$I$33,U5)))) | AA5: =IF(B5="","",IF(I5<>"Yes","Excluded",COUNTIFS(T$4:T$103,T5,I$4:I$103,"Yes",Z$4:Z$103,">"&Z5)+1)) | AB5: =IF(I5<>"Yes","",IF(AND(COUNTIFS(T$4:T$103,T5,I$4:I$103,"Yes")>=2,N5<W5*(1-Settings!$B$12)),"Well under median: check scope","")) | AC5: =IF(B5="","",TRIM(IF(COUNTIF(D5:H5,"Yes")<5,"Compliance gates not all Yes. ","")&IF(SUMPRODUCT(--ISTEXT(J5:M5))>0,"A price cell holds text, not a number. ","")&IF(N(J5)<=0,"No quoted price. ",IF(N(N5)<=0,"Levelled price is $0 or less. ",""))&IF(U5=0,"Package isn't on the Packages tab. ","")&IF(SUMPRODUCT(ISTEXT(O5:S5)+(O5:S5<0)+(O5:S5>10))>0,"Scores must be 0 to 10 (capped). ","")&IF(AND(AA5=1,COUNTIFS(T$4:T$103,T5,AA$4:AA$103,1)>1),"Tied for 1st: ask both for clarifications. ",""))) | AD5: =T5&"|"&AA5 | AF5: EXAMPLE: delete this row
A6: 08 Roofing | B6: Budget Roofs Co | D6: Yes | E6: No | F6: Yes | G6: Yes | H6: Yes | I6: =IF(B6="","",IF(AND(COUNTIF(D6:H6,"Yes")=5,SUMPRODUCT(--ISTEXT(J6:M6))=0,N(J6)>0,N(N6)>0,U6>0),"Yes","No")) | J6: 27900 | K6: 3500 | L6: 1200 | M6: 2000 | N6: =IF(B6="","",N(J6)+N(K6)+N(L6)+N(M6)) | O6: 5 | P6: 9 | Q6: 5 | R6: 4 | S6: 5 | T6: =IF(A6="","",LEFT(A6,2)) | U6: =IF(A6="",0,IFERROR(MATCH(LEFT(A6,3)&"*",'Tender Setup'!$A$4:$A$33,0),0)) | V6: {=IF(I6<>"Yes","",MIN(IF((T$4:T$103=T6)*(I$4:I$103="Yes"),N$4:N$103)))} | W6: {=IF(I6<>"Yes","",MEDIAN(IF((T$4:T$103=T6)*(I$4:I$103="Yes"),N$4:N$103)))} | X6: =IF(I6<>"Yes",0,V6/N6*INDEX('Tender Setup'!$C$4:$C$33,U6)) | Y6: =IF(I6<>"Yes",0,(MIN(10,MAX(0,N(O6)))*INDEX('Tender Setup'!$D$4:$D$33,U6)+MIN(10,MAX(0,N(P6)))*INDEX('Tender Setup'!$E$4:$E$33,U6)+MIN(10,MAX(0,N(Q6)))*INDEX('Tender Setup'!$F$4:$F$33,U6)+MIN(10,MAX(0,N(R6)))*INDEX('Tender Setup'!$G$4:$G$33,U6)+MIN(10,MAX(0,N(S6)))*INDEX('Tender Setup'!$H$4:$H$33,U6))/10) | Z6: =IF(B6="","",IF(I6<>"Yes",0,IF(N(INDEX('Tender Setup'!$I$4:$I$33,U6))=0,0,(X6+Y6)*100/INDEX('Tender Setup'!$I$4:$I$33,U6)))) | AA6: =IF(B6="","",IF(I6<>"Yes","Excluded",COUNTIFS(T$4:T$103,T6,I$4:I$103,"Yes",Z$4:Z$103,">"&Z6)+1)) | AB6: =IF(I6<>"Yes","",IF(AND(COUNTIFS(T$4:T$103,T6,I$4:I$103,"Yes")>=2,N6<W6*(1-Settings!$B$12)),"Well under median: check scope","")) | AC6: =IF(B6="","",TRIM(IF(COUNTIF(D6:H6,"Yes")<5,"Compliance gates not all Yes. ","")&IF(SUMPRODUCT(--ISTEXT(J6:M6))>0,"A price cell holds text, not a number. ","")&IF(N(J6)<=0,"No quoted price. ",IF(N(N6)<=0,"Levelled price is $0 or less. ",""))&IF(U6=0,"Package isn't on the Packages tab. ","")&IF(SUMPRODUCT(ISTEXT(O6:S6)+(O6:S6<0)+(O6:S6>10))>0,"Scores must be 0 to 10 (capped). ","")&IF(AND(AA6=1,COUNTIFS(T$4:T$103,T6,AA$4:AA$103,1)>1),"Tied for 1st: ask both for clarifications. ",""))) | AD6: =T6&"|"&AA6 | AF6: EXAMPLE: delete this row
I7: =IF(B7="","",IF(AND(COUNTIF(D7:H7,"Yes")=5,SUMPRODUCT(--ISTEXT(J7:M7))=0,N(J7)>0,N(N7)>0,U7>0),"Yes","No")) | N7: =IF(B7="","",N(J7)+N(K7)+N(L7)+N(M7)) | T7: =IF(A7="","",LEFT(A7,2)) | U7: =IF(A7="",0,IFERROR(MATCH(LEFT(A7,3)&"*",'Tender Setup'!$A$4:$A$33,0),0)) | V7: {=IF(I7<>"Yes","",MIN(IF((T$4:T$103=T7)*(I$4:I$103="Yes"),N$4:N$103)))} | W7: {=IF(I7<>"Yes","",MEDIAN(IF((T$4:T$103=T7)*(I$4:I$103="Yes"),N$4:N$103)))} | X7: =IF(I7<>"Yes",0,V7/N7*INDEX('Tender Setup'!$C$4:$C$33,U7)) | Y7: =IF(I7<>"Yes",0,(MIN(10,MAX(0,N(O7)))*INDEX('Tender Setup'!$D$4:$D$33,U7)+MIN(10,MAX(0,N(P7)))*INDEX('Tender Setup'!$E$4:$E$33,U7)+MIN(10,MAX(0,N(Q7)))*INDEX('Tender Setup'!$F$4:$F$33,U7)+MIN(10,MAX(0,N(R7)))*INDEX('Tender Setup'!$G$4:$G$33,U7)+MIN(10,MAX(0,N(S7)))*INDEX('Tender Setup'!$H$4:$H$33,U7))/10) | Z7: =IF(B7="","",IF(I7<>"Yes",0,IF(N(INDEX('Tender Setup'!$I$4:$I$33,U7))=0,0,(X7+Y7)*100/INDEX('Tender Setup'!$I$4:$I$33,U7)))) | AA7: =IF(B7="","",IF(I7<>"Yes","Excluded",COUNTIFS(T$4:T$103,T7,I$4:I$103,"Yes",Z$4:Z$103,">"&Z7)+1)) | AB7: =IF(I7<>"Yes","",IF(AND(COUNTIFS(T$4:T$103,T7,I$4:I$103,"Yes")>=2,N7<W7*(1-Settings!$B$12)),"Well under median: check scope","")) | AC7: =IF(B7="","",TRIM(IF(COUNTIF(D7:H7,"Yes")<5,"Compliance gates not all Yes. ","")&IF(SUMPRODUCT(--ISTEXT(J7:M7))>0,"A price cell holds text, not a number. ","")&IF(N(J7)<=0,"No quoted price. ",IF(N(N7)<=0,"Levelled price is $0 or less. ",""))&IF(U7=0,"Package isn't on the Packages tab. ","")&IF(SUMPRODUCT(ISTEXT(O7:S7)+(O7:S7<0)+(O7:S7>10))>0,"Scores must be 0 to 10 (capped). ","")&IF(AND(AA7=1,COUNTIFS(T$4:T$103,T7,AA$4:AA$103,1)>1),"Tied for 1st: ask both for clarifications. ",""))) | AD7: =T7&"|"&AA7
I8: =IF(B8="","",IF(AND(COUNTIF(D8:H8,"Yes")=5,SUMPRODUCT(--ISTEXT(J8:M8))=0,N(J8)>0,N(N8)>0,U8>0),"Yes","No")) | N8: =IF(B8="","",N(J8)+N(K8)+N(L8)+N(M8)) | T8: =IF(A8="","",LEFT(A8,2)) | U8: =IF(A8="",0,IFERROR(MATCH(LEFT(A8,3)&"*",'Tender Setup'!$A$4:$A$33,0),0)) | V8: {=IF(I8<>"Yes","",MIN(IF((T$4:T$103=T8)*(I$4:I$103="Yes"),N$4:N$103)))} | W8: {=IF(I8<>"Yes","",MEDIAN(IF((T$4:T$103=T8)*(I$4:I$103="Yes"),N$4:N$103)))} | X8: =IF(I8<>"Yes",0,V8/N8*INDEX('Tender Setup'!$C$4:$C$33,U8)) | Y8: =IF(I8<>"Yes",0,(MIN(10,MAX(0,N(O8)))*INDEX('Tender Setup'!$D$4:$D$33,U8)+MIN(10,MAX(0,N(P8)))*INDEX('Tender Setup'!$E$4:$E$33,U8)+MIN(10,MAX(0,N(Q8)))*INDEX('Tender Setup'!$F$4:$F$33,U8)+MIN(10,MAX(0,N(R8)))*INDEX('Tender Setup'!$G$4:$G$33,U8)+MIN(10,MAX(0,N(S8)))*INDEX('Tender Setup'!$H$4:$H$33,U8))/10) | Z8: =IF(B8="","",IF(I8<>"Yes",0,IF(N(INDEX('Tender Setup'!$I$4:$I$33,U8))=0,0,(X8+Y8)*100/INDEX('Tender Setup'!$I$4:$I$33,U8)))) | AA8: =IF(B8="","",IF(I8<>"Yes","Excluded",COUNTIFS(T$4:T$103,T8,I$4:I$103,"Yes",Z$4:Z$103,">"&Z8)+1)) | AB8: =IF(I8<>"Yes","",IF(AND(COUNTIFS(T$4:T$103,T8,I$4:I$103,"Yes")>=2,N8<W8*(1-Settings!$B$12)),"Well under median: check scope","")) | AC8: =IF(B8="","",TRIM(IF(COUNTIF(D8:H8,"Yes")<5,"Compliance gates not all Yes. ","")&IF(SUMPRODUCT(--ISTEXT(J8:M8))>0,"A price cell holds text, not a number. ","")&IF(N(J8)<=0,"No quoted price. ",IF(N(N8)<=0,"Levelled price is $0 or less. ",""))&IF(U8=0,"Package isn't on the Packages tab. ","")&IF(SUMPRODUCT(ISTEXT(O8:S8)+(O8:S8<0)+(O8:S8>10))>0,"Scores must be 0 to 10 (capped). ","")&IF(AND(AA8=1,COUNTIFS(T$4:T$103,T8,AA$4:AA$103,1)>1),"Tied for 1st: ask both for clarifications. ",""))) | AD8: =T8&"|"&AA8
I9: =IF(B9="","",IF(AND(COUNTIF(D9:H9,"Yes")=5,SUMPRODUCT(--ISTEXT(J9:M9))=0,N(J9)>0,N(N9)>0,U9>0),"Yes","No")) | N9: =IF(B9="","",N(J9)+N(K9)+N(L9)+N(M9)) | T9: =IF(A9="","",LEFT(A9,2)) | U9: =IF(A9="",0,IFERROR(MATCH(LEFT(A9,3)&"*",'Tender Setup'!$A$4:$A$33,0),0)) | V9: {=IF(I9<>"Yes","",MIN(IF((T$4:T$103=T9)*(I$4:I$103="Yes"),N$4:N$103)))} | W9: {=IF(I9<>"Yes","",MEDIAN(IF((T$4:T$103=T9)*(I$4:I$103="Yes"),N$4:N$103)))} | X9: =IF(I9<>"Yes",0,V9/N9*INDEX('Tender Setup'!$C$4:$C$33,U9)) | Y9: =IF(I9<>"Yes",0,(MIN(10,MAX(0,N(O9)))*INDEX('Tender Setup'!$D$4:$D$33,U9)+MIN(10,MAX(0,N(P9)))*INDEX('Tender Setup'!$E$4:$E$33,U9)+MIN(10,MAX(0,N(Q9)))*INDEX('Tender Setup'!$F$4:$F$33,U9)+MIN(10,MAX(0,N(R9)))*INDEX('Tender Setup'!$G$4:$G$33,U9)+MIN(10,MAX(0,N(S9)))*INDEX('Tender Setup'!$H$4:$H$33,U9))/10) | Z9: =IF(B9="","",IF(I9<>"Yes",0,IF(N(INDEX('Tender Setup'!$I$4:$I$33,U9))=0,0,(X9+Y9)*100/INDEX('Tender Setup'!$I$4:$I$33,U9)))) | AA9: =IF(B9="","",IF(I9<>"Yes","Excluded",COUNTIFS(T$4:T$103,T9,I$4:I$103,"Yes",Z$4:Z$103,">"&Z9)+1)) | AB9: =IF(I9<>"Yes","",IF(AND(COUNTIFS(T$4:T$103,T9,I$4:I$103,"Yes")>=2,N9<W9*(1-Settings!$B$12)),"Well under median: check scope","")) | AC9: =IF(B9="","",TRIM(IF(COUNTIF(D9:H9,"Yes")<5,"Compliance gates not all Yes. ","")&IF(SUMPRODUCT(--ISTEXT(J9:M9))>0,"A price cell holds text, not a number. ","")&IF(N(J9)<=0,"No quoted price. ",IF(N(N9)<=0,"Levelled price is $0 or less. ",""))&IF(U9=0,"Package isn't on the Packages tab. ","")&IF(SUMPRODUCT(ISTEXT(O9:S9)+(O9:S9<0)+(O9:S9>10))>0,"Scores must be 0 to 10 (capped). ","")&IF(AND(AA9=1,COUNTIFS(T$4:T$103,T9,AA$4:AA$103,1)>1),"Tied for 1st: ask both for clarifications. ",""))) | AD9: =T9&"|"&AA9
I10: =IF(B10="","",IF(AND(COUNTIF(D10:H10,"Yes")=5,SUMPRODUCT(--ISTEXT(J10:M10))=0,N(J10)>0,N(N10)>0,U10>0),"Yes","No")) | N10: =IF(B10="","",N(J10)+N(K10)+N(L10)+N(M10)) | T10: =IF(A10="","",LEFT(A10,2)) | U10: =IF(A10="",0,IFERROR(MATCH(LEFT(A10,3)&"*",'Tender Setup'!$A$4:$A$33,0),0)) | V10: {=IF(I10<>"Yes","",MIN(IF((T$4:T$103=T10)*(I$4:I$103="Yes"),N$4:N$103)))} | W10: {=IF(I10<>"Yes","",MEDIAN(IF((T$4:T$103=T10)*(I$4:I$103="Yes"),N$4:N$103)))} | X10: =IF(I10<>"Yes",0,V10/N10*INDEX('Tender Setup'!$C$4:$C$33,U10)) | Y10: =IF(I10<>"Yes",0,(MIN(10,MAX(0,N(O10)))*INDEX('Tender Setup'!$D$4:$D$33,U10)+MIN(10,MAX(0,N(P10)))*INDEX('Tender Setup'!$E$4:$E$33,U10)+MIN(10,MAX(0,N(Q10)))*INDEX('Tender Setup'!$F$4:$F$33,U10)+MIN(10,MAX(0,N(R10)))*INDEX('Tender Setup'!$G$4:$G$33,U10)+MIN(10,MAX(0,N(S10)))*INDEX('Tender Setup'!$H$4:$H$33,U10))/10) | Z10: =IF(B10="","",IF(I10<>"Yes",0,IF(N(INDEX('Tender Setup'!$I$4:$I$33,U10))=0,0,(X10+Y10)*100/INDEX('Tender Setup'!$I$4:$I$33,U10)))) | AA10: =IF(B10="","",IF(I10<>"Yes","Excluded",COUNTIFS(T$4:T$103,T10,I$4:I$103,"Yes",Z$4:Z$103,">"&Z10)+1)) | AB10: =IF(I10<>"Yes","",IF(AND(COUNTIFS(T$4:T$103,T10,I$4:I$103,"Yes")>=2,N10<W10*(1-Settings!$B$12)),"Well under median: check scope","")) | AC10: =IF(B10="","",TRIM(IF(COUNTIF(D10:H10,"Yes")<5,"Compliance gates not all Yes. ","")&IF(SUMPRODUCT(--ISTEXT(J10:M10))>0,"A price cell holds text, not a number. ","")&IF(N(J10)<=0,"No quoted price. ",IF(N(N10)<=0,"Levelled price is $0 or less. ",""))&IF(U10=0,"Package isn't on the Packages tab. ","")&IF(SUMPRODUCT(ISTEXT(O10:S10)+(O10:S10<0)+(O10:S10>10))>0,"Scores must be 0 to 10 (capped). ","")&IF(AND(AA10=1,COUNTIFS(T$4:T$103,T10,AA$4:AA$103,1)>1),"Tied for 1st: ask both for clarifications. ",""))) | AD10: =T10&"|"&AA10
I11: =IF(B11="","",IF(AND(COUNTIF(D11:H11,"Yes")=5,SUMPRODUCT(--ISTEXT(J11:M11))=0,N(J11)>0,N(N11)>0,U11>0),"Yes","No")) | N11: =IF(B11="","",N(J11)+N(K11)+N(L11)+N(M11)) | T11: =IF(A11="","",LEFT(A11,2)) | U11: =IF(A11="",0,IFERROR(MATCH(LEFT(A11,3)&"*",'Tender Setup'!$A$4:$A$33,0),0)) | V11: {=IF(I11<>"Yes","",MIN(IF((T$4:T$103=T11)*(I$4:I$103="Yes"),N$4:N$103)))} | W11: {=IF(I11<>"Yes","",MEDIAN(IF((T$4:T$103=T11)*(I$4:I$103="Yes"),N$4:N$103)))} | X11: =IF(I11<>"Yes",0,V11/N11*INDEX('Tender Setup'!$C$4:$C$33,U11)) | Y11: =IF(I11<>"Yes",0,(MIN(10,MAX(0,N(O11)))*INDEX('Tender Setup'!$D$4:$D$33,U11)+MIN(10,MAX(0,N(P11)))*INDEX('Tender Setup'!$E$4:$E$33,U11)+MIN(10,MAX(0,N(Q11)))*INDEX('Tender Setup'!$F$4:$F$33,U11)+MIN(10,MAX(0,N(R11)))*INDEX('Tender Setup'!$G$4:$G$33,U11)+MIN(10,MAX(0,N(S11)))*INDEX('Tender Setup'!$H$4:$H$33,U11))/10) | Z11: =IF(B11="","",IF(I11<>"Yes",0,IF(N(INDEX('Tender Setup'!$I$4:$I$33,U11))=0,0,(X11+Y11)*100/INDEX('Tender Setup'!$I$4:$I$33,U11)))) | AA11: =IF(B11="","",IF(I11<>"Yes","Excluded",COUNTIFS(T$4:T$103,T11,I$4:I$103,"Yes",Z$4:Z$103,">"&Z11)+1)) | AB11: =IF(I11<>"Yes","",IF(AND(COUNTIFS(T$4:T$103,T11,I$4:I$103,"Yes")>=2,N11<W11*(1-Settings!$B$12)),"Well under median: check scope","")) | AC11: =IF(B11="","",TRIM(IF(COUNTIF(D11:H11,"Yes")<5,"Compliance gates not all Yes. ","")&IF(SUMPRODUCT(--ISTEXT(J11:M11))>0,"A price cell holds text, not a number. ","")&IF(N(J11)<=0,"No quoted price. ",IF(N(N11)<=0,"Levelled price is $0 or less. ",""))&IF(U11=0,"Package isn't on the Packages tab. ","")&IF(SUMPRODUCT(ISTEXT(O11:S11)+(O11:S11<0)+(O11:S11>10))>0,"Scores must be 0 to 10 (capped). ","")&IF(AND(AA11=1,COUNTIFS(T$4:T$103,T11,AA$4:AA$103,1)>1),"Tied for 1st: ask both for clarifications. ",""))) | AD11: =T11&"|"&AA11
I12: =IF(B12="","",IF(AND(COUNTIF(D12:H12,"Yes")=5,SUMPRODUCT(--ISTEXT(J12:M12))=0,N(J12)>0,N(N12)>0,U12>0),"Yes","No")) | N12: =IF(B12="","",N(J12)+N(K12)+N(L12)+N(M12)) | T12: =IF(A12="","",LEFT(A12,2)) | U12: =IF(A12="",0,IFERROR(MATCH(LEFT(A12,3)&"*",'Tender Setup'!$A$4:$A$33,0),0)) | V12: {=IF(I12<>"Yes","",MIN(IF((T$4:T$103=T12)*(I$4:I$103="Yes"),N$4:N$103)))} | W12: {=IF(I12<>"Yes","",MEDIAN(IF((T$4:T$103=T12)*(I$4:I$103="Yes"),N$4:N$103)))} | X12: =IF(I12<>"Yes",0,V12/N12*INDEX('Tender Setup'!$C$4:$C$33,U12)) | Y12: =IF(I12<>"Yes",0,(MIN(10,MAX(0,N(O12)))*INDEX('Tender Setup'!$D$4:$D$33,U12)+MIN(10,MAX(0,N(P12)))*INDEX('Tender Setup'!$E$4:$E$33,U12)+MIN(10,MAX(0,N(Q12)))*INDEX('Tender Setup'!$F$4:$F$33,U12)+MIN(10,MAX(0,N(R12)))*INDEX('Tender Setup'!$G$4:$G$33,U12)+MIN(10,MAX(0,N(S12)))*INDEX('Tender Setup'!$H$4:$H$33,U12))/10) | Z12: =IF(B12="","",IF(I12<>"Yes",0,IF(N(INDEX('Tender Setup'!$I$4:$I$33,U12))=0,0,(X12+Y12)*100/INDEX('Tender Setup'!$I$4:$I$33,U12)))) | AA12: =IF(B12="","",IF(I12<>"Yes","Excluded",COUNTIFS(T$4:T$103,T12,I$4:I$103,"Yes",Z$4:Z$103,">"&Z12)+1)) | AB12: =IF(I12<>"Yes","",IF(AND(COUNTIFS(T$4:T$103,T12,I$4:I$103,"Yes")>=2,N12<W12*(1-Settings!$B$12)),"Well under median: check scope","")) | AC12: =IF(B12="","",TRIM(IF(COUNTIF(D12:H12,"Yes")<5,"Compliance gates not all Yes. ","")&IF(SUMPRODUCT(--ISTEXT(J12:M12))>0,"A price cell holds text, not a number. ","")&IF(N(J12)<=0,"No quoted price. ",IF(N(N12)<=0,"Levelled price is $0 or less. ",""))&IF(U12=0,"Package isn't on the Packages tab. ","")&IF(SUMPRODUCT(ISTEXT(O12:S12)+(O12:S12<0)+(O12:S12>10))>0,"Scores must be 0 to 10 (capped). ","")&IF(AND(AA12=1,COUNTIFS(T$4:T$103,T12,AA$4:AA$103,1)>1),"Tied for 1st: ask both for clarifications. ",""))) | AD12: =T12&"|"&AA12
I13: =IF(B13="","",IF(AND(COUNTIF(D13:H13,"Yes")=5,SUMPRODUCT(--ISTEXT(J13:M13))=0,N(J13)>0,N(N13)>0,U13>0),"Yes","No")) | N13: =IF(B13="","",N(J13)+N(K13)+N(L13)+N(M13)) | T13: =IF(A13="","",LEFT(A13,2)) | U13: =IF(A13="",0,IFERROR(MATCH(LEFT(A13,3)&"*",'Tender Setup'!$A$4:$A$33,0),0)) | V13: {=IF(I13<>"Yes","",MIN(IF((T$4:T$103=T13)*(I$4:I$103="Yes"),N$4:N$103)))} | W13: {=IF(I13<>"Yes","",MEDIAN(IF((T$4:T$103=T13)*(I$4:I$103="Yes"),N$4:N$103)))} | X13: =IF(I13<>"Yes",0,V13/N13*INDEX('Tender Setup'!$C$4:$C$33,U13)) | Y13: =IF(I13<>"Yes",0,(MIN(10,MAX(0,N(O13)))*INDEX('Tender Setup'!$D$4:$D$33,U13)+MIN(10,MAX(0,N(P13)))*INDEX('Tender Setup'!$E$4:$E$33,U13)+MIN(10,MAX(0,N(Q13)))*INDEX('Tender Setup'!$F$4:$F$33,U13)+MIN(10,MAX(0,N(R13)))*INDEX('Tender Setup'!$G$4:$G$33,U13)+MIN(10,MAX(0,N(S13)))*INDEX('Tender Setup'!$H$4:$H$33,U13))/10) | Z13: =IF(B13="","",IF(I13<>"Yes",0,IF(N(INDEX('Tender Setup'!$I$4:$I$33,U13))=0,0,(X13+Y13)*100/INDEX('Tender Setup'!$I$4:$I$33,U13)))) | AA13: =IF(B13="","",IF(I13<>"Yes","Excluded",COUNTIFS(T$4:T$103,T13,I$4:I$103,"Yes",Z$4:Z$103,">"&Z13)+1)) | AB13: =IF(I13<>"Yes","",IF(AND(COUNTIFS(T$4:T$103,T13,I$4:I$103,"Yes")>=2,N13<W13*(1-Settings!$B$12)),"Well under median: check scope","")) | AC13: =IF(B13="","",TRIM(IF(COUNTIF(D13:H13,"Yes")<5,"Compliance gates not all Yes. ","")&IF(SUMPRODUCT(--ISTEXT(J13:M13))>0,"A price cell holds text, not a number. ","")&IF(N(J13)<=0,"No quoted price. ",IF(N(N13)<=0,"Levelled price is $0 or less. ",""))&IF(U13=0,"Package isn't on the Packages tab. ","")&IF(SUMPRODUCT(ISTEXT(O13:S13)+(O13:S13<0)+(O13:S13>10))>0,"Scores must be 0 to 10 (capped). ","")&IF(AND(AA13=1,COUNTIFS(T$4:T$103,T13,AA$4:AA$103,1)>1),"Tied for 1st: ask both for clarifications. ",""))) | AD13: =T13&"|"&AA13
I14: =IF(B14="","",IF(AND(COUNTIF(D14:H14,"Yes")=5,SUMPRODUCT(--ISTEXT(J14:M14))=0,N(J14)>0,N(N14)>0,U14>0),"Yes","No")) | N14: =IF(B14="","",N(J14)+N(K14)+N(L14)+N(M14)) | T14: =IF(A14="","",LEFT(A14,2)) | U14: =IF(A14="",0,IFERROR(MATCH(LEFT(A14,3)&"*",'Tender Setup'!$A$4:$A$33,0),0)) | V14: {=IF(I14<>"Yes","",MIN(IF((T$4:T$103=T14)*(I$4:I$103="Yes"),N$4:N$103)))} | W14: {=IF(I14<>"Yes","",MEDIAN(IF((T$4:T$103=T14)*(I$4:I$103="Yes"),N$4:N$103)))} | X14: =IF(I14<>"Yes",0,V14/N14*INDEX('Tender Setup'!$C$4:$C$33,U14)) | Y14: =IF(I14<>"Yes",0,(MIN(10,MAX(0,N(O14)))*INDEX('Tender Setup'!$D$4:$D$33,U14)+MIN(10,MAX(0,N(P14)))*INDEX('Tender Setup'!$E$4:$E$33,U14)+MIN(10,MAX(0,N(Q14)))*INDEX('Tender Setup'!$F$4:$F$33,U14)+MIN(10,MAX(0,N(R14)))*INDEX('Tender Setup'!$G$4:$G$33,U14)+MIN(10,MAX(0,N(S14)))*INDEX('Tender Setup'!$H$4:$H$33,U14))/10) | Z14: =IF(B14="","",IF(I14<>"Yes",0,IF(N(INDEX('Tender Setup'!$I$4:$I$33,U14))=0,0,(X14+Y14)*100/INDEX('Tender Setup'!$I$4:$I$33,U14)))) | AA14: =IF(B14="","",IF(I14<>"Yes","Excluded",COUNTIFS(T$4:T$103,T14,I$4:I$103,"Yes",Z$4:Z$103,">"&Z14)+1)) | AB14: =IF(I14<>"Yes","",IF(AND(COUNTIFS(T$4:T$103,T14,I$4:I$103,"Yes")>=2,N14<W14*(1-Settings!$B$12)),"Well under median: check scope","")) | AC14: =IF(B14="","",TRIM(IF(COUNTIF(D14:H14,"Yes")<5,"Compliance gates not all Yes. ","")&IF(SUMPRODUCT(--ISTEXT(J14:M14))>0,"A price cell holds text, not a number. ","")&IF(N(J14)<=0,"No quoted price. ",IF(N(N14)<=0,"Levelled price is $0 or less. ",""))&IF(U14=0,"Package isn't on the Packages tab. ","")&IF(SUMPRODUCT(ISTEXT(O14:S14)+(O14:S14<0)+(O14:S14>10))>0,"Scores must be 0 to 10 (capped). ","")&IF(AND(AA14=1,COUNTIFS(T$4:T$103,T14,AA$4:AA$103,1)>1),"Tied for 1st: ask both for clarifications. ",""))) | AD14: =T14&"|"&AA14
I15: =IF(B15="","",IF(AND(COUNTIF(D15:H15,"Yes")=5,SUMPRODUCT(--ISTEXT(J15:M15))=0,N(J15)>0,N(N15)>0,U15>0),"Yes","No")) | N15: =IF(B15="","",N(J15)+N(K15)+N(L15)+N(M15)) | T15: =IF(A15="","",LEFT(A15,2)) | U15: =IF(A15="",0,IFERROR(MATCH(LEFT(A15,3)&"*",'Tender Setup'!$A$4:$A$33,0),0)) | V15: {=IF(I15<>"Yes","",MIN(IF((T$4:T$103=T15)*(I$4:I$103="Yes"),N$4:N$103)))} | W15: {=IF(I15<>"Yes","",MEDIAN(IF((T$4:T$103=T15)*(I$4:I$103="Yes"),N$4:N$103)))} | X15: =IF(I15<>"Yes",0,V15/N15*INDEX('Tender Setup'!$C$4:$C$33,U15)) | Y15: =IF(I15<>"Yes",0,(MIN(10,MAX(0,N(O15)))*INDEX('Tender Setup'!$D$4:$D$33,U15)+MIN(10,MAX(0,N(P15)))*INDEX('Tender Setup'!$E$4:$E$33,U15)+MIN(10,MAX(0,N(Q15)))*INDEX('Tender Setup'!$F$4:$F$33,U15)+MIN(10,MAX(0,N(R15)))*INDEX('Tender Setup'!$G$4:$G$33,U15)+MIN(10,MAX(0,N(S15)))*INDEX('Tender Setup'!$H$4:$H$33,U15))/10) | Z15: =IF(B15="","",IF(I15<>"Yes",0,IF(N(INDEX('Tender Setup'!$I$4:$I$33,U15))=0,0,(X15+Y15)*100/INDEX('Tender Setup'!$I$4:$I$33,U15)))) | AA15: =IF(B15="","",IF(I15<>"Yes","Excluded",COUNTIFS(T$4:T$103,T15,I$4:I$103,"Yes",Z$4:Z$103,">"&Z15)+1)) | AB15: =IF(I15<>"Yes","",IF(AND(COUNTIFS(T$4:T$103,T15,I$4:I$103,"Yes")>=2,N15<W15*(1-Settings!$B$12)),"Well under median: check scope","")) | AC15: =IF(B15="","",TRIM(IF(COUNTIF(D15:H15,"Yes")<5,"Compliance gates not all Yes. ","")&IF(SUMPRODUCT(--ISTEXT(J15:M15))>0,"A price cell holds text, not a number. ","")&IF(N(J15)<=0,"No quoted price. ",IF(N(N15)<=0,"Levelled price is $0 or less. ",""))&IF(U15=0,"Package isn't on the Packages tab. ","")&IF(SUMPRODUCT(ISTEXT(O15:S15)+(O15:S15<0)+(O15:S15>10))>0,"Scores must be 0 to 10 (capped). ","")&IF(AND(AA15=1,COUNTIFS(T$4:T$103,T15,AA$4:AA$103,1)>1),"Tied for 1st: ask both for clarifications. ",""))) | AD15: =T15&"|"&AA15
I16: =IF(B16="","",IF(AND(COUNTIF(D16:H16,"Yes")=5,SUMPRODUCT(--ISTEXT(J16:M16))=0,N(J16)>0,N(N16)>0,U16>0),"Yes","No")) | N16: =IF(B16="","",N(J16)+N(K16)+N(L16)+N(M16)) | T16: =IF(A16="","",LEFT(A16,2)) | U16: =IF(A16="",0,IFERROR(MATCH(LEFT(A16,3)&"*",'Tender Setup'!$A$4:$A$33,0),0)) | V16: {=IF(I16<>"Yes","",MIN(IF((T$4:T$103=T16)*(I$4:I$103="Yes"),N$4:N$103)))} | W16: {=IF(I16<>"Yes","",MEDIAN(IF((T$4:T$103=T16)*(I$4:I$103="Yes"),N$4:N$103)))} | X16: =IF(I16<>"Yes",0,V16/N16*INDEX('Tender Setup'!$C$4:$C$33,U16)) | Y16: =IF(I16<>"Yes",0,(MIN(10,MAX(0,N(O16)))*INDEX('Tender Setup'!$D$4:$D$33,U16)+MIN(10,MAX(0,N(P16)))*INDEX('Tender Setup'!$E$4:$E$33,U16)+MIN(10,MAX(0,N(Q16)))*INDEX('Tender Setup'!$F$4:$F$33,U16)+MIN(10,MAX(0,N(R16)))*INDEX('Tender Setup'!$G$4:$G$33,U16)+MIN(10,MAX(0,N(S16)))*INDEX('Tender Setup'!$H$4:$H$33,U16))/10) | Z16: =IF(B16="","",IF(I16<>"Yes",0,IF(N(INDEX('Tender Setup'!$I$4:$I$33,U16))=0,0,(X16+Y16)*100/INDEX('Tender Setup'!$I$4:$I$33,U16)))) | AA16: =IF(B16="","",IF(I16<>"Yes","Excluded",COUNTIFS(T$4:T$103,T16,I$4:I$103,"Yes",Z$4:Z$103,">"&Z16)+1)) | AB16: =IF(I16<>"Yes","",IF(AND(COUNTIFS(T$4:T$103,T16,I$4:I$103,"Yes")>=2,N16<W16*(1-Settings!$B$12)),"Well under median: check scope","")) | AC16: =IF(B16="","",TRIM(IF(COUNTIF(D16:H16,"Yes")<5,"Compliance gates not all Yes. ","")&IF(SUMPRODUCT(--ISTEXT(J16:M16))>0,"A price cell holds text, not a number. ","")&IF(N(J16)<=0,"No quoted price. ",IF(N(N16)<=0,"Levelled price is $0 or less. ",""))&IF(U16=0,"Package isn't on the Packages tab. ","")&IF(SUMPRODUCT(ISTEXT(O16:S16)+(O16:S16<0)+(O16:S16>10))>0,"Scores must be 0 to 10 (capped). ","")&IF(AND(AA16=1,COUNTIFS(T$4:T$103,T16,AA$4:AA$103,1)>1),"Tied for 1st: ask both for clarifications. ",""))) | AD16: =T16&"|"&AA16
I17: =IF(B17="","",IF(AND(COUNTIF(D17:H17,"Yes")=5,SUMPRODUCT(--ISTEXT(J17:M17))=0,N(J17)>0,N(N17)>0,U17>0),"Yes","No")) | N17: =IF(B17="","",N(J17)+N(K17)+N(L17)+N(M17)) | T17: =IF(A17="","",LEFT(A17,2)) | U17: =IF(A17="",0,IFERROR(MATCH(LEFT(A17,3)&"*",'Tender Setup'!$A$4:$A$33,0),0)) | V17: {=IF(I17<>"Yes","",MIN(IF((T$4:T$103=T17)*(I$4:I$103="Yes"),N$4:N$103)))} | W17: {=IF(I17<>"Yes","",MEDIAN(IF((T$4:T$103=T17)*(I$4:I$103="Yes"),N$4:N$103)))} | X17: =IF(I17<>"Yes",0,V17/N17*INDEX('Tender Setup'!$C$4:$C$33,U17)) | Y17: =IF(I17<>"Yes",0,(MIN(10,MAX(0,N(O17)))*INDEX('Tender Setup'!$D$4:$D$33,U17)+MIN(10,MAX(0,N(P17)))*INDEX('Tender Setup'!$E$4:$E$33,U17)+MIN(10,MAX(0,N(Q17)))*INDEX('Tender Setup'!$F$4:$F$33,U17)+MIN(10,MAX(0,N(R17)))*INDEX('Tender Setup'!$G$4:$G$33,U17)+MIN(10,MAX(0,N(S17)))*INDEX('Tender Setup'!$H$4:$H$33,U17))/10) | Z17: =IF(B17="","",IF(I17<>"Yes",0,IF(N(INDEX('Tender Setup'!$I$4:$I$33,U17))=0,0,(X17+Y17)*100/INDEX('Tender Setup'!$I$4:$I$33,U17)))) | AA17: =IF(B17="","",IF(I17<>"Yes","Excluded",COUNTIFS(T$4:T$103,T17,I$4:I$103,"Yes",Z$4:Z$103,">"&Z17)+1)) | AB17: =IF(I17<>"Yes","",IF(AND(COUNTIFS(T$4:T$103,T17,I$4:I$103,"Yes")>=2,N17<W17*(1-Settings!$B$12)),"Well under median: check scope","")) | AC17: =IF(B17="","",TRIM(IF(COUNTIF(D17:H17,"Yes")<5,"Compliance gates not all Yes. ","")&IF(SUMPRODUCT(--ISTEXT(J17:M17))>0,"A price cell holds text, not a number. ","")&IF(N(J17)<=0,"No quoted price. ",IF(N(N17)<=0,"Levelled price is $0 or less. ",""))&IF(U17=0,"Package isn't on the Packages tab. ","")&IF(SUMPRODUCT(ISTEXT(O17:S17)+(O17:S17<0)+(O17:S17>10))>0,"Scores must be 0 to 10 (capped). ","")&IF(AND(AA17=1,COUNTIFS(T$4:T$103,T17,AA$4:AA$103,1)>1),"Tied for 1st: ask both for clarifications. ",""))) | AD17: =T17&"|"&AA17
I18: =IF(B18="","",IF(AND(COUNTIF(D18:H18,"Yes")=5,SUMPRODUCT(--ISTEXT(J18:M18))=0,N(J18)>0,N(N18)>0,U18>0),"Yes","No")) | N18: =IF(B18="","",N(J18)+N(K18)+N(L18)+N(M18)) | T18: =IF(A18="","",LEFT(A18,2)) | U18: =IF(A18="",0,IFERROR(MATCH(LEFT(A18,3)&"*",'Tender Setup'!$A$4:$A$33,0),0)) | V18: {=IF(I18<>"Yes","",MIN(IF((T$4:T$103=T18)*(I$4:I$103="Yes"),N$4:N$103)))} | W18: {=IF(I18<>"Yes","",MEDIAN(IF((T$4:T$103=T18)*(I$4:I$103="Yes"),N$4:N$103)))} | X18: =IF(I18<>"Yes",0,V18/N18*INDEX('Tender Setup'!$C$4:$C$33,U18)) | Y18: =IF(I18<>"Yes",0,(MIN(10,MAX(0,N(O18)))*INDEX('Tender Setup'!$D$4:$D$33,U18)+MIN(10,MAX(0,N(P18)))*INDEX('Tender Setup'!$E$4:$E$33,U18)+MIN(10,MAX(0,N(Q18)))*INDEX('Tender Setup'!$F$4:$F$33,U18)+MIN(10,MAX(0,N(R18)))*INDEX('Tender Setup'!$G$4:$G$33,U18)+MIN(10,MAX(0,N(S18)))*INDEX('Tender Setup'!$H$4:$H$33,U18))/10) | Z18: =IF(B18="","",IF(I18<>"Yes",0,IF(N(INDEX('Tender Setup'!$I$4:$I$33,U18))=0,0,(X18+Y18)*100/INDEX('Tender Setup'!$I$4:$I$33,U18)))) | AA18: =IF(B18="","",IF(I18<>"Yes","Excluded",COUNTIFS(T$4:T$103,T18,I$4:I$103,"Yes",Z$4:Z$103,">"&Z18)+1)) | AB18: =IF(I18<>"Yes","",IF(AND(COUNTIFS(T$4:T$103,T18,I$4:I$103,"Yes")>=2,N18<W18*(1-Settings!$B$12)),"Well under median: check scope","")) | AC18: =IF(B18="","",TRIM(IF(COUNTIF(D18:H18,"Yes")<5,"Compliance gates not all Yes. ","")&IF(SUMPRODUCT(--ISTEXT(J18:M18))>0,"A price cell holds text, not a number. ","")&IF(N(J18)<=0,"No quoted price. ",IF(N(N18)<=0,"Levelled price is $0 or less. ",""))&IF(U18=0,"Package isn't on the Packages tab. ","")&IF(SUMPRODUCT(ISTEXT(O18:S18)+(O18:S18<0)+(O18:S18>10))>0,"Scores must be 0 to 10 (capped). ","")&IF(AND(AA18=1,COUNTIFS(T$4:T$103,T18,AA$4:AA$103,1)>1),"Tied for 1st: ask both for clarifications. ",""))) | AD18: =T18&"|"&AA18
... I103: =IF(B103="","",IF(AND(COUNTIF(D103:H103,"Yes")=5,SUMPRODUCT(--ISTEXT(J103:M103))=0,N(J103)>0,N(N103)>0,U103>0),"Yes","No")) | N103: =IF(B103="","",N(J103)+N(K103)+N(L103)+N(M103)) | T103: =IF(A103="","",LEFT(A103,2)) | U103: =IF(A103="",0,IFERROR(MATCH(LEFT(A103,3)&"*",'Tender Setup'!$A$4:$A$33,0),0)) | V103: {=IF(I103<>"Yes","",MIN(IF((T$4:T$103=T103)*(I$4:I$103="Yes"),N$4:N$103)))} | W103: {=IF(I103<>"Yes","",MEDIAN(IF((T$4:T$103=T103)*(I$4:I$103="Yes"),N$4:N$103)))} | X103: =IF(I103<>"Yes",0,V103/N103*INDEX('Tender Setup'!$C$4:$C$33,U103)) | Y103: =IF(I103<>"Yes",0,(MIN(10,MAX(0,N(O103)))*INDEX('Tender Setup'!$D$4:$D$33,U103)+MIN(10,MAX(0,N(P103)))*INDEX('Tender Setup'!$E$4:$E$33,U103)+MIN(10,MAX(0,N(Q103)))*INDEX('Tender Setup'!$F$4:$F$33,U103)+MIN(10,MAX(0,N(R103)))*INDEX('Tender Setup'!$G$4:$G$33,U103)+MIN(10,MAX(0,N(S103)))*INDEX('Tender Setup'!$H$4:$H$33,U103))/10) | Z103: =IF(B103="","",IF(I103<>"Yes",0,IF(N(INDEX('Tender Setup'!$I$4:$I$33,U103))=0,0,(X103+Y103)*100/INDEX('Tender Setup'!$I$4:$I$33,U103)))) | AA103: =IF(B103="","",IF(I103<>"Yes","Excluded",COUNTIFS(T$4:T$103,T103,I$4:I$103,"Yes",Z$4:Z$103,">"&Z103)+1)) | AB103: =IF(I103<>"Yes","",IF(AND(COUNTIFS(T$4:T$103,T103,I$4:I$103,"Yes")>=2,N103<W103*(1-Settings!$B$12)),"Well under median: check scope","")) | AC103: =IF(B103="","",TRIM(IF(COUNTIF(D103:H103,"Yes")<5,"Compliance gates not all Yes. ","")&IF(SUMPRODUCT(--ISTEXT(J103:M103))>0,"A price cell holds text, not a number. ","")&IF(N(J103)<=0,"No quoted price. ",IF(N(N103)<=0,"Levelled price is $0 or less. ",""))&IF(U103=0,"Package isn't on the Packages tab. ","")&IF(SUMPRODUCT(ISTEXT(O103:S103)+(O103:S103<0)+(O103:S103>10))>0,"Scores must be 0 to 10 (capped). ","")&IF(AND(AA103=1,COUNTIFS(T$4:T$103,T103,AA$4:AA$103,1)>1),"Tied for 1st: ask both for clarifications. ",""))) | AD103: =T103&"|"&AA103

Sheet Packages
A1: Trade packages & cost control
A2: Budget, committed (signed contracts + approved variations), paid and forecast for each package. Other tabs find a package by its two-digit No., so you can rename it safely. Type your own forecast in Forecast override if you have one.
A3: No. | B3: Package | C3: Scope | D3: Usual basis | E3: Licence / registration | F3: Paperwork to collect | G3: On site from | H3: Budget ($) | I3: Contracted ($) | J3: Approved variations ($) | K3: Committed ($) | L3: Paid ($) | M3: Forecast override ($) | N3: Forecast final ($) | O3: Under / (over) budget ($) | P3: Flag | Q3: Check | R3: Drive folder | S3: Folder | T3: Notes
A4: 01 | B4: 01 Surveyor | C4: Surveyor: set-out & re-establishment | D4: Lump sum | E4: Licensed land surveyor | F4: Set-out certificate | G4: G4 | I4: =IF(OR($B4="",$A4=""),"",SUMIFS('Trades'!$T$4:$T$103,'Trades'!$A$4:$A$103,$A4&" *",'Trades'!$S$4:$S$103,"Yes")) | J4: =IF(OR($B4="",$A4=""),"",SUMIFS('Variations'!$G$4:$G$153,'Variations'!$C$4:$C$153,$A4&" *",'Variations'!$I$4:$I$153,"Approved")) | K4: =IF(B4="","",N(I4)+N(J4)) | L4: =IF(OR($B4="",$A4=""),"",SUMIFS('Payments'!$F$4:$F$303,'Payments'!$B$4:$B$303,$A4&" *",'Payments'!$K$4:$K$303,"Yes")) | N4: =IF(B4="","",IF(ISNUMBER(M4),M4,IF(N(K4)>0,K4,N(H4)))) | O4: =IF(OR(B4="",N(H4)=0),"",H4-N4) | P4: =IF(OR(B4="",N(H4)=0),"",IF(N4>H4*(1+Settings!$B$13),"Over budget","")) | Q4: =IF(B4="","",TRIM(IF(OR(A4="",LEFT(B4,LEN(A4)+1)<>A4&" "),"Start the name with its No. and a space, e.g. 21 Pool. ","")&IF(AND(A4<>"",COUNTIF(A$4:A$33,A4)>1),"Duplicate No. ",""))) | R4: =IF(B4="","",IFERROR(INDEX('Google Drive Map'!$B$4:$B$33,MATCH("04/"&LEFT(B4,2),'Google Drive Map'!$A$4:$A$33,0)),"04 Trades & Tenders/"&B4)) | S4: =IF(R4="","",IF(IFERROR(INDEX('Google Drive Map'!$G$4:$G$33,MATCH(R4,'Google Drive Map'!$B$4:$B$33,0))&"","")="","",HYPERLINK(INDEX('Google Drive Map'!$G$4:$G$33,MATCH(R4,'Google Drive Map'!$B$4:$B$33,0)),"Open")))
A5: 02 | B5: 02 Demolition & earthworks | C5: Demolition / earthworks / excavation | D5: Lump sum or hourly rates | E5: Registered demolisher (if demolishing) | F5: SWMS, tip dockets, asbestos clearance | G5: G4 | I5: =IF(OR($B5="",$A5=""),"",SUMIFS('Trades'!$T$4:$T$103,'Trades'!$A$4:$A$103,$A5&" *",'Trades'!$S$4:$S$103,"Yes")) | J5: =IF(OR($B5="",$A5=""),"",SUMIFS('Variations'!$G$4:$G$153,'Variations'!$C$4:$C$153,$A5&" *",'Variations'!$I$4:$I$153,"Approved")) | K5: =IF(B5="","",N(I5)+N(J5)) | L5: =IF(OR($B5="",$A5=""),"",SUMIFS('Payments'!$F$4:$F$303,'Payments'!$B$4:$B$303,$A5&" *",'Payments'!$K$4:$K$303,"Yes")) | N5: =IF(B5="","",IF(ISNUMBER(M5),M5,IF(N(K5)>0,K5,N(H5)))) | O5: =IF(OR(B5="",N(H5)=0),"",H5-N5) | P5: =IF(OR(B5="",N(H5)=0),"",IF(N5>H5*(1+Settings!$B$13),"Over budget","")) | Q5: =IF(B5="","",TRIM(IF(OR(A5="",LEFT(B5,LEN(A5)+1)<>A5&" "),"Start the name with its No. and a space, e.g. 21 Pool. ","")&IF(AND(A5<>"",COUNTIF(A$4:A$33,A5)>1),"Duplicate No. ",""))) | R5: =IF(B5="","",IFERROR(INDEX('Google Drive Map'!$B$4:$B$33,MATCH("04/"&LEFT(B5,2),'Google Drive Map'!$A$4:$A$33,0)),"04 Trades & Tenders/"&B5)) | S5: =IF(R5="","",IF(IFERROR(INDEX('Google Drive Map'!$G$4:$G$33,MATCH(R5,'Google Drive Map'!$B$4:$B$33,0))&"","")="","",HYPERLINK(INDEX('Google Drive Map'!$G$4:$G$33,MATCH(R5,'Google Drive Map'!$B$4:$B$33,0)),"Open")))
A6: 03 | B6: 03 Plumbing & drainage | C6: Plumber: drainage, stormwater, sewer | D6: Lump sum per stage | E6: BPC licensed plumber | F6: Plumbing compliance certificate (PCC) | G6: G4 | I6: =IF(OR($B6="",$A6=""),"",SUMIFS('Trades'!$T$4:$T$103,'Trades'!$A$4:$A$103,$A6&" *",'Trades'!$S$4:$S$103,"Yes")) | J6: =IF(OR($B6="",$A6=""),"",SUMIFS('Variations'!$G$4:$G$153,'Variations'!$C$4:$C$153,$A6&" *",'Variations'!$I$4:$I$153,"Approved")) | K6: =IF(B6="","",N(I6)+N(J6)) | L6: =IF(OR($B6="",$A6=""),"",SUMIFS('Payments'!$F$4:$F$303,'Payments'!$B$4:$B$303,$A6&" *",'Payments'!$K$4:$K$303,"Yes")) | N6: =IF(B6="","",IF(ISNUMBER(M6),M6,IF(N(K6)>0,K6,N(H6)))) | O6: =IF(OR(B6="",N(H6)=0),"",H6-N6) | P6: =IF(OR(B6="",N(H6)=0),"",IF(N6>H6*(1+Settings!$B$13),"Over budget","")) | Q6: =IF(B6="","",TRIM(IF(OR(A6="",LEFT(B6,LEN(A6)+1)<>A6&" "),"Start the name with its No. and a space, e.g. 21 Pool. ","")&IF(AND(A6<>"",COUNTIF(A$4:A$33,A6)>1),"Duplicate No. ",""))) | R6: =IF(B6="","",IFERROR(INDEX('Google Drive Map'!$B$4:$B$33,MATCH("04/"&LEFT(B6,2),'Google Drive Map'!$A$4:$A$33,0)),"04 Trades & Tenders/"&B6)) | S6: =IF(R6="","",IF(IFERROR(INDEX('Google Drive Map'!$G$4:$G$33,MATCH(R6,'Google Drive Map'!$B$4:$B$33,0))&"","")="","",HYPERLINK(INDEX('Google Drive Map'!$G$4:$G$33,MATCH(R6,'Google Drive Map'!$B$4:$B$33,0)),"Open")))
A7: 04 | B7: 04 Concreter | C7: Concreter: footings & slab | D7: Lump sum (m² + extras) | E7: Registered if over $10k* | F7: Engineer pour approval, pre-pour inspection | G7: G4 | I7: =IF(OR($B7="",$A7=""),"",SUMIFS('Trades'!$T$4:$T$103,'Trades'!$A$4:$A$103,$A7&" *",'Trades'!$S$4:$S$103,"Yes")) | J7: =IF(OR($B7="",$A7=""),"",SUMIFS('Variations'!$G$4:$G$153,'Variations'!$C$4:$C$153,$A7&" *",'Variations'!$I$4:$I$153,"Approved")) | K7: =IF(B7="","",N(I7)+N(J7)) | L7: =IF(OR($B7="",$A7=""),"",SUMIFS('Payments'!$F$4:$F$303,'Payments'!$B$4:$B$303,$A7&" *",'Payments'!$K$4:$K$303,"Yes")) | N7: =IF(B7="","",IF(ISNUMBER(M7),M7,IF(N(K7)>0,K7,N(H7)))) | O7: =IF(OR(B7="",N(H7)=0),"",H7-N7) | P7: =IF(OR(B7="",N(H7)=0),"",IF(N7>H7*(1+Settings!$B$13),"Over budget","")) | Q7: =IF(B7="","",TRIM(IF(OR(A7="",LEFT(B7,LEN(A7)+1)<>A7&" "),"Start the name with its No. and a space, e.g. 21 Pool. ","")&IF(AND(A7<>"",COUNTIF(A$4:A$33,A7)>1),"Duplicate No. ",""))) | R7: =IF(B7="","",IFERROR(INDEX('Google Drive Map'!$B$4:$B$33,MATCH("04/"&LEFT(B7,2),'Google Drive Map'!$A$4:$A$33,0)),"04 Trades & Tenders/"&B7)) | S7: =IF(R7="","",IF(IFERROR(INDEX('Google Drive Map'!$G$4:$G$33,MATCH(R7,'Google Drive Map'!$B$4:$B$33,0))&"","")="","",HYPERLINK(INDEX('Google Drive Map'!$G$4:$G$33,MATCH(R7,'Google Drive Map'!$B$4:$B$33,0)),"Open")))
A8: 05 | B8: 05 Termite management | C8: Termite management | D8: Supply & install | E8: Licensed pest controller | F8: AS 3660.1 certificate, durable notice | G8: G4 | I8: =IF(OR($B8="",$A8=""),"",SUMIFS('Trades'!$T$4:$T$103,'Trades'!$A$4:$A$103,$A8&" *",'Trades'!$S$4:$S$103,"Yes")) | J8: =IF(OR($B8="",$A8=""),"",SUMIFS('Variations'!$G$4:$G$153,'Variations'!$C$4:$C$153,$A8&" *",'Variations'!$I$4:$I$153,"Approved")) | K8: =IF(B8="","",N(I8)+N(J8)) | L8: =IF(OR($B8="",$A8=""),"",SUMIFS('Payments'!$F$4:$F$303,'Payments'!$B$4:$B$303,$A8&" *",'Payments'!$K$4:$K$303,"Yes")) | N8: =IF(B8="","",IF(ISNUMBER(M8),M8,IF(N(K8)>0,K8,N(H8)))) | O8: =IF(OR(B8="",N(H8)=0),"",H8-N8) | P8: =IF(OR(B8="",N(H8)=0),"",IF(N8>H8*(1+Settings!$B$13),"Over budget","")) | Q8: =IF(B8="","",TRIM(IF(OR(A8="",LEFT(B8,LEN(A8)+1)<>A8&" "),"Start the name with its No. and a space, e.g. 21 Pool. ","")&IF(AND(A8<>"",COUNTIF(A$4:A$33,A8)>1),"Duplicate No. ",""))) | R8: =IF(B8="","",IFERROR(INDEX('Google Drive Map'!$B$4:$B$33,MATCH("04/"&LEFT(B8,2),'Google Drive Map'!$A$4:$A$33,0)),"04 Trades & Tenders/"&B8)) | S8: =IF(R8="","",IF(IFERROR(INDEX('Google Drive Map'!$G$4:$G$33,MATCH(R8,'Google Drive Map'!$B$4:$B$33,0))&"","")="","",HYPERLINK(INDEX('Google Drive Map'!$G$4:$G$33,MATCH(R8,'Google Drive Map'!$B$4:$B$33,0)),"Open")))
A9: 06 | B9: 06 Frame & truss supply | C9: Frame & truss supply | D9: Supply only | E9: n/a (supplier) | F9: Truss & frame design certificates | G9: G5 | I9: =IF(OR($B9="",$A9=""),"",SUMIFS('Trades'!$T$4:$T$103,'Trades'!$A$4:$A$103,$A9&" *",'Trades'!$S$4:$S$103,"Yes")) | J9: =IF(OR($B9="",$A9=""),"",SUMIFS('Variations'!$G$4:$G$153,'Variations'!$C$4:$C$153,$A9&" *",'Variations'!$I$4:$I$153,"Approved")) | K9: =IF(B9="","",N(I9)+N(J9)) | L9: =IF(OR($B9="",$A9=""),"",SUMIFS('Payments'!$F$4:$F$303,'Payments'!$B$4:$B$303,$A9&" *",'Payments'!$K$4:$K$303,"Yes")) | N9: =IF(B9="","",IF(ISNUMBER(M9),M9,IF(N(K9)>0,K9,N(H9)))) | O9: =IF(OR(B9="",N(H9)=0),"",H9-N9) | P9: =IF(OR(B9="",N(H9)=0),"",IF(N9>H9*(1+Settings!$B$13),"Over budget","")) | Q9: =IF(B9="","",TRIM(IF(OR(A9="",LEFT(B9,LEN(A9)+1)<>A9&" "),"Start the name with its No. and a space, e.g. 21 Pool. ","")&IF(AND(A9<>"",COUNTIF(A$4:A$33,A9)>1),"Duplicate No. ",""))) | R9: =IF(B9="","",IFERROR(INDEX('Google Drive Map'!$B$4:$B$33,MATCH("04/"&LEFT(B9,2),'Google Drive Map'!$A$4:$A$33,0)),"04 Trades & Tenders/"&B9)) | S9: =IF(R9="","",IF(IFERROR(INDEX('Google Drive Map'!$G$4:$G$33,MATCH(R9,'Google Drive Map'!$B$4:$B$33,0))&"","")="","",HYPERLINK(INDEX('Google Drive Map'!$G$4:$G$33,MATCH(R9,'Google Drive Map'!$B$4:$B$33,0)),"Open")))
A10: 07 | B10: 07 Carpenter (frame) | C10: Carpenter: frame, fascia, eaves | D10: Labour only or lump sum | E10: Registered if over $10k* | F10: Frame inspection pass | G10: G5 | I10: =IF(OR($B10="",$A10=""),"",SUMIFS('Trades'!$T$4:$T$103,'Trades'!$A$4:$A$103,$A10&" *",'Trades'!$S$4:$S$103,"Yes")) | J10: =IF(OR($B10="",$A10=""),"",SUMIFS('Variations'!$G$4:$G$153,'Variations'!$C$4:$C$153,$A10&" *",'Variations'!$I$4:$I$153,"Approved")) | K10: =IF(B10="","",N(I10)+N(J10)) | L10: =IF(OR($B10="",$A10=""),"",SUMIFS('Payments'!$F$4:$F$303,'Payments'!$B$4:$B$303,$A10&" *",'Payments'!$K$4:$K$303,"Yes")) | N10: =IF(B10="","",IF(ISNUMBER(M10),M10,IF(N(K10)>0,K10,N(H10)))) | O10: =IF(OR(B10="",N(H10)=0),"",H10-N10) | P10: =IF(OR(B10="",N(H10)=0),"",IF(N10>H10*(1+Settings!$B$13),"Over budget","")) | Q10: =IF(B10="","",TRIM(IF(OR(A10="",LEFT(B10,LEN(A10)+1)<>A10&" "),"Start the name with its No. and a space, e.g. 21 Pool. ","")&IF(AND(A10<>"",COUNTIF(A$4:A$33,A10)>1),"Duplicate No. ",""))) | R10: =IF(B10="","",IFERROR(INDEX('Google Drive Map'!$B$4:$B$33,MATCH("04/"&LEFT(B10,2),'Google Drive Map'!$A$4:$A$33,0)),"04 Trades & Tenders/"&B10)) | S10: =IF(R10="","",IF(IFERROR(INDEX('Google Drive Map'!$G$4:$G$33,MATCH(R10,'Google Drive Map'!$B$4:$B$33,0))&"","")="","",HYPERLINK(INDEX('Google Drive Map'!$G$4:$G$33,MATCH(R10,'Google Drive Map'!$B$4:$B$33,0)),"Open")))
A11: 08 | B11: 08 Roofing | C11: Roofer & plumber: roof, gutters, downpipes | D11: Supply & install | E11: Roof plumbing licence | F11: PCC (roofing) | G11: G5 | I11: =IF(OR($B11="",$A11=""),"",SUMIFS('Trades'!$T$4:$T$103,'Trades'!$A$4:$A$103,$A11&" *",'Trades'!$S$4:$S$103,"Yes")) | J11: =IF(OR($B11="",$A11=""),"",SUMIFS('Variations'!$G$4:$G$153,'Variations'!$C$4:$C$153,$A11&" *",'Variations'!$I$4:$I$153,"Approved")) | K11: =IF(B11="","",N(I11)+N(J11)) | L11: =IF(OR($B11="",$A11=""),"",SUMIFS('Payments'!$F$4:$F$303,'Payments'!$B$4:$B$303,$A11&" *",'Payments'!$K$4:$K$303,"Yes")) | N11: =IF(B11="","",IF(ISNUMBER(M11),M11,IF(N(K11)>0,K11,N(H11)))) | O11: =IF(OR(B11="",N(H11)=0),"",H11-N11) | P11: =IF(OR(B11="",N(H11)=0),"",IF(N11>H11*(1+Settings!$B$13),"Over budget","")) | Q11: =IF(B11="","",TRIM(IF(OR(A11="",LEFT(B11,LEN(A11)+1)<>A11&" "),"Start the name with its No. and a space, e.g. 21 Pool. ","")&IF(AND(A11<>"",COUNTIF(A$4:A$33,A11)>1),"Duplicate No. ",""))) | R11: =IF(B11="","",IFERROR(INDEX('Google Drive Map'!$B$4:$B$33,MATCH("04/"&LEFT(B11,2),'Google Drive Map'!$A$4:$A$33,0)),"04 Trades & Tenders/"&B11)) | S11: =IF(R11="","",IF(IFERROR(INDEX('Google Drive Map'!$G$4:$G$33,MATCH(R11,'Google Drive Map'!$B$4:$B$33,0))&"","")="","",HYPERLINK(INDEX('Google Drive Map'!$G$4:$G$33,MATCH(R11,'Google Drive Map'!$B$4:$B$33,0)),"Open")))
A12: 09 | B12: 09 Windows & external doors | C12: Windows & external doors | D12: Supply (& install) | E12: n/a / glazier | F12: AS 2047 / 1288 glazing certificate, energy labels | G12: G5 | I12: =IF(OR($B12="",$A12=""),"",SUMIFS('Trades'!$T$4:$T$103,'Trades'!$A$4:$A$103,$A12&" *",'Trades'!$S$4:$S$103,"Yes")) | J12: =IF(OR($B12="",$A12=""),"",SUMIFS('Variations'!$G$4:$G$153,'Variations'!$C$4:$C$153,$A12&" *",'Variations'!$I$4:$I$153,"Approved")) | K12: =IF(B12="","",N(I12)+N(J12)) | L12: =IF(OR($B12="",$A12=""),"",SUMIFS('Payments'!$F$4:$F$303,'Payments'!$B$4:$B$303,$A12&" *",'Payments'!$K$4:$K$303,"Yes")) | N12: =IF(B12="","",IF(ISNUMBER(M12),M12,IF(N(K12)>0,K12,N(H12)))) | O12: =IF(OR(B12="",N(H12)=0),"",H12-N12) | P12: =IF(OR(B12="",N(H12)=0),"",IF(N12>H12*(1+Settings!$B$13),"Over budget","")) | Q12: =IF(B12="","",TRIM(IF(OR(A12="",LEFT(B12,LEN(A12)+1)<>A12&" "),"Start the name with its No. and a space, e.g. 21 Pool. ","")&IF(AND(A12<>"",COUNTIF(A$4:A$33,A12)>1),"Duplicate No. ",""))) | R12: =IF(B12="","",IFERROR(INDEX('Google Drive Map'!$B$4:$B$33,MATCH("04/"&LEFT(B12,2),'Google Drive Map'!$A$4:$A$33,0)),"04 Trades & Tenders/"&B12)) | S12: =IF(R12="","",IF(IFERROR(INDEX('Google Drive Map'!$G$4:$G$33,MATCH(R12,'Google Drive Map'!$B$4:$B$33,0))&"","")="","",HYPERLINK(INDEX('Google Drive Map'!$G$4:$G$33,MATCH(R12,'Google Drive Map'!$B$4:$B$33,0)),"Open")))
A13: 10 | B13: 10 Bricklayer & cladding | C13: Bricklayer / cladding | D13: Rate per 1,000 bricks or m² | E13: Registered if over $10k* | F13: Wall-tie & flashing photos | G13: G5 | I13: =IF(OR($B13="",$A13=""),"",SUMIFS('Trades'!$T$4:$T$103,'Trades'!$A$4:$A$103,$A13&" *",'Trades'!$S$4:$S$103,"Yes")) | J13: =IF(OR($B13="",$A13=""),"",SUMIFS('Variations'!$G$4:$G$153,'Variations'!$C$4:$C$153,$A13&" *",'Variations'!$I$4:$I$153,"Approved")) | K13: =IF(B13="","",N(I13)+N(J13)) | L13: =IF(OR($B13="",$A13=""),"",SUMIFS('Payments'!$F$4:$F$303,'Payments'!$B$4:$B$303,$A13&" *",'Payments'!$K$4:$K$303,"Yes")) | N13: =IF(B13="","",IF(ISNUMBER(M13),M13,IF(N(K13)>0,K13,N(H13)))) | O13: =IF(OR(B13="",N(H13)=0),"",H13-N13) | P13: =IF(OR(B13="",N(H13)=0),"",IF(N13>H13*(1+Settings!$B$13),"Over budget","")) | Q13: =IF(B13="","",TRIM(IF(OR(A13="",LEFT(B13,LEN(A13)+1)<>A13&" "),"Start the name with its No. and a space, e.g. 21 Pool. ","")&IF(AND(A13<>"",COUNTIF(A$4:A$33,A13)>1),"Duplicate No. ",""))) | R13: =IF(B13="","",IFERROR(INDEX('Google Drive Map'!$B$4:$B$33,MATCH("04/"&LEFT(B13,2),'Google Drive Map'!$A$4:$A$33,0)),"04 Trades & Tenders/"&B13)) | S13: =IF(R13="","",IF(IFERROR(INDEX('Google Drive Map'!$G$4:$G$33,MATCH(R13,'Google Drive Map'!$B$4:$B$33,0))&"","")="","",HYPERLINK(INDEX('Google Drive Map'!$G$4:$G$33,MATCH(R13,'Google Drive Map'!$B$4:$B$33,0)),"Open")))
A14: 11 | B14: 11 Electrician | C14: Electrician: rough-in & fit-off | D14: Lump sum + points schedule | E14: ESV licensed electrician | F14: Certificate of Electrical Safety | G14: G5 | I14: =IF(OR($B14="",$A14=""),"",SUMIFS('Trades'!$T$4:$T$103,'Trades'!$A$4:$A$103,$A14&" *",'Trades'!$S$4:$S$103,"Yes")) | J14: =IF(OR($B14="",$A14=""),"",SUMIFS('Variations'!$G$4:$G$153,'Variations'!$C$4:$C$153,$A14&" *",'Variations'!$I$4:$I$153,"Approved")) | K14: =IF(B14="","",N(I14)+N(J14)) | L14: =IF(OR($B14="",$A14=""),"",SUMIFS('Payments'!$F$4:$F$303,'Payments'!$B$4:$B$303,$A14&" *",'Payments'!$K$4:$K$303,"Yes")) | N14: =IF(B14="","",IF(ISNUMBER(M14),M14,IF(N(K14)>0,K14,N(H14)))) | O14: =IF(OR(B14="",N(H14)=0),"",H14-N14) | P14: =IF(OR(B14="",N(H14)=0),"",IF(N14>H14*(1+Settings!$B$13),"Over budget","")) | Q14: =IF(B14="","",TRIM(IF(OR(A14="",LEFT(B14,LEN(A14)+1)<>A14&" "),"Start the name with its No. and a space, e.g. 21 Pool. ","")&IF(AND(A14<>"",COUNTIF(A$4:A$33,A14)>1),"Duplicate No. ",""))) | R14: =IF(B14="","",IFERROR(INDEX('Google Drive Map'!$B$4:$B$33,MATCH("04/"&LEFT(B14,2),'Google Drive Map'!$A$4:$A$33,0)),"04 Trades & Tenders/"&B14)) | S14: =IF(R14="","",IF(IFERROR(INDEX('Google Drive Map'!$G$4:$G$33,MATCH(R14,'Google Drive Map'!$B$4:$B$33,0))&"","")="","",HYPERLINK(INDEX('Google Drive Map'!$G$4:$G$33,MATCH(R14,'Google Drive Map'!$B$4:$B$33,0)),"Open")))
A15: 12 | B15: 12 Insulation | C15: Insulation | D15: Supply & install | E15: n/a | F15: Insulation certificate (R-values per energy report) | G15: G5 | I15: =IF(OR($B15="",$A15=""),"",SUMIFS('Trades'!$T$4:$T$103,'Trades'!$A$4:$A$103,$A15&" *",'Trades'!$S$4:$S$103,"Yes")) | J15: =IF(OR($B15="",$A15=""),"",SUMIFS('Variations'!$G$4:$G$153,'Variations'!$C$4:$C$153,$A15&" *",'Variations'!$I$4:$I$153,"Approved")) | K15: =IF(B15="","",N(I15)+N(J15)) | L15: =IF(OR($B15="",$A15=""),"",SUMIFS('Payments'!$F$4:$F$303,'Payments'!$B$4:$B$303,$A15&" *",'Payments'!$K$4:$K$303,"Yes")) | N15: =IF(B15="","",IF(ISNUMBER(M15),M15,IF(N(K15)>0,K15,N(H15)))) | O15: =IF(OR(B15="",N(H15)=0),"",H15-N15) | P15: =IF(OR(B15="",N(H15)=0),"",IF(N15>H15*(1+Settings!$B$13),"Over budget","")) | Q15: =IF(B15="","",TRIM(IF(OR(A15="",LEFT(B15,LEN(A15)+1)<>A15&" "),"Start the name with its No. and a space, e.g. 21 Pool. ","")&IF(AND(A15<>"",COUNTIF(A$4:A$33,A15)>1),"Duplicate No. ",""))) | R15: =IF(B15="","",IFERROR(INDEX('Google Drive Map'!$B$4:$B$33,MATCH("04/"&LEFT(B15,2),'Google Drive Map'!$A$4:$A$33,0)),"04 Trades & Tenders/"&B15)) | S15: =IF(R15="","",IF(IFERROR(INDEX('Google Drive Map'!$G$4:$G$33,MATCH(R15,'Google Drive Map'!$B$4:$B$33,0))&"","")="","",HYPERLINK(INDEX('Google Drive Map'!$G$4:$G$33,MATCH(R15,'Google Drive Map'!$B$4:$B$33,0)),"Open")))
... A23: 20 | B23: 20 Floor coverings & landscaping | C23: Floor coverings, driveway, landscaping | D23: Supply & install | E23: Varies | F23: Warranties | G23: G7 | I23: =IF(OR($B23="",$A23=""),"",SUMIFS('Trades'!$T$4:$T$103,'Trades'!$A$4:$A$103,$A23&" *",'Trades'!$S$4:$S$103,"Yes")) | J23: =IF(OR($B23="",$A23=""),"",SUMIFS('Variations'!$G$4:$G$153,'Variations'!$C$4:$C$153,$A23&" *",'Variations'!$I$4:$I$153,"Approved")) | K23: =IF(B23="","",N(I23)+N(J23)) | L23: =IF(OR($B23="",$A23=""),"",SUMIFS('Payments'!$F$4:$F$303,'Payments'!$B$4:$B$303,$A23&" *",'Payments'!$K$4:$K$303,"Yes")) | N23: =IF(B23="","",IF(ISNUMBER(M23),M23,IF(N(K23)>0,K23,N(H23)))) | O23: =IF(OR(B23="",N(H23)=0),"",H23-N23) | P23: =IF(OR(B23="",N(H23)=0),"",IF(N23>H23*(1+Settings!$B$13),"Over budget","")) | Q23: =IF(B23="","",TRIM(IF(OR(A23="",LEFT(B23,LEN(A23)+1)<>A23&" "),"Start the name with its No. and a space, e.g. 21 Pool. ","")&IF(AND(A23<>"",COUNTIF(A$4:A$33,A23)>1),"Duplicate No. ",""))) | R23: =IF(B23="","",IFERROR(INDEX('Google Drive Map'!$B$4:$B$33,MATCH("04/"&LEFT(B23,2),'Google Drive Map'!$A$4:$A$33,0)),"04 Trades & Tenders/"&B23)) | S23: =IF(R23="","",IF(IFERROR(INDEX('Google Drive Map'!$G$4:$G$33,MATCH(R23,'Google Drive Map'!$B$4:$B$33,0))&"","")="","",HYPERLINK(INDEX('Google Drive Map'!$G$4:$G$33,MATCH(R23,'Google Drive Map'!$B$4:$B$33,0)),"Open")))
I24: =IF(OR($B24="",$A24=""),"",SUMIFS('Trades'!$T$4:$T$103,'Trades'!$A$4:$A$103,$A24&" *",'Trades'!$S$4:$S$103,"Yes")) | J24: =IF(OR($B24="",$A24=""),"",SUMIFS('Variations'!$G$4:$G$153,'Variations'!$C$4:$C$153,$A24&" *",'Variations'!$I$4:$I$153,"Approved")) | K24: =IF(B24="","",N(I24)+N(J24)) | L24: =IF(OR($B24="",$A24=""),"",SUMIFS('Payments'!$F$4:$F$303,'Payments'!$B$4:$B$303,$A24&" *",'Payments'!$K$4:$K$303,"Yes")) | N24: =IF(B24="","",IF(ISNUMBER(M24),M24,IF(N(K24)>0,K24,N(H24)))) | O24: =IF(OR(B24="",N(H24)=0),"",H24-N24) | P24: =IF(OR(B24="",N(H24)=0),"",IF(N24>H24*(1+Settings!$B$13),"Over budget","")) | Q24: =IF(B24="","",TRIM(IF(OR(A24="",LEFT(B24,LEN(A24)+1)<>A24&" "),"Start the name with its No. and a space, e.g. 21 Pool. ","")&IF(AND(A24<>"",COUNTIF(A$4:A$33,A24)>1),"Duplicate No. ",""))) | R24: =IF(B24="","",IFERROR(INDEX('Google Drive Map'!$B$4:$B$33,MATCH("04/"&LEFT(B24,2),'Google Drive Map'!$A$4:$A$33,0)),"04 Trades & Tenders/"&B24)) | S24: =IF(R24="","",IF(IFERROR(INDEX('Google Drive Map'!$G$4:$G$33,MATCH(R24,'Google Drive Map'!$B$4:$B$33,0))&"","")="","",HYPERLINK(INDEX('Google Drive Map'!$G$4:$G$33,MATCH(R24,'Google Drive Map'!$B$4:$B$33,0)),"Open")))
I25: =IF(OR($B25="",$A25=""),"",SUMIFS('Trades'!$T$4:$T$103,'Trades'!$A$4:$A$103,$A25&" *",'Trades'!$S$4:$S$103,"Yes")) | J25: =IF(OR($B25="",$A25=""),"",SUMIFS('Variations'!$G$4:$G$153,'Variations'!$C$4:$C$153,$A25&" *",'Variations'!$I$4:$I$153,"Approved")) | K25: =IF(B25="","",N(I25)+N(J25)) | L25: =IF(OR($B25="",$A25=""),"",SUMIFS('Payments'!$F$4:$F$303,'Payments'!$B$4:$B$303,$A25&" *",'Payments'!$K$4:$K$303,"Yes")) | N25: =IF(B25="","",IF(ISNUMBER(M25),M25,IF(N(K25)>0,K25,N(H25)))) | O25: =IF(OR(B25="",N(H25)=0),"",H25-N25) | P25: =IF(OR(B25="",N(H25)=0),"",IF(N25>H25*(1+Settings!$B$13),"Over budget","")) | Q25: =IF(B25="","",TRIM(IF(OR(A25="",LEFT(B25,LEN(A25)+1)<>A25&" "),"Start the name with its No. and a space, e.g. 21 Pool. ","")&IF(AND(A25<>"",COUNTIF(A$4:A$33,A25)>1),"Duplicate No. ",""))) | R25: =IF(B25="","",IFERROR(INDEX('Google Drive Map'!$B$4:$B$33,MATCH("04/"&LEFT(B25,2),'Google Drive Map'!$A$4:$A$33,0)),"04 Trades & Tenders/"&B25)) | S25: =IF(R25="","",IF(IFERROR(INDEX('Google Drive Map'!$G$4:$G$33,MATCH(R25,'Google Drive Map'!$B$4:$B$33,0))&"","")="","",HYPERLINK(INDEX('Google Drive Map'!$G$4:$G$33,MATCH(R25,'Google Drive Map'!$B$4:$B$33,0)),"Open")))
I26: =IF(OR($B26="",$A26=""),"",SUMIFS('Trades'!$T$4:$T$103,'Trades'!$A$4:$A$103,$A26&" *",'Trades'!$S$4:$S$103,"Yes")) | J26: =IF(OR($B26="",$A26=""),"",SUMIFS('Variations'!$G$4:$G$153,'Variations'!$C$4:$C$153,$A26&" *",'Variations'!$I$4:$I$153,"Approved")) | K26: =IF(B26="","",N(I26)+N(J26)) | L26: =IF(OR($B26="",$A26=""),"",SUMIFS('Payments'!$F$4:$F$303,'Payments'!$B$4:$B$303,$A26&" *",'Payments'!$K$4:$K$303,"Yes")) | N26: =IF(B26="","",IF(ISNUMBER(M26),M26,IF(N(K26)>0,K26,N(H26)))) | O26: =IF(OR(B26="",N(H26)=0),"",H26-N26) | P26: =IF(OR(B26="",N(H26)=0),"",IF(N26>H26*(1+Settings!$B$13),"Over budget","")) | Q26: =IF(B26="","",TRIM(IF(OR(A26="",LEFT(B26,LEN(A26)+1)<>A26&" "),"Start the name with its No. and a space, e.g. 21 Pool. ","")&IF(AND(A26<>"",COUNTIF(A$4:A$33,A26)>1),"Duplicate No. ",""))) | R26: =IF(B26="","",IFERROR(INDEX('Google Drive Map'!$B$4:$B$33,MATCH("04/"&LEFT(B26,2),'Google Drive Map'!$A$4:$A$33,0)),"04 Trades & Tenders/"&B26)) | S26: =IF(R26="","",IF(IFERROR(INDEX('Google Drive Map'!$G$4:$G$33,MATCH(R26,'Google Drive Map'!$B$4:$B$33,0))&"","")="","",HYPERLINK(INDEX('Google Drive Map'!$G$4:$G$33,MATCH(R26,'Google Drive Map'!$B$4:$B$33,0)),"Open")))
I27: =IF(OR($B27="",$A27=""),"",SUMIFS('Trades'!$T$4:$T$103,'Trades'!$A$4:$A$103,$A27&" *",'Trades'!$S$4:$S$103,"Yes")) | J27: =IF(OR($B27="",$A27=""),"",SUMIFS('Variations'!$G$4:$G$153,'Variations'!$C$4:$C$153,$A27&" *",'Variations'!$I$4:$I$153,"Approved")) | K27: =IF(B27="","",N(I27)+N(J27)) | L27: =IF(OR($B27="",$A27=""),"",SUMIFS('Payments'!$F$4:$F$303,'Payments'!$B$4:$B$303,$A27&" *",'Payments'!$K$4:$K$303,"Yes")) | N27: =IF(B27="","",IF(ISNUMBER(M27),M27,IF(N(K27)>0,K27,N(H27)))) | O27: =IF(OR(B27="",N(H27)=0),"",H27-N27) | P27: =IF(OR(B27="",N(H27)=0),"",IF(N27>H27*(1+Settings!$B$13),"Over budget","")) | Q27: =IF(B27="","",TRIM(IF(OR(A27="",LEFT(B27,LEN(A27)+1)<>A27&" "),"Start the name with its No. and a space, e.g. 21 Pool. ","")&IF(AND(A27<>"",COUNTIF(A$4:A$33,A27)>1),"Duplicate No. ",""))) | R27: =IF(B27="","",IFERROR(INDEX('Google Drive Map'!$B$4:$B$33,MATCH("04/"&LEFT(B27,2),'Google Drive Map'!$A$4:$A$33,0)),"04 Trades & Tenders/"&B27)) | S27: =IF(R27="","",IF(IFERROR(INDEX('Google Drive Map'!$G$4:$G$33,MATCH(R27,'Google Drive Map'!$B$4:$B$33,0))&"","")="","",HYPERLINK(INDEX('Google Drive Map'!$G$4:$G$33,MATCH(R27,'Google Drive Map'!$B$4:$B$33,0)),"Open")))
I28: =IF(OR($B28="",$A28=""),"",SUMIFS('Trades'!$T$4:$T$103,'Trades'!$A$4:$A$103,$A28&" *",'Trades'!$S$4:$S$103,"Yes")) | J28: =IF(OR($B28="",$A28=""),"",SUMIFS('Variations'!$G$4:$G$153,'Variations'!$C$4:$C$153,$A28&" *",'Variations'!$I$4:$I$153,"Approved")) | K28: =IF(B28="","",N(I28)+N(J28)) | L28: =IF(OR($B28="",$A28=""),"",SUMIFS('Payments'!$F$4:$F$303,'Payments'!$B$4:$B$303,$A28&" *",'Payments'!$K$4:$K$303,"Yes")) | N28: =IF(B28="","",IF(ISNUMBER(M28),M28,IF(N(K28)>0,K28,N(H28)))) | O28: =IF(OR(B28="",N(H28)=0),"",H28-N28) | P28: =IF(OR(B28="",N(H28)=0),"",IF(N28>H28*(1+Settings!$B$13),"Over budget","")) | Q28: =IF(B28="","",TRIM(IF(OR(A28="",LEFT(B28,LEN(A28)+1)<>A28&" "),"Start the name with its No. and a space, e.g. 21 Pool. ","")&IF(AND(A28<>"",COUNTIF(A$4:A$33,A28)>1),"Duplicate No. ",""))) | R28: =IF(B28="","",IFERROR(INDEX('Google Drive Map'!$B$4:$B$33,MATCH("04/"&LEFT(B28,2),'Google Drive Map'!$A$4:$A$33,0)),"04 Trades & Tenders/"&B28)) | S28: =IF(R28="","",IF(IFERROR(INDEX('Google Drive Map'!$G$4:$G$33,MATCH(R28,'Google Drive Map'!$B$4:$B$33,0))&"","")="","",HYPERLINK(INDEX('Google Drive Map'!$G$4:$G$33,MATCH(R28,'Google Drive Map'!$B$4:$B$33,0)),"Open")))
I29: =IF(OR($B29="",$A29=""),"",SUMIFS('Trades'!$T$4:$T$103,'Trades'!$A$4:$A$103,$A29&" *",'Trades'!$S$4:$S$103,"Yes")) | J29: =IF(OR($B29="",$A29=""),"",SUMIFS('Variations'!$G$4:$G$153,'Variations'!$C$4:$C$153,$A29&" *",'Variations'!$I$4:$I$153,"Approved")) | K29: =IF(B29="","",N(I29)+N(J29)) | L29: =IF(OR($B29="",$A29=""),"",SUMIFS('Payments'!$F$4:$F$303,'Payments'!$B$4:$B$303,$A29&" *",'Payments'!$K$4:$K$303,"Yes")) | N29: =IF(B29="","",IF(ISNUMBER(M29),M29,IF(N(K29)>0,K29,N(H29)))) | O29: =IF(OR(B29="",N(H29)=0),"",H29-N29) | P29: =IF(OR(B29="",N(H29)=0),"",IF(N29>H29*(1+Settings!$B$13),"Over budget","")) | Q29: =IF(B29="","",TRIM(IF(OR(A29="",LEFT(B29,LEN(A29)+1)<>A29&" "),"Start the name with its No. and a space, e.g. 21 Pool. ","")&IF(AND(A29<>"",COUNTIF(A$4:A$33,A29)>1),"Duplicate No. ",""))) | R29: =IF(B29="","",IFERROR(INDEX('Google Drive Map'!$B$4:$B$33,MATCH("04/"&LEFT(B29,2),'Google Drive Map'!$A$4:$A$33,0)),"04 Trades & Tenders/"&B29)) | S29: =IF(R29="","",IF(IFERROR(INDEX('Google Drive Map'!$G$4:$G$33,MATCH(R29,'Google Drive Map'!$B$4:$B$33,0))&"","")="","",HYPERLINK(INDEX('Google Drive Map'!$G$4:$G$33,MATCH(R29,'Google Drive Map'!$B$4:$B$33,0)),"Open")))
I30: =IF(OR($B30="",$A30=""),"",SUMIFS('Trades'!$T$4:$T$103,'Trades'!$A$4:$A$103,$A30&" *",'Trades'!$S$4:$S$103,"Yes")) | J30: =IF(OR($B30="",$A30=""),"",SUMIFS('Variations'!$G$4:$G$153,'Variations'!$C$4:$C$153,$A30&" *",'Variations'!$I$4:$I$153,"Approved")) | K30: =IF(B30="","",N(I30)+N(J30)) | L30: =IF(OR($B30="",$A30=""),"",SUMIFS('Payments'!$F$4:$F$303,'Payments'!$B$4:$B$303,$A30&" *",'Payments'!$K$4:$K$303,"Yes")) | N30: =IF(B30="","",IF(ISNUMBER(M30),M30,IF(N(K30)>0,K30,N(H30)))) | O30: =IF(OR(B30="",N(H30)=0),"",H30-N30) | P30: =IF(OR(B30="",N(H30)=0),"",IF(N30>H30*(1+Settings!$B$13),"Over budget","")) | Q30: =IF(B30="","",TRIM(IF(OR(A30="",LEFT(B30,LEN(A30)+1)<>A30&" "),"Start the name with its No. and a space, e.g. 21 Pool. ","")&IF(AND(A30<>"",COUNTIF(A$4:A$33,A30)>1),"Duplicate No. ",""))) | R30: =IF(B30="","",IFERROR(INDEX('Google Drive Map'!$B$4:$B$33,MATCH("04/"&LEFT(B30,2),'Google Drive Map'!$A$4:$A$33,0)),"04 Trades & Tenders/"&B30)) | S30: =IF(R30="","",IF(IFERROR(INDEX('Google Drive Map'!$G$4:$G$33,MATCH(R30,'Google Drive Map'!$B$4:$B$33,0))&"","")="","",HYPERLINK(INDEX('Google Drive Map'!$G$4:$G$33,MATCH(R30,'Google Drive Map'!$B$4:$B$33,0)),"Open")))
I31: =IF(OR($B31="",$A31=""),"",SUMIFS('Trades'!$T$4:$T$103,'Trades'!$A$4:$A$103,$A31&" *",'Trades'!$S$4:$S$103,"Yes")) | J31: =IF(OR($B31="",$A31=""),"",SUMIFS('Variations'!$G$4:$G$153,'Variations'!$C$4:$C$153,$A31&" *",'Variations'!$I$4:$I$153,"Approved")) | K31: =IF(B31="","",N(I31)+N(J31)) | L31: =IF(OR($B31="",$A31=""),"",SUMIFS('Payments'!$F$4:$F$303,'Payments'!$B$4:$B$303,$A31&" *",'Payments'!$K$4:$K$303,"Yes")) | N31: =IF(B31="","",IF(ISNUMBER(M31),M31,IF(N(K31)>0,K31,N(H31)))) | O31: =IF(OR(B31="",N(H31)=0),"",H31-N31) | P31: =IF(OR(B31="",N(H31)=0),"",IF(N31>H31*(1+Settings!$B$13),"Over budget","")) | Q31: =IF(B31="","",TRIM(IF(OR(A31="",LEFT(B31,LEN(A31)+1)<>A31&" "),"Start the name with its No. and a space, e.g. 21 Pool. ","")&IF(AND(A31<>"",COUNTIF(A$4:A$33,A31)>1),"Duplicate No. ",""))) | R31: =IF(B31="","",IFERROR(INDEX('Google Drive Map'!$B$4:$B$33,MATCH("04/"&LEFT(B31,2),'Google Drive Map'!$A$4:$A$33,0)),"04 Trades & Tenders/"&B31)) | S31: =IF(R31="","",IF(IFERROR(INDEX('Google Drive Map'!$G$4:$G$33,MATCH(R31,'Google Drive Map'!$B$4:$B$33,0))&"","")="","",HYPERLINK(INDEX('Google Drive Map'!$G$4:$G$33,MATCH(R31,'Google Drive Map'!$B$4:$B$33,0)),"Open")))
I32: =IF(OR($B32="",$A32=""),"",SUMIFS('Trades'!$T$4:$T$103,'Trades'!$A$4:$A$103,$A32&" *",'Trades'!$S$4:$S$103,"Yes")) | J32: =IF(OR($B32="",$A32=""),"",SUMIFS('Variations'!$G$4:$G$153,'Variations'!$C$4:$C$153,$A32&" *",'Variations'!$I$4:$I$153,"Approved")) | K32: =IF(B32="","",N(I32)+N(J32)) | L32: =IF(OR($B32="",$A32=""),"",SUMIFS('Payments'!$F$4:$F$303,'Payments'!$B$4:$B$303,$A32&" *",'Payments'!$K$4:$K$303,"Yes")) | N32: =IF(B32="","",IF(ISNUMBER(M32),M32,IF(N(K32)>0,K32,N(H32)))) | O32: =IF(OR(B32="",N(H32)=0),"",H32-N32) | P32: =IF(OR(B32="",N(H32)=0),"",IF(N32>H32*(1+Settings!$B$13),"Over budget","")) | Q32: =IF(B32="","",TRIM(IF(OR(A32="",LEFT(B32,LEN(A32)+1)<>A32&" "),"Start the name with its No. and a space, e.g. 21 Pool. ","")&IF(AND(A32<>"",COUNTIF(A$4:A$33,A32)>1),"Duplicate No. ",""))) | R32: =IF(B32="","",IFERROR(INDEX('Google Drive Map'!$B$4:$B$33,MATCH("04/"&LEFT(B32,2),'Google Drive Map'!$A$4:$A$33,0)),"04 Trades & Tenders/"&B32)) | S32: =IF(R32="","",IF(IFERROR(INDEX('Google Drive Map'!$G$4:$G$33,MATCH(R32,'Google Drive Map'!$B$4:$B$33,0))&"","")="","",HYPERLINK(INDEX('Google Drive Map'!$G$4:$G$33,MATCH(R32,'Google Drive Map'!$B$4:$B$33,0)),"Open")))
I33: =IF(OR($B33="",$A33=""),"",SUMIFS('Trades'!$T$4:$T$103,'Trades'!$A$4:$A$103,$A33&" *",'Trades'!$S$4:$S$103,"Yes")) | J33: =IF(OR($B33="",$A33=""),"",SUMIFS('Variations'!$G$4:$G$153,'Variations'!$C$4:$C$153,$A33&" *",'Variations'!$I$4:$I$153,"Approved")) | K33: =IF(B33="","",N(I33)+N(J33)) | L33: =IF(OR($B33="",$A33=""),"",SUMIFS('Payments'!$F$4:$F$303,'Payments'!$B$4:$B$303,$A33&" *",'Payments'!$K$4:$K$303,"Yes")) | N33: =IF(B33="","",IF(ISNUMBER(M33),M33,IF(N(K33)>0,K33,N(H33)))) | O33: =IF(OR(B33="",N(H33)=0),"",H33-N33) | P33: =IF(OR(B33="",N(H33)=0),"",IF(N33>H33*(1+Settings!$B$13),"Over budget","")) | Q33: =IF(B33="","",TRIM(IF(OR(A33="",LEFT(B33,LEN(A33)+1)<>A33&" "),"Start the name with its No. and a space, e.g. 21 Pool. ","")&IF(AND(A33<>"",COUNTIF(A$4:A$33,A33)>1),"Duplicate No. ",""))) | R33: =IF(B33="","",IFERROR(INDEX('Google Drive Map'!$B$4:$B$33,MATCH("04/"&LEFT(B33,2),'Google Drive Map'!$A$4:$A$33,0)),"04 Trades & Tenders/"&B33)) | S33: =IF(R33="","",IF(IFERROR(INDEX('Google Drive Map'!$G$4:$G$33,MATCH(R33,'Google Drive Map'!$B$4:$B$33,0))&"","")="","",HYPERLINK(INDEX('Google Drive Map'!$G$4:$G$33,MATCH(R33,'Google Drive Map'!$B$4:$B$33,0)),"Open")))

Sheet Trades
A1: Trade register
A2: Every trade you invite or engage. Licence and insurance dates turn amber before they expire (days set on Settings) and red once expired. Type dates as dates, e.g. 30/06/2027.
A3: Package | B3: Business name | C3: Contact | D3: Phone | E3: Email | F3: ABN | G3: GST registered? | H3: Licence / registration | I3: Licence no. | J3: Licence expiry | K3: Public liability insurer | L3: PL expiry | M3: WorkCover | N3: Home warranty cover (> $20k) | O3: SWMS received | P3: White cards checked | Q3: Status | R3: Contract type | S3: Contract signed? | T3: Contract value inc GST ($) | U3: Deposit ($) | V3: Deposit check | W3: Paperwork | X3: Contract checks | Y3: Drive folder | Z3: Folder | AA3: Notes
A4: 08 Roofing | B4: Ridgeline Metal Roofs | G4: Yes | H4: Roof plumbing licence | J4: 46568 | L4: 46477 | M4: Yes | N4: Yes | O4: Yes | P4: Yes | Q4: Engaged | R4: Supply & install | S4: Yes | T4: 36900 | U4: 1845 | V4: =IF(OR(N(T4)=0,N(U4)=0),"",IF(U4>T4*IF(T4<Settings!$B$5,Settings!$B$4,Settings!$B$6),"Over statutory cap","OK")) | W4: =IF(B4="","",IF(OR(AND(J4<>"",NOT(ISNUMBER(J4))),AND(L4<>"",NOT(ISNUMBER(L4)))),"Check date: typed as text",IF(OR(AND(ISNUMBER(J4),J4<TODAY()),AND(ISNUMBER(L4),L4<TODAY())),"Expired",IF(OR(AND(ISNUMBER(J4),J4-TODAY()<=Settings!$B$11),AND(ISNUMBER(L4),L4-TODAY()<=Settings!$B$11)),"Expires within "&Settings!$B$11&" days",IF(AND(OR(Q4="Engaged",S4="Yes"),OR(J4="",L4="")),"Missing expiry date","OK"))))) | X4: =IF(B4="","",TRIM(IF(COUNTIF(B$4:B$103,B4)>1,"Duplicate business name. ","")&IF(AND(N(T4)>Settings!$B$7,H4=""),"Over "&TEXT(Settings!$B$7,"$#,##0")&": record the builder registration (or exemption) and use a written major domestic building contract. ","")&IF(AND(N(T4)>Settings!$B$8,N4<>"Yes"),"Home warranty cover needed over "&TEXT(Settings!$B$8,"$#,##0")&". ",""))) | Y4: =IF(A4="","",IFERROR(INDEX('Google Drive Map'!$B$4:$B$33,MATCH("04/"&LEFT(A4,2),'Google Drive Map'!$A$4:$A$33,0)),"04 Trades & Tenders/"&A4)) | Z4: =IF(Y4="","",IF(IFERROR(INDEX('Google Drive Map'!$G$4:$G$33,MATCH(Y4,'Google Drive Map'!$B$4:$B$33,0))&"","")="","",HYPERLINK(INDEX('Google Drive Map'!$G$4:$G$33,MATCH(Y4,'Google Drive Map'!$B$4:$B$33,0)),"Open"))) | AA4: EXAMPLE: delete this row
V5: =IF(OR(N(T5)=0,N(U5)=0),"",IF(U5>T5*IF(T5<Settings!$B$5,Settings!$B$4,Settings!$B$6),"Over statutory cap","OK")) | W5: =IF(B5="","",IF(OR(AND(J5<>"",NOT(ISNUMBER(J5))),AND(L5<>"",NOT(ISNUMBER(L5)))),"Check date: typed as text",IF(OR(AND(ISNUMBER(J5),J5<TODAY()),AND(ISNUMBER(L5),L5<TODAY())),"Expired",IF(OR(AND(ISNUMBER(J5),J5-TODAY()<=Settings!$B$11),AND(ISNUMBER(L5),L5-TODAY()<=Settings!$B$11)),"Expires within "&Settings!$B$11&" days",IF(AND(OR(Q5="Engaged",S5="Yes"),OR(J5="",L5="")),"Missing expiry date","OK"))))) | X5: =IF(B5="","",TRIM(IF(COUNTIF(B$4:B$103,B5)>1,"Duplicate business name. ","")&IF(AND(N(T5)>Settings!$B$7,H5=""),"Over "&TEXT(Settings!$B$7,"$#,##0")&": record the builder registration (or exemption) and use a written major domestic building contract. ","")&IF(AND(N(T5)>Settings!$B$8,N5<>"Yes"),"Home warranty cover needed over "&TEXT(Settings!$B$8,"$#,##0")&". ",""))) | Y5: =IF(A5="","",IFERROR(INDEX('Google Drive Map'!$B$4:$B$33,MATCH("04/"&LEFT(A5,2),'Google Drive Map'!$A$4:$A$33,0)),"04 Trades & Tenders/"&A5)) | Z5: =IF(Y5="","",IF(IFERROR(INDEX('Google Drive Map'!$G$4:$G$33,MATCH(Y5,'Google Drive Map'!$B$4:$B$33,0))&"","")="","",HYPERLINK(INDEX('Google Drive Map'!$G$4:$G$33,MATCH(Y5,'Google Drive Map'!$B$4:$B$33,0)),"Open")))
V6: =IF(OR(N(T6)=0,N(U6)=0),"",IF(U6>T6*IF(T6<Settings!$B$5,Settings!$B$4,Settings!$B$6),"Over statutory cap","OK")) | W6: =IF(B6="","",IF(OR(AND(J6<>"",NOT(ISNUMBER(J6))),AND(L6<>"",NOT(ISNUMBER(L6)))),"Check date: typed as text",IF(OR(AND(ISNUMBER(J6),J6<TODAY()),AND(ISNUMBER(L6),L6<TODAY())),"Expired",IF(OR(AND(ISNUMBER(J6),J6-TODAY()<=Settings!$B$11),AND(ISNUMBER(L6),L6-TODAY()<=Settings!$B$11)),"Expires within "&Settings!$B$11&" days",IF(AND(OR(Q6="Engaged",S6="Yes"),OR(J6="",L6="")),"Missing expiry date","OK"))))) | X6: =IF(B6="","",TRIM(IF(COUNTIF(B$4:B$103,B6)>1,"Duplicate business name. ","")&IF(AND(N(T6)>Settings!$B$7,H6=""),"Over "&TEXT(Settings!$B$7,"$#,##0")&": record the builder registration (or exemption) and use a written major domestic building contract. ","")&IF(AND(N(T6)>Settings!$B$8,N6<>"Yes"),"Home warranty cover needed over "&TEXT(Settings!$B$8,"$#,##0")&". ",""))) | Y6: =IF(A6="","",IFERROR(INDEX('Google Drive Map'!$B$4:$B$33,MATCH("04/"&LEFT(A6,2),'Google Drive Map'!$A$4:$A$33,0)),"04 Trades & Tenders/"&A6)) | Z6: =IF(Y6="","",IF(IFERROR(INDEX('Google Drive Map'!$G$4:$G$33,MATCH(Y6,'Google Drive Map'!$B$4:$B$33,0))&"","")="","",HYPERLINK(INDEX('Google Drive Map'!$G$4:$G$33,MATCH(Y6,'Google Drive Map'!$B$4:$B$33,0)),"Open")))
